Workbook

Sheet Executive Dashboard
A1: EXECUTIVE DASHBOARD · S&OP one-page (₹ Cr)
A2: Honasa / Mamaearth · Modern Trade · rolling 3-month demand & supply view — recomputes from the Control Panel
A4: Scenario | D4: Forecast Window | G4: Selected 3M Forecast | J4: 3M Target
A5: ='Control Panel'!$B$5 | D5: ='Control Panel'!$B$4&" → "&'Control Panel'!$B$7 | G5: ='Forecast Engine'!$AT$13+'Forecast Engine'!$AU$13+'Forecast Engine'!$AV$13 | J5: =SUMIFS('Monthly Target Upload'!$D$4:$D$15,'Monthly Target Upload'!$A$4:$A$15,'Control Panel'!$B$4)+SUMIFS('Monthly Target Upload'!$D$4:$D$15,'Monthly Target Upload'!$A$4:$A$15,'Control Panel'!$B$6)+SUMIFS('Monthly Target Upload'!$D$4:$D$15,'Monthly Target Upload'!$A$4:$A$15,'Control Panel'!$B$7)
A7: =IFERROR("Target achievement: "&TEXT(('Forecast Engine'!$AT$13+'Forecast Engine'!$AU$13+'Forecast Engine'!$AV$13)/(SUMIFS('Monthly Target Upload'!$D$4:$D$15,'Monthly Target Upload'!$A$4:$A$15,'Control Panel'!$B$4)+SUMIFS('Monthly Target Upload'!$D$4:$D$15,'Monthly Target Upload'!$A$4:$A$15,'Control Panel'!$B$6)+SUMIFS('Monthly Target Upload'!$D$4:$D$15,'Monthly Target Upload'!$A$4:$A$15,'Control Panel'!$B$7)),"0.0%"),"—") | G7: ="Model accuracy (back-test): "&TEXT('Forecast Accuracy'!$B$21,"0.0%")&" · WMAPE "&TEXT('Forecast Accuracy'!$B$18,"0.0%")
A9: Brand Performance · Base 3-month forecast
A10: Brand | B10: M | C10: M+1 | D10: M+2 | E10: 3M Total | F10: % Mix
A11: Mamaearth | B11: =SUMIFS('Forecast Engine'!$AK$4:$AK$12,'Forecast Engine'!$A$4:$A$12,$A11) | C11: =SUMIFS('Forecast Engine'!$AL$4:$AL$12,'Forecast Engine'!$A$4:$A$12,$A11) | D11: =SUMIFS('Forecast Engine'!$AM$4:$AM$12,'Forecast Engine'!$A$4:$A$12,$A11) | E11: =SUM(B11:D11) | F11: =IFERROR(E11/SUM($E$11:$E$14),0)
A12: The Derma Co. | B12: =SUMIFS('Forecast Engine'!$AK$4:$AK$12,'Forecast Engine'!$A$4:$A$12,$A12) | C12: =SUMIFS('Forecast Engine'!$AL$4:$AL$12,'Forecast Engine'!$A$4:$A$12,$A12) | D12: =SUMIFS('Forecast Engine'!$AM$4:$AM$12,'Forecast Engine'!$A$4:$A$12,$A12) | E12: =SUM(B12:D12) | F12: =IFERROR(E12/SUM($E$11:$E$14),0)
A13: Aqualogica | B13: =SUMIFS('Forecast Engine'!$AK$4:$AK$12,'Forecast Engine'!$A$4:$A$12,$A13) | C13: =SUMIFS('Forecast Engine'!$AL$4:$AL$12,'Forecast Engine'!$A$4:$A$12,$A13) | D13: =SUMIFS('Forecast Engine'!$AM$4:$AM$12,'Forecast Engine'!$A$4:$A$12,$A13) | E13: =SUM(B13:D13) | F13: =IFERROR(E13/SUM($E$11:$E$14),0)
A14: BBLUNT | B14: =SUMIFS('Forecast Engine'!$AK$4:$AK$12,'Forecast Engine'!$A$4:$A$12,$A14) | C14: =SUMIFS('Forecast Engine'!$AL$4:$AL$12,'Forecast Engine'!$A$4:$A$12,$A14) | D14: =SUMIFS('Forecast Engine'!$AM$4:$AM$12,'Forecast Engine'!$A$4:$A$12,$A14) | E14: =SUM(B14:D14) | F14: =IFERROR(E14/SUM($E$11:$E$14),0)
A15: Total | B15: =SUM(B11:B14) | C15: =SUM(C11:C14) | D15: =SUM(D11:D14) | E15: =SUM(E11:E14)
A17: Quick links
A18: → Scenario Summary | E18: → Forecast Plan Article-Chain | I18: → Business_Event_Master
A19: → Event Impact Dashboard | E19: → Event Simulator | I19: → Target Distribution
A20: → Warehouse Optimization | E20: → Forecast Accuracy | I20: → AI Business Insights
A21: → Demand Planner Workbench

Sheet Control Panel
A1: CONTROL PANEL · every blue cell drives the rolling forecast
A2: 1 · Forecast Horizon (rolling)
A3: Last Actual Month (data closed through) | B3: May'26 | C3: set to the latest month present in Primary Sales History
A4: Forecast Month (M) | B4: Jun'26 | C4: first month to forecast; advance one month each cycle
A5: Business Scenario (drives 'Selected' columns) | B5: Base
A6: Forecast Month (M+1) | B6: =INDEX(Calendar!$B$3:$B$38,MATCH($B$4,Calendar!$B$3:$B$38,0)+1)
A7: Forecast Month (M+2) | B7: =INDEX(Calendar!$B$3:$B$38,MATCH($B$4,Calendar!$B$3:$B$38,0)+2)
A8: Idx · Last Actual | B8: =MATCH('Control Panel'!$B$3,Calendar!$B$3:$B$38,0)
A9: Idx · M | B9: =MATCH('Control Panel'!$B$4,Calendar!$B$3:$B$38,0)
A10: Idx · M+1 | B10: =MATCH('Control Panel'!$B$6,Calendar!$B$3:$B$38,0)
A11: Idx · M+2 | B11: =MATCH('Control Panel'!$B$7,Calendar!$B$3:$B$38,0)
A12: Month Name · M | B12: =INDEX(Calendar!$C$3:$C$38,'Control Panel'!$B$9)
A13: Month Name · M+1 | B13: =INDEX(Calendar!$C$3:$C$38,'Control Panel'!$B$10)
A14: Month Name · M+2 | B14: =INDEX(Calendar!$C$3:$C$38,'Control Panel'!$B$11)
A16: 2 · Statistical Method Weights (auto-normalised)
A17: WMA (weighted moving avg) | B17: 0.2
A18: Exponential Smoothing | B18: 0.2
A19: Linear Trend | B19: 0.15
A20: Seasonal Index | B20: 0.15
A21: CAGR | B21: 0.1
A22: Rolling Average | B22: 0.1
A23: YoY Growth | B23: 0.1
A24: Sum of method weights | B24: =SUM(B17:B23)
A26: 3 · Method Parameters
A27: Exponential Smoothing α | B27: 0.4 | C27: higher = more weight on recent months
A28: WMA weight · latest month | B28: 0.5
A29: WMA weight · 2nd month | B29: 0.3
A30: WMA weight · 3rd month | B30: 0.2
A32: 4 · AI Ensemble Blend (Statistical + Business + Drivers)
A33: Weight · Statistical | B33: 0.5
A34: Weight · Business | B34: 0.3
A35: Weight · Driver-adjusted | B35: 0.2
A36: Momentum cap (±) | B36: 0.15 | C36: limits brand-momentum driver
A38: 5 · Scenario Multipliers
A39: Base | B39: 1
A40: Optimistic | B40: 1.08
A41: Conservative | B41: 0.92
A42: Selected multiplier | B42: =IF('Control Panel'!$B$5="Optimistic",'Control Panel'!$B$40,IF('Control Panel'!$B$5="Conservative",'Control Panel'!$B$41,'Control Panel'!$B$39))
A44: 6 · Business Forecast Defaults
A45: Default business adjustment % | B45: 0.05 | C45: applied when a series has no explicit override
A47: 7 · Forecast Accuracy Settings
A48: Back-test window (months) | B48: 6
A49: Tracking-signal alert limit (±) | B49: 4
A50: Accuracy target % | B50: 0.8
A52: 8 · Warehouse Capacity (₹ Cr dispatch / month)
A53: Gurgaon | B53: 60
A54: Mumbai | B54: 55
A55: Bangalore | B55: 45
A56: Kolkata | B56: 25

Sheet Forecast Engine
A1: FORECAST ENGINE · rolling 3-month statistical + business + AI ensemble (₹ Cr)
A2: Every value is a formula off the Control Panel. Monthly matrix (right) is pulled from Primary Sales History via SUMIFS; helper columns extract the rolling window; the 7 methods blend into Statistical → Business → AI → scenarios. See Documentation for maths.
A3: Brand | B3: Category | C3: Seas Cat | D3: M-1 | E3: M-2 | F3: M-3 | G3: M-6 | H3: M-12 | I3: Avg3 | J3: Avg6 | K3: Avg12 | L3: Momentum | M3: Trend/mo | N3: CAGR/mo | O3: Seas·M | P3: Seas·M+1 | Q3: Seas·M+2 | R3: SMLY·M | S3: SMLY·M+1 | T3: SMLY·M+2 | U3: Biz Adj % | V3: Promo1 | W3: Promo2 | X3: Promo3 | Y3: NPI1 | Z3: NPI2 | AA3: NPI3 | AB3: Stat·M | AC3: Stat·M+1 | AD3: Stat·M+2 | AE3: Biz·M | AF3: Biz·M+1 | AG3: Biz·M+2 | AH3: AI·M | AI3: AI·M+1 | AJ3: AI·M+2 | AK3: Base·M | AL3: Base·M+1 | AM3: Base·M+2 | AN3: Opt·M | AO3: Opt·M+1 | AP3: Opt·M+2 | AQ3: Cons·M | AR3: Cons·M+1 | AS3: Cons·M+2 | AT3: Sel·M | AU3: Sel·M+1 | AV3: Sel·M+2 | AW3: Apr'25 | AX3: May'25 | AY3: Jun'25 | AZ3: Jul'25 | BA3: Aug'25 | BB3: Sep'25 | BC3: Oct'25 | BD3: Nov'25 | BE3: Dec'25 | BF3: Jan'25 | BG3: Feb'25 | BH3: Mar'25 | BI3: Apr'26 | BJ3: May'26 | BK3: Jun'26 | BL3: Jul'26 | BM3: Aug'26 | BN3: Sep'26 | BO3: Oct'26 | BP3: Nov'26 | BQ3: Dec'26 | BR3: Jan'26 | BS3: Feb'26 | BT3: Mar'26
A4: Mamaearth | B4: Face | C4: Face | D4: =IFERROR(INDEX($AW4:$BT4,1,'Control Panel'!$B$8-0),0) | E4: =IFERROR(INDEX($AW4:$BT4,1,'Control Panel'!$B$8-1),0) | F4: =IFERROR(INDEX($AW4:$BT4,1,'Control Panel'!$B$8-2),0) | G4: =IFERROR(INDEX($AW4:$BT4,1,'Control Panel'!$B$8-5),0) | H4: =IFERROR(INDEX($AW4:$BT4,1,'Control Panel'!$B$8-11),0) | I4: =AVERAGE(D4,E4,F4) | J4: =(D4+E4+F4+IFERROR(INDEX($AW4:$BT4,1,'Control Panel'!$B$8-3),0)+IFERROR(INDEX($AW4:$BT4,1,'Control Panel'!$B$8-4),0)+G4)/6 | K4: =(IFERROR(INDEX($AW4:$BT4,1,'Control Panel'!$B$8-0),0)+IFERROR(INDEX($AW4:$BT4,1,'Control Panel'!$B$8-1),0)+IFERROR(INDEX($AW4:$BT4,1,'Control Panel'!$B$8-2),0)+IFERROR(INDEX($AW4:$BT4,1,'Control Panel'!$B$8-3),0)+IFERROR(INDEX($AW4:$BT4,1,'Control Panel'!$B$8-4),0)+IFERROR(INDEX($AW4:$BT4,1,'Control Panel'!$B$8-5),0)+IFERROR(INDEX($AW4:$BT4,1,'Control Panel'!$B$8-6),0)+IFERROR(INDEX($AW4:$BT4,1,'Control Panel'!$B$8-7),0)+IFERROR(INDEX($AW4:$BT4,1,'Control Panel'!$B$8-8),0)+IFERROR(INDEX($AW4:$BT4,1,'Control Panel'!$B$8-9),0)+IFERROR(INDEX($AW4:$BT4,1,'Control Panel'!$B$8-10),0)+IFERROR(INDEX($AW4:$BT4,1,'Control Panel'!$B$8-11),0))/12 | L4: =IFERROR(MAX(-'Control Panel'!$B$36,MIN('Control Panel'!$B$36,(I4-J4)/J4)),0) | M4: =(D4-G4)/5 | N4: =IFERROR(IF(H4>0,(D4/H4)^(1/12)-1,0),0) | O4: =IFERROR((IFERROR(INDEX('Seasonality Matrix'!$B$4:$M$11,MATCH($C4,'Seasonality Matrix'!$A$4:$A$11,0),MATCH('Control Panel'!$B$12,'Seasonality Matrix'!$B$3:$M$3,0)),1))/(IFERROR(AVERAGE(INDEX('Seasonality Matrix'!$B$4:$M$11,MATCH($C4,'Seasonality Matrix'!$A$4:$A$11,0),0)),1)),1) | P4: =IFERROR((IFERROR(INDEX('Seasonality Matrix'!$B$4:$M$11,MATCH($C4,'Seasonality Matrix'!$A$4:$A$11,0),MATCH('Control Panel'!$B$13,'Seasonality Matrix'!$B$3:$M$3,0)),1))/(IFERROR(AVERAGE(INDEX('Seasonality Matrix'!$B$4:$M$11,MATCH($C4,'Seasonality Matrix'!$A$4:$A$11,0),0)),1)),1) | Q4: =IFERROR((IFERROR(INDEX('Seasonality Matrix'!$B$4:$M$11,MATCH($C4,'Seasonality Matrix'!$A$4:$A$11,0),MATCH('Control Panel'!$B$14,'Seasonality Matrix'!$B$3:$M$3,0)),1))/(IFERROR(AVERAGE(INDEX('Seasonality Matrix'!$B$4:$M$11,MATCH($C4,'Seasonality Matrix'!$A$4:$A$11,0),0)),1)),1) | R4: =IFERROR(INDEX($AW4:$BT4,1,'Control Panel'!$B$9-12),0) | S4: =IFERROR(INDEX($AW4:$BT4,1,'Control Panel'!$B$10-12),0) | T4: =IFERROR(INDEX($AW4:$BT4,1,'Control Panel'!$B$11-12),0) | U4: ='Control Panel'!$B$45 | V4: =IFERROR(SUMIFS('Promotion Calendar'!$G$4:$G$12,'Promotion Calendar'!$A$4:$A$12,$A4,'Promotion Calendar'!$B$4:$B$12,$B4,'Promotion Calendar'!$C$4:$C$12,'Control Panel'!$B$4),0) | W4: =IFERROR(SUMIFS('Promotion Calendar'!$G$4:$G$12,'Promotion Calendar'!$A$4:$A$12,$A4,'Promotion Calendar'!$B$4:$B$12,$B4,'Promotion Calendar'!$C$4:$C$12,'Control Panel'!$B$6),0) | X4: =IFERROR(SUMIFS('Promotion Calendar'!$G$4:$G$12,'Promotion Calendar'!$A$4:$A$12,$A4,'Promotion Calendar'!$B$4:$B$12,$B4,'Promotion Calendar'!$C$4:$C$12,'Control Panel'!$B$7),0) | Y4: =IFERROR(SUMIFS('NPI & EPD Planning'!$I$4:$I$10,'NPI & EPD Planning'!$A$4:$A$10,$A4,'NPI & EPD Planning'!$B$4:$B$10,$B4,'NPI & EPD Planning'!$D$4:$D$10,'Control Panel'!$B$4),0) | Z4: =IFERROR(SUMIFS('NPI & EPD Planning'!$I$4:$I$10,'NPI & EPD Planning'!$A$4:$A$10,$A4,'NPI & EPD Planning'!$B$4:$B$10,$B4,'NPI & EPD Planning'!$D$4:$D$10,'Control Panel'!$B$6),0) | AA4: =IFERROR(SUMIFS('NPI & EPD Planning'!$I$4:$I$10,'NPI & EPD Planning'!$A$4:$A$10,$A4,'NPI & EPD Planning'!$B$4:$B$10,$B4,'NPI & EPD Planning'!$D$4:$D$10,'Control Panel'!$B$7),0) | AB4: =IFERROR(('Control Panel'!$B$17*(('Control Panel'!$B$28*D4+'Control Panel'!$B$29*E4+'Control Panel'!$B$30*F4)*O4)+'Control Panel'!$B$18*((('Control Panel'!$B$27*(1-'Control Panel'!$B$27)^0*IFERROR(INDEX($AW4:$BT4,1,'Control Panel'!$B$8-0),0)+'Control Panel'!$B$27*(1-'Control Panel'!$B$27)^1*IFERROR(INDEX($AW4:$BT4,1,'Control Panel'!$B$8-1),0)+'Control Panel'!$B$27*(1-'Control Panel'!$B$27)^2*IFERROR(INDEX($AW4:$BT4,1,'Control Panel'!$B$8-2),0)+'Control Panel'!$B$27*(1-'Control Panel'!$B$27)^3*IFERROR(INDEX($AW4:$BT4,1,'Control Panel'!$B$8-3),0)+'Control Panel'!$B$27*(1-'Control Panel'!$B$27)^4*IFERROR(INDEX($AW4:$BT4,1,'Control Panel'!$B$8-4),0)+'Control Panel'!$B$27*(1-'Control Panel'!$B$27)^5*IFERROR(INDEX($AW4:$BT4,1,'Control Panel'!$B$8-5),0))/(1-(1-'Control Panel'!$B$27)^6))*O4)+'Control Panel'!$B$19*((D4+M4*1)*O4)+'Control Panel'!$B$20*(K4*O4)+'Control Panel'!$B$21*(D4*(1+N4)^1*O4)+'Control Panel'!$B$22*(I4*O4)+'Control Panel'!$B$23*(R4*(1+IFERROR(D4/H4-1,0))))/'Control Panel'!$B$24,0) | AC4: =IFERROR(('Control Panel'!$B$17*(('Control Panel'!$B$28*D4+'Control Panel'!$B$29*E4+'Control Panel'!$B$30*F4)*P4)+'Control Panel'!$B$18*((('Control Panel'!$B$27*(1-'Control Panel'!$B$27)^0*IFERROR(INDEX($AW4:$BT4,1,'Control Panel'!$B$8-0),0)+'Control Panel'!$B$27*(1-'Control Panel'!$B$27)^1*IFERROR(INDEX($AW4:$BT4,1,'Control Panel'!$B$8-1),0)+'Control Panel'!$B$27*(1-'Control Panel'!$B$27)^2*IFERROR(INDEX($AW4:$BT4,1,'Control Panel'!$B$8-2),0)+'Control Panel'!$B$27*(1-'Control Panel'!$B$27)^3*IFERROR(INDEX($AW4:$BT4,1,'Control Panel'!$B$8-3),0)+'Control Panel'!$B$27*(1-'Control Panel'!$B$27)^4*IFERROR(INDEX($AW4:$BT4,1,'Control Panel'!$B$8-4),0)+'Control Panel'!$B$27*(1-'Control Panel'!$B$27)^5*IFERROR(INDEX($AW4:$BT4,1,'Control Panel'!$B$8-5),0))/(1-(1-'Control Panel'!$B$27)^6))*P4)+'Control Panel'!$B$19*((D4+M4*2)*P4)+'Control Panel'!$B$20*(K4*P4)+'Control Panel'!$B$21*(D4*(1+N4)^2*P4)+'Control Panel'!$B$22*(I4*P4)+'Control Panel'!$B$23*(S4*(1+IFERROR(D4/H4-1,0))))/'Control Panel'!$B$24,0) | AD4: =IFERROR(('Control Panel'!$B$17*(('Control Panel'!$B$28*D4+'Control Panel'!$B$29*E4+'Control Panel'!$B$30*F4)*Q4)+'Control Panel'!$B$18*((('Control Panel'!$B$27*(1-'Control Panel'!$B$27)^0*IFERROR(INDEX($AW4:$BT4,1,'Control Panel'!$B$8-0),0)+'Control Panel'!$B$27*(1-'Control Panel'!$B$27)^1*IFERROR(INDEX($AW4:$BT4,1,'Control Panel'!$B$8-1),0)+'Control Panel'!$B$27*(1-'Control Panel'!$B$27)^2*IFERROR(INDEX($AW4:$BT4,1,'Control Panel'!$B$8-2),0)+'Control Panel'!$B$27*(1-'Control Panel'!$B$27)^3*IFERROR(INDEX($AW4:$BT4,1,'Control Panel'!$B$8-3),0)+'Control Panel'!$B$27*(1-'Control Panel'!$B$27)^4*IFERROR(INDEX($AW4:$BT4,1,'Control Panel'!$B$8-4),0)+'Control Panel'!$B$27*(1-'Control Panel'!$B$27)^5*IFERROR(INDEX($AW4:$BT4,1,'Control Panel'!$B$8-5),0))/(1-(1-'Control Panel'!$B$27)^6))*Q4)+'Control Panel'!$B$19*((D4+M4*3)*Q4)+'Control Panel'!$B$20*(K4*Q4)+'Control Panel'!$B$21*(D4*(1+N4)^3*Q4)+'Control Panel'!$B$22*(I4*Q4)+'Control Panel'!$B$23*(T4*(1+IFERROR(D4/H4-1,0))))/'Control Panel'!$B$24,0) | AE4: =MAX(0,AB4*(1+U4+V4)) | AF4: =MAX(0,AC4*(1+U4+W4)) | AG4: =MAX(0,AD4*(1+U4+X4)) | AH4: =IFERROR(('Control Panel'!$B$33*AB4+'Control Panel'!$B$34*AE4+'Control Panel'!$B$35*(AB4*(1+L4+V4)))/('Control Panel'!$B$33+'Control Panel'!$B$34+'Control Panel'!$B$35),0) | AI4: =IFERROR(('Control Panel'!$B$33*AC4+'Control Panel'!$B$34*AF4+'Control Panel'!$B$35*(AC4*(1+L4+W4)))/('Control Panel'!$B$33+'Control Panel'!$B$34+'Control Panel'!$B$35),0) | AJ4: =IFERROR(('Control Panel'!$B$33*AD4+'Control Panel'!$B$34*AG4+'Control Panel'!$B$35*(AD4*(1+L4+X4)))/('Control Panel'!$B$33+'Control Panel'!$B$34+'Control Panel'!$B$35),0) | AK4: =AH4*'Control Panel'!$B$39+Y4 | AL4: =AI4*'Control Panel'!$B$39+Z4 | AM4: =AJ4*'Control Panel'!$B$39+AA4 | AN4: =AH4*'Control Panel'!$B$40+Y4 | AO4: =AI4*'Control Panel'!$B$40+Z4 | AP4: =AJ4*'Control Panel'!$B$40+AA4 | AQ4: =AH4*'Control Panel'!$B$41+Y4 | AR4: =AI4*'Control Panel'!$B$41+Z4 | AS4: =AJ4*'Control Panel'!$B$41+AA4 | AT4: =AH4*'Control Panel'!$B$42+Y4 | AU4: =AI4*'Control Panel'!$B$42+Z4 | AV4: =AJ4*'Control Panel'!$B$42+AA4 | AW4: =SUMIFS('Primary Sales History'!$C$4:$C$33,'Primary Sales History'!$A$4:$A$33,$A4,'Primary Sales History'!$B$4:$B$33,$B4) | AX4: =SUMIFS('Primary Sales History'!$D$4:$D$33,'Primary Sales History'!$A$4:$A$33,$A4,'Primary Sales History'!$B$4:$B$33,$B4) | AY4: =SUMIFS('Primary Sales History'!$E$4:$E$33,'Primary Sales History'!$A$4:$A$33,$A4,'Primary Sales History'!$B$4:$B$33,$B4) | AZ4: =SUMIFS('Primary Sales History'!$F$4:$F$33,'Primary Sales History'!$A$4:$A$33,$A4,'Primary Sales History'!$B$4:$B$33,$B4) | BA4: =SUMIFS('Primary Sales History'!$G$4:$G$33,'Primary Sales History'!$A$4:$A$33,$A4,'Primary Sales History'!$B$4:$B$33,$B4) | BB4: =SUMIFS('Primary Sales History'!$H$4:$H$33,'Primary Sales History'!$A$4:$A$33,$A4,'Primary Sales History'!$B$4:$B$33,$B4) | BC4: =SUMIFS('Primary Sales History'!$I$4:$I$33,'Primary Sales History'!$A$4:$A$33,$A4,'Primary Sales History'!$B$4:$B$33,$B4) | BD4: =SUMIFS('Primary Sales History'!$J$4:$J$33,'Primary Sales History'!$A$4:$A$33,$A4,'Primary Sales History'!$B$4:$B$33,$B4) | BE4: =SUMIFS('Primary Sales History'!$K$4:$K$33,'Primary Sales History'!$A$4:$A$33,$A4,'Primary Sales History'!$B$4:$B$33,$B4) | BF4: =SUMIFS('Primary Sales History'!$L$4:$L$33,'Primary Sales History'!$A$4:$A$33,$A4,'Primary Sales History'!$B$4:$B$33,$B4) | BG4: =SUMIFS('Primary Sales History'!$M$4:$M$33,'Primary Sales History'!$A$4:$A$33,$A4,'Primary Sales History'!$B$4:$B$33,$B4) | BH4: =SUMIFS('Primary Sales History'!$N$4:$N$33,'Primary Sales History'!$A$4:$A$33,$A4,'Primary Sales History'!$B$4:$B$33,$B4) | BI4: =SUMIFS('Primary Sales History'!$O$4:$O$33,'Primary Sales History'!$A$4:$A$33,$A4,'Primary Sales History'!$B$4:$B$33,$B4) | BJ4: =SUMIFS('Primary Sales History'!$P$4:$P$33,'Primary Sales History'!$A$4:$A$33,$A4,'Primary Sales History'!$B$4:$B$33,$B4) | BK4: 0 | BL4: 0 | BM4: 0 | BN4: 0 | BO4: 0 | BP4: 0 | BQ4: 0 | BR4: 0 | BS4: 0 | BT4: 0
A5: Mamaearth | B5: Hair | C5: Hair | D5: =IFERROR(INDEX($AW5:$BT5,1,'Control Panel'!$B$8-0),0) | E5: =IFERROR(INDEX($AW5:$BT5,1,'Control Panel'!$B$8-1),0) | F5: =IFERROR(INDEX($AW5:$BT5,1,'Control Panel'!$B$8-2),0) | G5: =IFERROR(INDEX($AW5:$BT5,1,'Control Panel'!$B$8-5),0) | H5: =IFERROR(INDEX($AW5:$BT5,1,'Control Panel'!$B$8-11),0) | I5: =AVERAGE(D5,E5,F5) | J5: =(D5+E5+F5+IFERROR(INDEX($AW5:$BT5,1,'Control Panel'!$B$8-3),0)+IFERROR(INDEX($AW5:$BT5,1,'Control Panel'!$B$8-4),0)+G5)/6 | K5: =(IFERROR(INDEX($AW5:$BT5,1,'Control Panel'!$B$8-0),0)+IFERROR(INDEX($AW5:$BT5,1,'Control Panel'!$B$8-1),0)+IFERROR(INDEX($AW5:$BT5,1,'Control Panel'!$B$8-2),0)+IFERROR(INDEX($AW5:$BT5,1,'Control Panel'!$B$8-3),0)+IFERROR(INDEX($AW5:$BT5,1,'Control Panel'!$B$8-4),0)+IFERROR(INDEX($AW5:$BT5,1,'Control Panel'!$B$8-5),0)+IFERROR(INDEX($AW5:$BT5,1,'Control Panel'!$B$8-6),0)+IFERROR(INDEX($AW5:$BT5,1,'Control Panel'!$B$8-7),0)+IFERROR(INDEX($AW5:$BT5,1,'Control Panel'!$B$8-8),0)+IFERROR(INDEX($AW5:$BT5,1,'Control Panel'!$B$8-9),0)+IFERROR(INDEX($AW5:$BT5,1,'Control Panel'!$B$8-10),0)+IFERROR(INDEX($AW5:$BT5,1,'Control Panel'!$B$8-11),0))/12 | L5: =IFERROR(MAX(-'Control Panel'!$B$36,MIN('Control Panel'!$B$36,(I5-J5)/J5)),0) | M5: =(D5-G5)/5 | N5: =IFERROR(IF(H5>0,(D5/H5)^(1/12)-1,0),0) | O5: =IFERROR((IFERROR(INDEX('Seasonality Matrix'!$B$4:$M$11,MATCH($C5,'Seasonality Matrix'!$A$4:$A$11,0),MATCH('Control Panel'!$B$12,'Seasonality Matrix'!$B$3:$M$3,0)),1))/(IFERROR(AVERAGE(INDEX('Seasonality Matrix'!$B$4:$M$11,MATCH($C5,'Seasonality Matrix'!$A$4:$A$11,0),0)),1)),1) | P5: =IFERROR((IFERROR(INDEX('Seasonality Matrix'!$B$4:$M$11,MATCH($C5,'Seasonality Matrix'!$A$4:$A$11,0),MATCH('Control Panel'!$B$13,'Seasonality Matrix'!$B$3:$M$3,0)),1))/(IFERROR(AVERAGE(INDEX('Seasonality Matrix'!$B$4:$M$11,MATCH($C5,'Seasonality Matrix'!$A$4:$A$11,0),0)),1)),1) | Q5: =IFERROR((IFERROR(INDEX('Seasonality Matrix'!$B$4:$M$11,MATCH($C5,'Seasonality Matrix'!$A$4:$A$11,0),MATCH('Control Panel'!$B$14,'Seasonality Matrix'!$B$3:$M$3,0)),1))/(IFERROR(AVERAGE(INDEX('Seasonality Matrix'!$B$4:$M$11,MATCH($C5,'Seasonality Matrix'!$A$4:$A$11,0),0)),1)),1) | R5: =IFERROR(INDEX($AW5:$BT5,1,'Control Panel'!$B$9-12),0) | S5: =IFERROR(INDEX($AW5:$BT5,1,'Control Panel'!$B$10-12),0) | T5: =IFERROR(INDEX($AW5:$BT5,1,'Control Panel'!$B$11-12),0) | U5: ='Control Panel'!$B$45 | V5: =IFERROR(SUMIFS('Promotion Calendar'!$G$4:$G$12,'Promotion Calendar'!$A$4:$A$12,$A5,'Promotion Calendar'!$B$4:$B$12,$B5,'Promotion Calendar'!$C$4:$C$12,'Control Panel'!$B$4),0) | W5: =IFERROR(SUMIFS('Promotion Calendar'!$G$4:$G$12,'Promotion Calendar'!$A$4:$A$12,$A5,'Promotion Calendar'!$B$4:$B$12,$B5,'Promotion Calendar'!$C$4:$C$12,'Control Panel'!$B$6),0) | X5: =IFERROR(SUMIFS('Promotion Calendar'!$G$4:$G$12,'Promotion Calendar'!$A$4:$A$12,$A5,'Promotion Calendar'!$B$4:$B$12,$B5,'Promotion Calendar'!$C$4:$C$12,'Control Panel'!$B$7),0) | Y5: =IFERROR(SUMIFS('NPI & EPD Planning'!$I$4:$I$10,'NPI & EPD Planning'!$A$4:$A$10,$A5,'NPI & EPD Planning'!$B$4:$B$10,$B5,'NPI & EPD Planning'!$D$4:$D$10,'Control Panel'!$B$4),0) | Z5: =IFERROR(SUMIFS('NPI & EPD Planning'!$I$4:$I$10,'NPI & EPD Planning'!$A$4:$A$10,$A5,'NPI & EPD Planning'!$B$4:$B$10,$B5,'NPI & EPD Planning'!$D$4:$D$10,'Control Panel'!$B$6),0) | AA5: =IFERROR(SUMIFS('NPI & EPD Planning'!$I$4:$I$10,'NPI & EPD Planning'!$A$4:$A$10,$A5,'NPI & EPD Planning'!$B$4:$B$10,$B5,'NPI & EPD Planning'!$D$4:$D$10,'Control Panel'!$B$7),0) | AB5: =IFERROR(('Control Panel'!$B$17*(('Control Panel'!$B$28*D5+'Control Panel'!$B$29*E5+'Control Panel'!$B$30*F5)*O5)+'Control Panel'!$B$18*((('Control Panel'!$B$27*(1-'Control Panel'!$B$27)^0*IFERROR(INDEX($AW5:$BT5,1,'Control Panel'!$B$8-0),0)+'Control Panel'!$B$27*(1-'Control Panel'!$B$27)^1*IFERROR(INDEX($AW5:$BT5,1,'Control Panel'!$B$8-1),0)+'Control Panel'!$B$27*(1-'Control Panel'!$B$27)^2*IFERROR(INDEX($AW5:$BT5,1,'Control Panel'!$B$8-2),0)+'Control Panel'!$B$27*(1-'Control Panel'!$B$27)^3*IFERROR(INDEX($AW5:$BT5,1,'Control Panel'!$B$8-3),0)+'Control Panel'!$B$27*(1-'Control Panel'!$B$27)^4*IFERROR(INDEX($AW5:$BT5,1,'Control Panel'!$B$8-4),0)+'Control Panel'!$B$27*(1-'Control Panel'!$B$27)^5*IFERROR(INDEX($AW5:$BT5,1,'Control Panel'!$B$8-5),0))/(1-(1-'Control Panel'!$B$27)^6))*O5)+'Control Panel'!$B$19*((D5+M5*1)*O5)+'Control Panel'!$B$20*(K5*O5)+'Control Panel'!$B$21*(D5*(1+N5)^1*O5)+'Control Panel'!$B$22*(I5*O5)+'Control Panel'!$B$23*(R5*(1+IFERROR(D5/H5-1,0))))/'Control Panel'!$B$24,0) | AC5: =IFERROR(('Control Panel'!$B$17*(('Control Panel'!$B$28*D5+'Control Panel'!$B$29*E5+'Control Panel'!$B$30*F5)*P5)+'Control Panel'!$B$18*((('Control Panel'!$B$27*(1-'Control Panel'!$B$27)^0*IFERROR(INDEX($AW5:$BT5,1,'Control Panel'!$B$8-0),0)+'Control Panel'!$B$27*(1-'Control Panel'!$B$27)^1*IFERROR(INDEX($AW5:$BT5,1,'Control Panel'!$B$8-1),0)+'Control Panel'!$B$27*(1-'Control Panel'!$B$27)^2*IFERROR(INDEX($AW5:$BT5,1,'Control Panel'!$B$8-2),0)+'Control Panel'!$B$27*(1-'Control Panel'!$B$27)^3*IFERROR(INDEX($AW5:$BT5,1,'Control Panel'!$B$8-3),0)+'Control Panel'!$B$27*(1-'Control Panel'!$B$27)^4*IFERROR(INDEX($AW5:$BT5,1,'Control Panel'!$B$8-4),0)+'Control Panel'!$B$27*(1-'Control Panel'!$B$27)^5*IFERROR(INDEX($AW5:$BT5,1,'Control Panel'!$B$8-5),0))/(1-(1-'Control Panel'!$B$27)^6))*P5)+'Control Panel'!$B$19*((D5+M5*2)*P5)+'Control Panel'!$B$20*(K5*P5)+'Control Panel'!$B$21*(D5*(1+N5)^2*P5)+'Control Panel'!$B$22*(I5*P5)+'Control Panel'!$B$23*(S5*(1+IFERROR(D5/H5-1,0))))/'Control Panel'!$B$24,0) | AD5: =IFERROR(('Control Panel'!$B$17*(('Control Panel'!$B$28*D5+'Control Panel'!$B$29*E5+'Control Panel'!$B$30*F5)*Q5)+'Control Panel'!$B$18*((('Control Panel'!$B$27*(1-'Control Panel'!$B$27)^0*IFERROR(INDEX($AW5:$BT5,1,'Control Panel'!$B$8-0),0)+'Control Panel'!$B$27*(1-'Control Panel'!$B$27)^1*IFERROR(INDEX($AW5:$BT5,1,'Control Panel'!$B$8-1),0)+'Control Panel'!$B$27*(1-'Control Panel'!$B$27)^2*IFERROR(INDEX($AW5:$BT5,1,'Control Panel'!$B$8-2),0)+'Control Panel'!$B$27*(1-'Control Panel'!$B$27)^3*IFERROR(INDEX($AW5:$BT5,1,'Control Panel'!$B$8-3),0)+'Control Panel'!$B$27*(1-'Control Panel'!$B$27)^4*IFERROR(INDEX($AW5:$BT5,1,'Control Panel'!$B$8-4),0)+'Control Panel'!$B$27*(1-'Control Panel'!$B$27)^5*IFERROR(INDEX($AW5:$BT5,1,'Control Panel'!$B$8-5),0))/(1-(1-'Control Panel'!$B$27)^6))*Q5)+'Control Panel'!$B$19*((D5+M5*3)*Q5)+'Control Panel'!$B$20*(K5*Q5)+'Control Panel'!$B$21*(D5*(1+N5)^3*Q5)+'Control Panel'!$B$22*(I5*Q5)+'Control Panel'!$B$23*(T5*(1+IFERROR(D5/H5-1,0))))/'Control Panel'!$B$24,0) | AE5: =MAX(0,AB5*(1+U5+V5)) | AF5: =MAX(0,AC5*(1+U5+W5)) | AG5: =MAX(0,AD5*(1+U5+X5)) | AH5: =IFERROR(('Control Panel'!$B$33*AB5+'Control Panel'!$B$34*AE5+'Control Panel'!$B$35*(AB5*(1+L5+V5)))/('Control Panel'!$B$33+'Control Panel'!$B$34+'Control Panel'!$B$35),0) | AI5: =IFERROR(('Control Panel'!$B$33*AC5+'Control Panel'!$B$34*AF5+'Control Panel'!$B$35*(AC5*(1+L5+W5)))/('Control Panel'!$B$33+'Control Panel'!$B$34+'Control Panel'!$B$35),0) | AJ5: =IFERROR(('Control Panel'!$B$33*AD5+'Control Panel'!$B$34*AG5+'Control Panel'!$B$35*(AD5*(1+L5+X5)))/('Control Panel'!$B$33+'Control Panel'!$B$34+'Control Panel'!$B$35),0) | AK5: =AH5*'Control Panel'!$B$39+Y5 | AL5: =AI5*'Control Panel'!$B$39+Z5 | AM5: =AJ5*'Control Panel'!$B$39+AA5 | AN5: =AH5*'Control Panel'!$B$40+Y5 | AO5: =AI5*'Control Panel'!$B$40+Z5 | AP5: =AJ5*'Control Panel'!$B$40+AA5 | AQ5: =AH5*'Control Panel'!$B$41+Y5 | AR5: =AI5*'Control Panel'!$B$41+Z5 | AS5: =AJ5*'Control Panel'!$B$41+AA5 | AT5: =AH5*'Control Panel'!$B$42+Y5 | AU5: =AI5*'Control Panel'!$B$42+Z5 | AV5: =AJ5*'Control Panel'!$B$42+AA5 | AW5: =SUMIFS('Primary Sales History'!$C$4:$C$33,'Primary Sales History'!$A$4:$A$33,$A5,'Primary Sales History'!$B$4:$B$33,$B5) | AX5: =SUMIFS('Primary Sales History'!$D$4:$D$33,'Primary Sales History'!$A$4:$A$33,$A5,'Primary Sales History'!$B$4:$B$33,$B5) | AY5: =SUMIFS('Primary Sales History'!$E$4:$E$33,'Primary Sales History'!$A$4:$A$33,$A5,'Primary Sales History'!$B$4:$B$33,$B5) | AZ5: =SUMIFS('Primary Sales History'!$F$4:$F$33,'Primary Sales History'!$A$4:$A$33,$A5,'Primary Sales History'!$B$4:$B$33,$B5) | BA5: =SUMIFS('Primary Sales History'!$G$4:$G$33,'Primary Sales History'!$A$4:$A$33,$A5,'Primary Sales History'!$B$4:$B$33,$B5) | BB5: =SUMIFS('Primary Sales History'!$H$4:$H$33,'Primary Sales History'!$A$4:$A$33,$A5,'Primary Sales History'!$B$4:$B$33,$B5) | BC5: =SUMIFS('Primary Sales History'!$I$4:$I$33,'Primary Sales History'!$A$4:$A$33,$A5,'Primary Sales History'!$B$4:$B$33,$B5) | BD5: =SUMIFS('Primary Sales History'!$J$4:$J$33,'Primary Sales History'!$A$4:$A$33,$A5,'Primary Sales History'!$B$4:$B$33,$B5) | BE5: =SUMIFS('Primary Sales History'!$K$4:$K$33,'Primary Sales History'!$A$4:$A$33,$A5,'Primary Sales History'!$B$4:$B$33,$B5) | BF5: =SUMIFS('Primary Sales History'!$L$4:$L$33,'Primary Sales History'!$A$4:$A$33,$A5,'Primary Sales History'!$B$4:$B$33,$B5) | BG5: =SUMIFS('Primary Sales History'!$M$4:$M$33,'Primary Sales History'!$A$4:$A$33,$A5,'Primary Sales History'!$B$4:$B$33,$B5) | BH5: =SUMIFS('Primary Sales History'!$N$4:$N$33,'Primary Sales History'!$A$4:$A$33,$A5,'Primary Sales History'!$B$4:$B$33,$B5) | BI5: =SUMIFS('Primary Sales History'!$O$4:$O$33,'Primary Sales History'!$A$4:$A$33,$A5,'Primary Sales History'!$B$4:$B$33,$B5) | BJ5: =SUMIFS('Primary Sales History'!$P$4:$P$33,'Primary Sales History'!$A$4:$A$33,$A5,'Primary Sales History'!$B$4:$B$33,$B5) | BK5: 0 | BL5: 0 | BM5: 0 | BN5: 0 | BO5: 0 | BP5: 0 | BQ5: 0 | BR5: 0 | BS5: 0 | BT5: 0
A6: The Derma Co. | B6: Face | C6: Face | D6: =IFERROR(INDEX($AW6:$BT6,1,'Control Panel'!$B$8-0),0) | E6: =IFERROR(INDEX($AW6:$BT6,1,'Control Panel'!$B$8-1),0) | F6: =IFERROR(INDEX($AW6:$BT6,1,'Control Panel'!$B$8-2),0) | G6: =IFERROR(INDEX($AW6:$BT6,1,'Control Panel'!$B$8-5),0) | H6: =IFERROR(INDEX($AW6:$BT6,1,'Control Panel'!$B$8-11),0) | I6: =AVERAGE(D6,E6,F6) | J6: =(D6+E6+F6+IFERROR(INDEX($AW6:$BT6,1,'Control Panel'!$B$8-3),0)+IFERROR(INDEX($AW6:$BT6,1,'Control Panel'!$B$8-4),0)+G6)/6 | K6: =(IFERROR(INDEX($AW6:$BT6,1,'Control Panel'!$B$8-0),0)+IFERROR(INDEX($AW6:$BT6,1,'Control Panel'!$B$8-1),0)+IFERROR(INDEX($AW6:$BT6,1,'Control Panel'!$B$8-2),0)+IFERROR(INDEX($AW6:$BT6,1,'Control Panel'!$B$8-3),0)+IFERROR(INDEX($AW6:$BT6,1,'Control Panel'!$B$8-4),0)+IFERROR(INDEX($AW6:$BT6,1,'Control Panel'!$B$8-5),0)+IFERROR(INDEX($AW6:$BT6,1,'Control Panel'!$B$8-6),0)+IFERROR(INDEX($AW6:$BT6,1,'Control Panel'!$B$8-7),0)+IFERROR(INDEX($AW6:$BT6,1,'Control Panel'!$B$8-8),0)+IFERROR(INDEX($AW6:$BT6,1,'Control Panel'!$B$8-9),0)+IFERROR(INDEX($AW6:$BT6,1,'Control Panel'!$B$8-10),0)+IFERROR(INDEX($AW6:$BT6,1,'Control Panel'!$B$8-11),0))/12 | L6: =IFERROR(MAX(-'Control Panel'!$B$36,MIN('Control Panel'!$B$36,(I6-J6)/J6)),0) | M6: =(D6-G6)/5 | N6: =IFERROR(IF(H6>0,(D6/H6)^(1/12)-1,0),0) | O6: =IFERROR((IFERROR(INDEX('Seasonality Matrix'!$B$4:$M$11,MATCH($C6,'Seasonality Matrix'!$A$4:$A$11,0),MATCH('Control Panel'!$B$12,'Seasonality Matrix'!$B$3:$M$3,0)),1))/(IFERROR(AVERAGE(INDEX('Seasonality Matrix'!$B$4:$M$11,MATCH($C6,'Seasonality Matrix'!$A$4:$A$11,0),0)),1)),1) | P6: =IFERROR((IFERROR(INDEX('Seasonality Matrix'!$B$4:$M$11,MATCH($C6,'Seasonality Matrix'!$A$4:$A$11,0),MATCH('Control Panel'!$B$13,'Seasonality Matrix'!$B$3:$M$3,0)),1))/(IFERROR(AVERAGE(INDEX('Seasonality Matrix'!$B$4:$M$11,MATCH($C6,'Seasonality Matrix'!$A$4:$A$11,0),0)),1)),1) | Q6: =IFERROR((IFERROR(INDEX('Seasonality Matrix'!$B$4:$M$11,MATCH($C6,'Seasonality Matrix'!$A$4:$A$11,0),MATCH('Control Panel'!$B$14,'Seasonality Matrix'!$B$3:$M$3,0)),1))/(IFERROR(AVERAGE(INDEX('Seasonality Matrix'!$B$4:$M$11,MATCH($C6,'Seasonality Matrix'!$A$4:$A$11,0),0)),1)),1) | R6: =IFERROR(INDEX($AW6:$BT6,1,'Control Panel'!$B$9-12),0) | S6: =IFERROR(INDEX($AW6:$BT6,1,'Control Panel'!$B$10-12),0) | T6: =IFERROR(INDEX($AW6:$BT6,1,'Control Panel'!$B$11-12),0) | U6: ='Control Panel'!$B$45 | V6: =IFERROR(SUMIFS('Promotion Calendar'!$G$4:$G$12,'Promotion Calendar'!$A$4:$A$12,$A6,'Promotion Calendar'!$B$4:$B$12,$B6,'Promotion Calendar'!$C$4:$C$12,'Control Panel'!$B$4),0) | W6: =IFERROR(SUMIFS('Promotion Calendar'!$G$4:$G$12,'Promotion Calendar'!$A$4:$A$12,$A6,'Promotion Calendar'!$B$4:$B$12,$B6,'Promotion Calendar'!$C$4:$C$12,'Control Panel'!$B$6),0) | X6: =IFERROR(SUMIFS('Promotion Calendar'!$G$4:$G$12,'Promotion Calendar'!$A$4:$A$12,$A6,'Promotion Calendar'!$B$4:$B$12,$B6,'Promotion Calendar'!$C$4:$C$12,'Control Panel'!$B$7),0) | Y6: =IFERROR(SUMIFS('NPI & EPD Planning'!$I$4:$I$10,'NPI & EPD Planning'!$A$4:$A$10,$A6,'NPI & EPD Planning'!$B$4:$B$10,$B6,'NPI & EPD Planning'!$D$4:$D$10,'Control Panel'!$B$4),0) | Z6: =IFERROR(SUMIFS('NPI & EPD Planning'!$I$4:$I$10,'NPI & EPD Planning'!$A$4:$A$10,$A6,'NPI & EPD Planning'!$B$4:$B$10,$B6,'NPI & EPD Planning'!$D$4:$D$10,'Control Panel'!$B$6),0) | AA6: =IFERROR(SUMIFS('NPI & EPD Planning'!$I$4:$I$10,'NPI & EPD Planning'!$A$4:$A$10,$A6,'NPI & EPD Planning'!$B$4:$B$10,$B6,'NPI & EPD Planning'!$D$4:$D$10,'Control Panel'!$B$7),0) | AB6: =IFERROR(('Control Panel'!$B$17*(('Control Panel'!$B$28*D6+'Control Panel'!$B$29*E6+'Control Panel'!$B$30*F6)*O6)+'Control Panel'!$B$18*((('Control Panel'!$B$27*(1-'Control Panel'!$B$27)^0*IFERROR(INDEX($AW6:$BT6,1,'Control Panel'!$B$8-0),0)+'Control Panel'!$B$27*(1-'Control Panel'!$B$27)^1*IFERROR(INDEX($AW6:$BT6,1,'Control Panel'!$B$8-1),0)+'Control Panel'!$B$27*(1-'Control Panel'!$B$27)^2*IFERROR(INDEX($AW6:$BT6,1,'Control Panel'!$B$8-2),0)+'Control Panel'!$B$27*(1-'Control Panel'!$B$27)^3*IFERROR(INDEX($AW6:$BT6,1,'Control Panel'!$B$8-3),0)+'Control Panel'!$B$27*(1-'Control Panel'!$B$27)^4*IFERROR(INDEX($AW6:$BT6,1,'Control Panel'!$B$8-4),0)+'Control Panel'!$B$27*(1-'Control Panel'!$B$27)^5*IFERROR(INDEX($AW6:$BT6,1,'Control Panel'!$B$8-5),0))/(1-(1-'Control Panel'!$B$27)^6))*O6)+'Control Panel'!$B$19*((D6+M6*1)*O6)+'Control Panel'!$B$20*(K6*O6)+'Control Panel'!$B$21*(D6*(1+N6)^1*O6)+'Control Panel'!$B$22*(I6*O6)+'Control Panel'!$B$23*(R6*(1+IFERROR(D6/H6-1,0))))/'Control Panel'!$B$24,0) | AC6: =IFERROR(('Control Panel'!$B$17*(('Control Panel'!$B$28*D6+'Control Panel'!$B$29*E6+'Control Panel'!$B$30*F6)*P6)+'Control Panel'!$B$18*((('Control Panel'!$B$27*(1-'Control Panel'!$B$27)^0*IFERROR(INDEX($AW6:$BT6,1,'Control Panel'!$B$8-0),0)+'Control Panel'!$B$27*(1-'Control Panel'!$B$27)^1*IFERROR(INDEX($AW6:$BT6,1,'Control Panel'!$B$8-1),0)+'Control Panel'!$B$27*(1-'Control Panel'!$B$27)^2*IFERROR(INDEX($AW6:$BT6,1,'Control Panel'!$B$8-2),0)+'Control Panel'!$B$27*(1-'Control Panel'!$B$27)^3*IFERROR(INDEX($AW6:$BT6,1,'Control Panel'!$B$8-3),0)+'Control Panel'!$B$27*(1-'Control Panel'!$B$27)^4*IFERROR(INDEX($AW6:$BT6,1,'Control Panel'!$B$8-4),0)+'Control Panel'!$B$27*(1-'Control Panel'!$B$27)^5*IFERROR(INDEX($AW6:$BT6,1,'Control Panel'!$B$8-5),0))/(1-(1-'Control Panel'!$B$27)^6))*P6)+'Control Panel'!$B$19*((D6+M6*2)*P6)+'Control Panel'!$B$20*(K6*P6)+'Control Panel'!$B$21*(D6*(1+N6)^2*P6)+'Control Panel'!$B$22*(I6*P6)+'Control Panel'!$B$23*(S6*(1+IFERROR(D6/H6-1,0))))/'Control Panel'!$B$24,0) | AD6: =IFERROR(('Control Panel'!$B$17*(('Control Panel'!$B$28*D6+'Control Panel'!$B$29*E6+'Control Panel'!$B$30*F6)*Q6)+'Control Panel'!$B$18*((('Control Panel'!$B$27*(1-'Control Panel'!$B$27)^0*IFERROR(INDEX($AW6:$BT6,1,'Control Panel'!$B$8-0),0)+'Control Panel'!$B$27*(1-'Control Panel'!$B$27)^1*IFERROR(INDEX($AW6:$BT6,1,'Control Panel'!$B$8-1),0)+'Control Panel'!$B$27*(1-'Control Panel'!$B$27)^2*IFERROR(INDEX($AW6:$BT6,1,'Control Panel'!$B$8-2),0)+'Control Panel'!$B$27*(1-'Control Panel'!$B$27)^3*IFERROR(INDEX($AW6:$BT6,1,'Control Panel'!$B$8-3),0)+'Control Panel'!$B$27*(1-'Control Panel'!$B$27)^4*IFERROR(INDEX($AW6:$BT6,1,'Control Panel'!$B$8-4),0)+'Control Panel'!$B$27*(1-'Control Panel'!$B$27)^5*IFERROR(INDEX($AW6:$BT6,1,'Control Panel'!$B$8-5),0))/(1-(1-'Control Panel'!$B$27)^6))*Q6)+'Control Panel'!$B$19*((D6+M6*3)*Q6)+'Control Panel'!$B$20*(K6*Q6)+'Control Panel'!$B$21*(D6*(1+N6)^3*Q6)+'Control Panel'!$B$22*(I6*Q6)+'Control Panel'!$B$23*(T6*(1+IFERROR(D6/H6-1,0))))/'Control Panel'!$B$24,0) | AE6: =MAX(0,AB6*(1+U6+V6)) | AF6: =MAX(0,AC6*(1+U6+W6)) | AG6: =MAX(0,AD6*(1+U6+X6)) | AH6: =IFERROR(('Control Panel'!$B$33*AB6+'Control Panel'!$B$34*AE6+'Control Panel'!$B$35*(AB6*(1+L6+V6)))/('Control Panel'!$B$33+'Control Panel'!$B$34+'Control Panel'!$B$35),0) | AI6: =IFERROR(('Control Panel'!$B$33*AC6+'Control Panel'!$B$34*AF6+'Control Panel'!$B$35*(AC6*(1+L6+W6)))/('Control Panel'!$B$33+'Control Panel'!$B$34+'Control Panel'!$B$35),0) | AJ6: =IFERROR(('Control Panel'!$B$33*AD6+'Control Panel'!$B$34*AG6+'Control Panel'!$B$35*(AD6*(1+L6+X6)))/('Control Panel'!$B$33+'Control Panel'!$B$34+'Control Panel'!$B$35),0) | AK6: =AH6*'Control Panel'!$B$39+Y6 | AL6: =AI6*'Control Panel'!$B$39+Z6 | AM6: =AJ6*'Control Panel'!$B$39+AA6 | AN6: =AH6*'Control Panel'!$B$40+Y6 | AO6: =AI6*'Control Panel'!$B$40+Z6 | AP6: =AJ6*'Control Panel'!$B$40+AA6 | AQ6: =AH6*'Control Panel'!$B$41+Y6 | AR6: =AI6*'Control Panel'!$B$41+Z6 | AS6: =AJ6*'Control Panel'!$B$41+AA6 | AT6: =AH6*'Control Panel'!$B$42+Y6 | AU6: =AI6*'Control Panel'!$B$42+Z6 | AV6: =AJ6*'Control Panel'!$B$42+AA6 | AW6: =SUMIFS('Primary Sales History'!$C$4:$C$33,'Primary Sales History'!$A$4:$A$33,$A6,'Primary Sales History'!$B$4:$B$33,$B6) | AX6: =SUMIFS('Primary Sales History'!$D$4:$D$33,'Primary Sales History'!$A$4:$A$33,$A6,'Primary Sales History'!$B$4:$B$33,$B6) | AY6: =SUMIFS('Primary Sales History'!$E$4:$E$33,'Primary Sales History'!$A$4:$A$33,$A6,'Primary Sales History'!$B$4:$B$33,$B6) | AZ6: =SUMIFS('Primary Sales History'!$F$4:$F$33,'Primary Sales History'!$A$4:$A$33,$A6,'Primary Sales History'!$B$4:$B$33,$B6) | BA6: =SUMIFS('Primary Sales History'!$G$4:$G$33,'Primary Sales History'!$A$4:$A$33,$A6,'Primary Sales History'!$B$4:$B$33,$B6) | BB6: =SUMIFS('Primary Sales History'!$H$4:$H$33,'Primary Sales History'!$A$4:$A$33,$A6,'Primary Sales History'!$B$4:$B$33,$B6) | BC6: =SUMIFS('Primary Sales History'!$I$4:$I$33,'Primary Sales History'!$A$4:$A$33,$A6,'Primary Sales History'!$B$4:$B$33,$B6) | BD6: =SUMIFS('Primary Sales History'!$J$4:$J$33,'Primary Sales History'!$A$4:$A$33,$A6,'Primary Sales History'!$B$4:$B$33,$B6) | BE6: =SUMIFS('Primary Sales History'!$K$4:$K$33,'Primary Sales History'!$A$4:$A$33,$A6,'Primary Sales History'!$B$4:$B$33,$B6) | BF6: =SUMIFS('Primary Sales History'!$L$4:$L$33,'Primary Sales History'!$A$4:$A$33,$A6,'Primary Sales History'!$B$4:$B$33,$B6) | BG6: =SUMIFS('Primary Sales History'!$M$4:$M$33,'Primary Sales History'!$A$4:$A$33,$A6,'Primary Sales History'!$B$4:$B$33,$B6) | BH6: =SUMIFS('Primary Sales History'!$N$4:$N$33,'Primary Sales History'!$A$4:$A$33,$A6,'Primary Sales History'!$B$4:$B$33,$B6) | BI6: =SUMIFS('Primary Sales History'!$O$4:$O$33,'Primary Sales History'!$A$4:$A$33,$A6,'Primary Sales History'!$B$4:$B$33,$B6) | BJ6: =SUMIFS('Primary Sales History'!$P$4:$P$33,'Primary Sales History'!$A$4:$A$33,$A6,'Primary Sales History'!$B$4:$B$33,$B6) | BK6: 0 | BL6: 0 | BM6: 0 | BN6: 0 | BO6: 0 | BP6: 0 | BQ6: 0 | BR6: 0 | BS6: 0 | BT6: 0
A7: Mamaearth | B7: Body | C7: Body | D7: =IFERROR(INDEX($AW7:$BT7,1,'Control Panel'!$B$8-0),0) | E7: =IFERROR(INDEX($AW7:$BT7,1,'Control Panel'!$B$8-1),0) | F7: =IFERROR(INDEX($AW7:$BT7,1,'Control Panel'!$B$8-2),0) | G7: =IFERROR(INDEX($AW7:$BT7,1,'Control Panel'!$B$8-5),0) | H7: =IFERROR(INDEX($AW7:$BT7,1,'Control Panel'!$B$8-11),0) | I7: =AVERAGE(D7,E7,F7) | J7: =(D7+E7+F7+IFERROR(INDEX($AW7:$BT7,1,'Control Panel'!$B$8-3),0)+IFERROR(INDEX($AW7:$BT7,1,'Control Panel'!$B$8-4),0)+G7)/6 | K7: =(IFERROR(INDEX($AW7:$BT7,1,'Control Panel'!$B$8-0),0)+IFERROR(INDEX($AW7:$BT7,1,'Control Panel'!$B$8-1),0)+IFERROR(INDEX($AW7:$BT7,1,'Control Panel'!$B$8-2),0)+IFERROR(INDEX($AW7:$BT7,1,'Control Panel'!$B$8-3),0)+IFERROR(INDEX($AW7:$BT7,1,'Control Panel'!$B$8-4),0)+IFERROR(INDEX($AW7:$BT7,1,'Control Panel'!$B$8-5),0)+IFERROR(INDEX($AW7:$BT7,1,'Control Panel'!$B$8-6),0)+IFERROR(INDEX($AW7:$BT7,1,'Control Panel'!$B$8-7),0)+IFERROR(INDEX($AW7:$BT7,1,'Control Panel'!$B$8-8),0)+IFERROR(INDEX($AW7:$BT7,1,'Control Panel'!$B$8-9),0)+IFERROR(INDEX($AW7:$BT7,1,'Control Panel'!$B$8-10),0)+IFERROR(INDEX($AW7:$BT7,1,'Control Panel'!$B$8-11),0))/12 | L7: =IFERROR(MAX(-'Control Panel'!$B$36,MIN('Control Panel'!$B$36,(I7-J7)/J7)),0) | M7: =(D7-G7)/5 | N7: =IFERROR(IF(H7>0,(D7/H7)^(1/12)-1,0),0) | O7: =IFERROR((IFERROR(INDEX('Seasonality Matrix'!$B$4:$M$11,MATCH($C7,'Seasonality Matrix'!$A$4:$A$11,0),MATCH('Control Panel'!$B$12,'Seasonality Matrix'!$B$3:$M$3,0)),1))/(IFERROR(AVERAGE(INDEX('Seasonality Matrix'!$B$4:$M$11,MATCH($C7,'Seasonality Matrix'!$A$4:$A$11,0),0)),1)),1) | P7: =IFERROR((IFERROR(INDEX('Seasonality Matrix'!$B$4:$M$11,MATCH($C7,'Seasonality Matrix'!$A$4:$A$11,0),MATCH('Control Panel'!$B$13,'Seasonality Matrix'!$B$3:$M$3,0)),1))/(IFERROR(AVERAGE(INDEX('Seasonality Matrix'!$B$4:$M$11,MATCH($C7,'Seasonality Matrix'!$A$4:$A$11,0),0)),1)),1) | Q7: =IFERROR((IFERROR(INDEX('Seasonality Matrix'!$B$4:$M$11,MATCH($C7,'Seasonality Matrix'!$A$4:$A$11,0),MATCH('Control Panel'!$B$14,'Seasonality Matrix'!$B$3:$M$3,0)),1))/(IFERROR(AVERAGE(INDEX('Seasonality Matrix'!$B$4:$M$11,MATCH($C7,'Seasonality Matrix'!$A$4:$A$11,0),0)),1)),1) | R7: =IFERROR(INDEX($AW7:$BT7,1,'Control Panel'!$B$9-12),0) | S7: =IFERROR(INDEX($AW7:$BT7,1,'Control Panel'!$B$10-12),0) | T7: =IFERROR(INDEX($AW7:$BT7,1,'Control Panel'!$B$11-12),0) | U7: ='Control Panel'!$B$45 | V7: =IFERROR(SUMIFS('Promotion Calendar'!$G$4:$G$12,'Promotion Calendar'!$A$4:$A$12,$A7,'Promotion Calendar'!$B$4:$B$12,$B7,'Promotion Calendar'!$C$4:$C$12,'Control Panel'!$B$4),0) | W7: =IFERROR(SUMIFS('Promotion Calendar'!$G$4:$G$12,'Promotion Calendar'!$A$4:$A$12,$A7,'Promotion Calendar'!$B$4:$B$12,$B7,'Promotion Calendar'!$C$4:$C$12,'Control Panel'!$B$6),0) | X7: =IFERROR(SUMIFS('Promotion Calendar'!$G$4:$G$12,'Promotion Calendar'!$A$4:$A$12,$A7,'Promotion Calendar'!$B$4:$B$12,$B7,'Promotion Calendar'!$C$4:$C$12,'Control Panel'!$B$7),0) | Y7: =IFERROR(SUMIFS('NPI & EPD Planning'!$I$4:$I$10,'NPI & EPD Planning'!$A$4:$A$10,$A7,'NPI & EPD Planning'!$B$4:$B$10,$B7,'NPI & EPD Planning'!$D$4:$D$10,'Control Panel'!$B$4),0) | Z7: =IFERROR(SUMIFS('NPI & EPD Planning'!$I$4:$I$10,'NPI & EPD Planning'!$A$4:$A$10,$A7,'NPI & EPD Planning'!$B$4:$B$10,$B7,'NPI & EPD Planning'!$D$4:$D$10,'Control Panel'!$B$6),0) | AA7: =IFERROR(SUMIFS('NPI & EPD Planning'!$I$4:$I$10,'NPI & EPD Planning'!$A$4:$A$10,$A7,'NPI & EPD Planning'!$B$4:$B$10,$B7,'NPI & EPD Planning'!$D$4:$D$10,'Control Panel'!$B$7),0) | AB7: =IFERROR(('Control Panel'!$B$17*(('Control Panel'!$B$28*D7+'Control Panel'!$B$29*E7+'Control Panel'!$B$30*F7)*O7)+'Control Panel'!$B$18*((('Control Panel'!$B$27*(1-'Control Panel'!$B$27)^0*IFERROR(INDEX($AW7:$BT7,1,'Control Panel'!$B$8-0),0)+'Control Panel'!$B$27*(1-'Control Panel'!$B$27)^1*IFERROR(INDEX($AW7:$BT7,1,'Control Panel'!$B$8-1),0)+'Control Panel'!$B$27*(1-'Control Panel'!$B$27)^2*IFERROR(INDEX($AW7:$BT7,1,'Control Panel'!$B$8-2),0)+'Control Panel'!$B$27*(1-'Control Panel'!$B$27)^3*IFERROR(INDEX($AW7:$BT7,1,'Control Panel'!$B$8-3),0)+'Control Panel'!$B$27*(1-'Control Panel'!$B$27)^4*IFERROR(INDEX($AW7:$BT7,1,'Control Panel'!$B$8-4),0)+'Control Panel'!$B$27*(1-'Control Panel'!$B$27)^5*IFERROR(INDEX($AW7:$BT7,1,'Control Panel'!$B$8-5),0))/(1-(1-'Control Panel'!$B$27)^6))*O7)+'Control Panel'!$B$19*((D7+M7*1)*O7)+'Control Panel'!$B$20*(K7*O7)+'Control Panel'!$B$21*(D7*(1+N7)^1*O7)+'Control Panel'!$B$22*(I7*O7)+'Control Panel'!$B$23*(R7*(1+IFERROR(D7/H7-1,0))))/'Control Panel'!$B$24,0) | AC7: =IFERROR(('Control Panel'!$B$17*(('Control Panel'!$B$28*D7+'Control Panel'!$B$29*E7+'Control Panel'!$B$30*F7)*P7)+'Control Panel'!$B$18*((('Control Panel'!$B$27*(1-'Control Panel'!$B$27)^0*IFERROR(INDEX($AW7:$BT7,1,'Control Panel'!$B$8-0),0)+'Control Panel'!$B$27*(1-'Control Panel'!$B$27)^1*IFERROR(INDEX($AW7:$BT7,1,'Control Panel'!$B$8-1),0)+'Control Panel'!$B$27*(1-'Control Panel'!$B$27)^2*IFERROR(INDEX($AW7:$BT7,1,'Control Panel'!$B$8-2),0)+'Control Panel'!$B$27*(1-'Control Panel'!$B$27)^3*IFERROR(INDEX($AW7:$BT7,1,'Control Panel'!$B$8-3),0)+'Control Panel'!$B$27*(1-'Control Panel'!$B$27)^4*IFERROR(INDEX($AW7:$BT7,1,'Control Panel'!$B$8-4),0)+'Control Panel'!$B$27*(1-'Control Panel'!$B$27)^5*IFERROR(INDEX($AW7:$BT7,1,'Control Panel'!$B$8-5),0))/(1-(1-'Control Panel'!$B$27)^6))*P7)+'Control Panel'!$B$19*((D7+M7*2)*P7)+'Control Panel'!$B$20*(K7*P7)+'Control Panel'!$B$21*(D7*(1+N7)^2*P7)+'Control Panel'!$B$22*(I7*P7)+'Control Panel'!$B$23*(S7*(1+IFERROR(D7/H7-1,0))))/'Control Panel'!$B$24,0) | AD7: =IFERROR(('Control Panel'!$B$17*(('Control Panel'!$B$28*D7+'Control Panel'!$B$29*E7+'Control Panel'!$B$30*F7)*Q7)+'Control Panel'!$B$18*((('Control Panel'!$B$27*(1-'Control Panel'!$B$27)^0*IFERROR(INDEX($AW7:$BT7,1,'Control Panel'!$B$8-0),0)+'Control Panel'!$B$27*(1-'Control Panel'!$B$27)^1*IFERROR(INDEX($AW7:$BT7,1,'Control Panel'!$B$8-1),0)+'Control Panel'!$B$27*(1-'Control Panel'!$B$27)^2*IFERROR(INDEX($AW7:$BT7,1,'Control Panel'!$B$8-2),0)+'Control Panel'!$B$27*(1-'Control Panel'!$B$27)^3*IFERROR(INDEX($AW7:$BT7,1,'Control Panel'!$B$8-3),0)+'Control Panel'!$B$27*(1-'Control Panel'!$B$27)^4*IFERROR(INDEX($AW7:$BT7,1,'Control Panel'!$B$8-4),0)+'Control Panel'!$B$27*(1-'Control Panel'!$B$27)^5*IFERROR(INDEX($AW7:$BT7,1,'Control Panel'!$B$8-5),0))/(1-(1-'Control Panel'!$B$27)^6))*Q7)+'Control Panel'!$B$19*((D7+M7*3)*Q7)+'Control Panel'!$B$20*(K7*Q7)+'Control Panel'!$B$21*(D7*(1+N7)^3*Q7)+'Control Panel'!$B$22*(I7*Q7)+'Control Panel'!$B$23*(T7*(1+IFERROR(D7/H7-1,0))))/'Control Panel'!$B$24,0) | AE7: =MAX(0,AB7*(1+U7+V7)) | AF7: =MAX(0,AC7*(1+U7+W7)) | AG7: =MAX(0,AD7*(1+U7+X7)) | AH7: =IFERROR(('Control Panel'!$B$33*AB7+'Control Panel'!$B$34*AE7+'Control Panel'!$B$35*(AB7*(1+L7+V7)))/('Control Panel'!$B$33+'Control Panel'!$B$34+'Control Panel'!$B$35),0) | AI7: =IFERROR(('Control Panel'!$B$33*AC7+'Control Panel'!$B$34*AF7+'Control Panel'!$B$35*(AC7*(1+L7+W7)))/('Control Panel'!$B$33+'Control Panel'!$B$34+'Control Panel'!$B$35),0) | AJ7: =IFERROR(('Control Panel'!$B$33*AD7+'Control Panel'!$B$34*AG7+'Control Panel'!$B$35*(AD7*(1+L7+X7)))/('Control Panel'!$B$33+'Control Panel'!$B$34+'Control Panel'!$B$35),0) | AK7: =AH7*'Control Panel'!$B$39+Y7 | AL7: =AI7*'Control Panel'!$B$39+Z7 | AM7: =AJ7*'Control Panel'!$B$39+AA7 | AN7: =AH7*'Control Panel'!$B$40+Y7 | AO7: =AI7*'Control Panel'!$B$40+Z7 | AP7: =AJ7*'Control Panel'!$B$40+AA7 | AQ7: =AH7*'Control Panel'!$B$41+Y7 | AR7: =AI7*'Control Panel'!$B$41+Z7 | AS7: =AJ7*'Control Panel'!$B$41+AA7 | AT7: =AH7*'Control Panel'!$B$42+Y7 | AU7: =AI7*'Control Panel'!$B$42+Z7 | AV7: =AJ7*'Control Panel'!$B$42+AA7 | AW7: =SUMIFS('Primary Sales History'!$C$4:$C$33,'Primary Sales History'!$A$4:$A$33,$A7,'Primary Sales History'!$B$4:$B$33,$B7) | AX7: =SUMIFS('Primary Sales History'!$D$4:$D$33,'Primary Sales History'!$A$4:$A$33,$A7,'Primary Sales History'!$B$4:$B$33,$B7) | AY7: =SUMIFS('Primary Sales History'!$E$4:$E$33,'Primary Sales History'!$A$4:$A$33,$A7,'Primary Sales History'!$B$4:$B$33,$B7) | AZ7: =SUMIFS('Primary Sales History'!$F$4:$F$33,'Primary Sales History'!$A$4:$A$33,$A7,'Primary Sales History'!$B$4:$B$33,$B7) | BA7: =SUMIFS('Primary Sales History'!$G$4:$G$33,'Primary Sales History'!$A$4:$A$33,$A7,'Primary Sales History'!$B$4:$B$33,$B7) | BB7: =SUMIFS('Primary Sales History'!$H$4:$H$33,'Primary Sales History'!$A$4:$A$33,$A7,'Primary Sales History'!$B$4:$B$33,$B7) | BC7: =SUMIFS('Primary Sales History'!$I$4:$I$33,'Primary Sales History'!$A$4:$A$33,$A7,'Primary Sales History'!$B$4:$B$33,$B7) | BD7: =SUMIFS('Primary Sales History'!$J$4:$J$33,'Primary Sales History'!$A$4:$A$33,$A7,'Primary Sales History'!$B$4:$B$33,$B7) | BE7: =SUMIFS('Primary Sales History'!$K$4:$K$33,'Primary Sales History'!$A$4:$A$33,$A7,'Primary Sales History'!$B$4:$B$33,$B7) | BF7: =SUMIFS('Primary Sales History'!$L$4:$L$33,'Primary Sales History'!$A$4:$A$33,$A7,'Primary Sales History'!$B$4:$B$33,$B7) | BG7: =SUMIFS('Primary Sales History'!$M$4:$M$33,'Primary Sales History'!$A$4:$A$33,$A7,'Primary Sales History'!$B$4:$B$33,$B7) | BH7: =SUMIFS('Primary Sales History'!$N$4:$N$33,'Primary Sales History'!$A$4:$A$33,$A7,'Primary Sales History'!$B$4:$B$33,$B7) | BI7: =SUMIFS('Primary Sales History'!$O$4:$O$33,'Primary Sales History'!$A$4:$A$33,$A7,'Primary Sales History'!$B$4:$B$33,$B7) | BJ7: =SUMIFS('Primary Sales History'!$P$4:$P$33,'Primary Sales History'!$A$4:$A$33,$A7,'Primary Sales History'!$B$4:$B$33,$B7) | BK7: 0 | BL7: 0 | BM7: 0 | BN7: 0 | BO7: 0 | BP7: 0 | BQ7: 0 | BR7: 0 | BS7: 0 | BT7: 0
A8: Mamaearth | B8: Baby | C8: Baby | D8: =IFERROR(INDEX($AW8:$BT8,1,'Control Panel'!$B$8-0),0) | E8: =IFERROR(INDEX($AW8:$BT8,1,'Control Panel'!$B$8-1),0) | F8: =IFERROR(INDEX($AW8:$BT8,1,'Control Panel'!$B$8-2),0) | G8: =IFERROR(INDEX($AW8:$BT8,1,'Control Panel'!$B$8-5),0) | H8: =IFERROR(INDEX($AW8:$BT8,1,'Control Panel'!$B$8-11),0) | I8: =AVERAGE(D8,E8,F8) | J8: =(D8+E8+F8+IFERROR(INDEX($AW8:$BT8,1,'Control Panel'!$B$8-3),0)+IFERROR(INDEX($AW8:$BT8,1,'Control Panel'!$B$8-4),0)+G8)/6 | K8: =(IFERROR(INDEX($AW8:$BT8,1,'Control Panel'!$B$8-0),0)+IFERROR(INDEX($AW8:$BT8,1,'Control Panel'!$B$8-1),0)+IFERROR(INDEX($AW8:$BT8,1,'Control Panel'!$B$8-2),0)+IFERROR(INDEX($AW8:$BT8,1,'Control Panel'!$B$8-3),0)+IFERROR(INDEX($AW8:$BT8,1,'Control Panel'!$B$8-4),0)+IFERROR(INDEX($AW8:$BT8,1,'Control Panel'!$B$8-5),0)+IFERROR(INDEX($AW8:$BT8,1,'Control Panel'!$B$8-6),0)+IFERROR(INDEX($AW8:$BT8,1,'Control Panel'!$B$8-7),0)+IFERROR(INDEX($AW8:$BT8,1,'Control Panel'!$B$8-8),0)+IFERROR(INDEX($AW8:$BT8,1,'Control Panel'!$B$8-9),0)+IFERROR(INDEX($AW8:$BT8,1,'Control Panel'!$B$8-10),0)+IFERROR(INDEX($AW8:$BT8,1,'Control Panel'!$B$8-11),0))/12 | L8: =IFERROR(MAX(-'Control Panel'!$B$36,MIN('Control Panel'!$B$36,(I8-J8)/J8)),0) | M8: =(D8-G8)/5 | N8: =IFERROR(IF(H8>0,(D8/H8)^(1/12)-1,0),0) | O8: =IFERROR((IFERROR(INDEX('Seasonality Matrix'!$B$4:$M$11,MATCH($C8,'Seasonality Matrix'!$A$4:$A$11,0),MATCH('Control Panel'!$B$12,'Seasonality Matrix'!$B$3:$M$3,0)),1))/(IFERROR(AVERAGE(INDEX('Seasonality Matrix'!$B$4:$M$11,MATCH($C8,'Seasonality Matrix'!$A$4:$A$11,0),0)),1)),1) | P8: =IFERROR((IFERROR(INDEX('Seasonality Matrix'!$B$4:$M$11,MATCH($C8,'Seasonality Matrix'!$A$4:$A$11,0),MATCH('Control Panel'!$B$13,'Seasonality Matrix'!$B$3:$M$3,0)),1))/(IFERROR(AVERAGE(INDEX('Seasonality Matrix'!$B$4:$M$11,MATCH($C8,'Seasonality Matrix'!$A$4:$A$11,0),0)),1)),1) | Q8: =IFERROR((IFERROR(INDEX('Seasonality Matrix'!$B$4:$M$11,MATCH($C8,'Seasonality Matrix'!$A$4:$A$11,0),MATCH('Control Panel'!$B$14,'Seasonality Matrix'!$B$3:$M$3,0)),1))/(IFERROR(AVERAGE(INDEX('Seasonality Matrix'!$B$4:$M$11,MATCH($C8,'Seasonality Matrix'!$A$4:$A$11,0),0)),1)),1) | R8: =IFERROR(INDEX($AW8:$BT8,1,'Control Panel'!$B$9-12),0) | S8: =IFERROR(INDEX($AW8:$BT8,1,'Control Panel'!$B$10-12),0) | T8: =IFERROR(INDEX($AW8:$BT8,1,'Control Panel'!$B$11-12),0) | U8: ='Control Panel'!$B$45 | V8: =IFERROR(SUMIFS('Promotion Calendar'!$G$4:$G$12,'Promotion Calendar'!$A$4:$A$12,$A8,'Promotion Calendar'!$B$4:$B$12,$B8,'Promotion Calendar'!$C$4:$C$12,'Control Panel'!$B$4),0) | W8: =IFERROR(SUMIFS('Promotion Calendar'!$G$4:$G$12,'Promotion Calendar'!$A$4:$A$12,$A8,'Promotion Calendar'!$B$4:$B$12,$B8,'Promotion Calendar'!$C$4:$C$12,'Control Panel'!$B$6),0) | X8: =IFERROR(SUMIFS('Promotion Calendar'!$G$4:$G$12,'Promotion Calendar'!$A$4:$A$12,$A8,'Promotion Calendar'!$B$4:$B$12,$B8,'Promotion Calendar'!$C$4:$C$12,'Control Panel'!$B$7),0) | Y8: =IFERROR(SUMIFS('NPI & EPD Planning'!$I$4:$I$10,'NPI & EPD Planning'!$A$4:$A$10,$A8,'NPI & EPD Planning'!$B$4:$B$10,$B8,'NPI & EPD Planning'!$D$4:$D$10,'Control Panel'!$B$4),0) | Z8: =IFERROR(SUMIFS('NPI & EPD Planning'!$I$4:$I$10,'NPI & EPD Planning'!$A$4:$A$10,$A8,'NPI & EPD Planning'!$B$4:$B$10,$B8,'NPI & EPD Planning'!$D$4:$D$10,'Control Panel'!$B$6),0) | AA8: =IFERROR(SUMIFS('NPI & EPD Planning'!$I$4:$I$10,'NPI & EPD Planning'!$A$4:$A$10,$A8,'NPI & EPD Planning'!$B$4:$B$10,$B8,'NPI & EPD Planning'!$D$4:$D$10,'Control Panel'!$B$7),0) | AB8: =IFERROR(('Control Panel'!$B$17*(('Control Panel'!$B$28*D8+'Control Panel'!$B$29*E8+'Control Panel'!$B$30*F8)*O8)+'Control Panel'!$B$18*((('Control Panel'!$B$27*(1-'Control Panel'!$B$27)^0*IFERROR(INDEX($AW8:$BT8,1,'Control Panel'!$B$8-0),0)+'Control Panel'!$B$27*(1-'Control Panel'!$B$27)^1*IFERROR(INDEX($AW8:$BT8,1,'Control Panel'!$B$8-1),0)+'Control Panel'!$B$27*(1-'Control Panel'!$B$27)^2*IFERROR(INDEX($AW8:$BT8,1,'Control Panel'!$B$8-2),0)+'Control Panel'!$B$27*(1-'Control Panel'!$B$27)^3*IFERROR(INDEX($AW8:$BT8,1,'Control Panel'!$B$8-3),0)+'Control Panel'!$B$27*(1-'Control Panel'!$B$27)^4*IFERROR(INDEX($AW8:$BT8,1,'Control Panel'!$B$8-4),0)+'Control Panel'!$B$27*(1-'Control Panel'!$B$27)^5*IFERROR(INDEX($AW8:$BT8,1,'Control Panel'!$B$8-5),0))/(1-(1-'Control Panel'!$B$27)^6))*O8)+'Control Panel'!$B$19*((D8+M8*1)*O8)+'Control Panel'!$B$20*(K8*O8)+'Control Panel'!$B$21*(D8*(1+N8)^1*O8)+'Control Panel'!$B$22*(I8*O8)+'Control Panel'!$B$23*(R8*(1+IFERROR(D8/H8-1,0))))/'Control Panel'!$B$24,0) | AC8: =IFERROR(('Control Panel'!$B$17*(('Control Panel'!$B$28*D8+'Control Panel'!$B$29*E8+'Control Panel'!$B$30*F8)*P8)+'Control Panel'!$B$18*((('Control Panel'!$B$27*(1-'Control Panel'!$B$27)^0*IFERROR(INDEX($AW8:$BT8,1,'Control Panel'!$B$8-0),0)+'Control Panel'!$B$27*(1-'Control Panel'!$B$27)^1*IFERROR(INDEX($AW8:$BT8,1,'Control Panel'!$B$8-1),0)+'Control Panel'!$B$27*(1-'Control Panel'!$B$27)^2*IFERROR(INDEX($AW8:$BT8,1,'Control Panel'!$B$8-2),0)+'Control Panel'!$B$27*(1-'Control Panel'!$B$27)^3*IFERROR(INDEX($AW8:$BT8,1,'Control Panel'!$B$8-3),0)+'Control Panel'!$B$27*(1-'Control Panel'!$B$27)^4*IFERROR(INDEX($AW8:$BT8,1,'Control Panel'!$B$8-4),0)+'Control Panel'!$B$27*(1-'Control Panel'!$B$27)^5*IFERROR(INDEX($AW8:$BT8,1,'Control Panel'!$B$8-5),0))/(1-(1-'Control Panel'!$B$27)^6))*P8)+'Control Panel'!$B$19*((D8+M8*2)*P8)+'Control Panel'!$B$20*(K8*P8)+'Control Panel'!$B$21*(D8*(1+N8)^2*P8)+'Control Panel'!$B$22*(I8*P8)+'Control Panel'!$B$23*(S8*(1+IFERROR(D8/H8-1,0))))/'Control Panel'!$B$24,0) | AD8: =IFERROR(('Control Panel'!$B$17*(('Control Panel'!$B$28*D8+'Control Panel'!$B$29*E8+'Control Panel'!$B$30*F8)*Q8)+'Control Panel'!$B$18*((('Control Panel'!$B$27*(1-'Control Panel'!$B$27)^0*IFERROR(INDEX($AW8:$BT8,1,'Control Panel'!$B$8-0),0)+'Control Panel'!$B$27*(1-'Control Panel'!$B$27)^1*IFERROR(INDEX($AW8:$BT8,1,'Control Panel'!$B$8-1),0)+'Control Panel'!$B$27*(1-'Control Panel'!$B$27)^2*IFERROR(INDEX($AW8:$BT8,1,'Control Panel'!$B$8-2),0)+'Control Panel'!$B$27*(1-'Control Panel'!$B$27)^3*IFERROR(INDEX($AW8:$BT8,1,'Control Panel'!$B$8-3),0)+'Control Panel'!$B$27*(1-'Control Panel'!$B$27)^4*IFERROR(INDEX($AW8:$BT8,1,'Control Panel'!$B$8-4),0)+'Control Panel'!$B$27*(1-'Control Panel'!$B$27)^5*IFERROR(INDEX($AW8:$BT8,1,'Control Panel'!$B$8-5),0))/(1-(1-'Control Panel'!$B$27)^6))*Q8)+'Control Panel'!$B$19*((D8+M8*3)*Q8)+'Control Panel'!$B$20*(K8*Q8)+'Control Panel'!$B$21*(D8*(1+N8)^3*Q8)+'Control Panel'!$B$22*(I8*Q8)+'Control Panel'!$B$23*(T8*(1+IFERROR(D8/H8-1,0))))/'Control Panel'!$B$24,0) | AE8: =MAX(0,AB8*(1+U8+V8)) | AF8: =MAX(0,AC8*(1+U8+W8)) | AG8: =MAX(0,AD8*(1+U8+X8)) | AH8: =IFERROR(('Control Panel'!$B$33*AB8+'Control Panel'!$B$34*AE8+'Control Panel'!$B$35*(AB8*(1+L8+V8)))/('Control Panel'!$B$33+'Control Panel'!$B$34+'Control Panel'!$B$35),0) | AI8: =IFERROR(('Control Panel'!$B$33*AC8+'Control Panel'!$B$34*AF8+'Control Panel'!$B$35*(AC8*(1+L8+W8)))/('Control Panel'!$B$33+'Control Panel'!$B$34+'Control Panel'!$B$35),0) | AJ8: =IFERROR(('Control Panel'!$B$33*AD8+'Control Panel'!$B$34*AG8+'Control Panel'!$B$35*(AD8*(1+L8+X8)))/('Control Panel'!$B$33+'Control Panel'!$B$34+'Control Panel'!$B$35),0) | AK8: =AH8*'Control Panel'!$B$39+Y8 | AL8: =AI8*'Control Panel'!$B$39+Z8 | AM8: =AJ8*'Control Panel'!$B$39+AA8 | AN8: =AH8*'Control Panel'!$B$40+Y8 | AO8: =AI8*'Control Panel'!$B$40+Z8 | AP8: =AJ8*'Control Panel'!$B$40+AA8 | AQ8: =AH8*'Control Panel'!$B$41+Y8 | AR8: =AI8*'Control Panel'!$B$41+Z8 | AS8: =AJ8*'Control Panel'!$B$41+AA8 | AT8: =AH8*'Control Panel'!$B$42+Y8 | AU8: =AI8*'Control Panel'!$B$42+Z8 | AV8: =AJ8*'Control Panel'!$B$42+AA8 | AW8: =SUMIFS('Primary Sales History'!$C$4:$C$33,'Primary Sales History'!$A$4:$A$33,$A8,'Primary Sales History'!$B$4:$B$33,$B8) | AX8: =SUMIFS('Primary Sales History'!$D$4:$D$33,'Primary Sales History'!$A$4:$A$33,$A8,'Primary Sales History'!$B$4:$B$33,$B8) | AY8: =SUMIFS('Primary Sales History'!$E$4:$E$33,'Primary Sales History'!$A$4:$A$33,$A8,'Primary Sales History'!$B$4:$B$33,$B8) | AZ8: =SUMIFS('Primary Sales History'!$F$4:$F$33,'Primary Sales History'!$A$4:$A$33,$A8,'Primary Sales History'!$B$4:$B$33,$B8) | BA8: =SUMIFS('Primary Sales History'!$G$4:$G$33,'Primary Sales History'!$A$4:$A$33,$A8,'Primary Sales History'!$B$4:$B$33,$B8) | BB8: =SUMIFS('Primary Sales History'!$H$4:$H$33,'Primary Sales History'!$A$4:$A$33,$A8,'Primary Sales History'!$B$4:$B$33,$B8) | BC8: =SUMIFS('Primary Sales History'!$I$4:$I$33,'Primary Sales History'!$A$4:$A$33,$A8,'Primary Sales History'!$B$4:$B$33,$B8) | BD8: =SUMIFS('Primary Sales History'!$J$4:$J$33,'Primary Sales History'!$A$4:$A$33,$A8,'Primary Sales History'!$B$4:$B$33,$B8) | BE8: =SUMIFS('Primary Sales History'!$K$4:$K$33,'Primary Sales History'!$A$4:$A$33,$A8,'Primary Sales History'!$B$4:$B$33,$B8) | BF8: =SUMIFS('Primary Sales History'!$L$4:$L$33,'Primary Sales History'!$A$4:$A$33,$A8,'Primary Sales History'!$B$4:$B$33,$B8) | BG8: =SUMIFS('Primary Sales History'!$M$4:$M$33,'Primary Sales History'!$A$4:$A$33,$A8,'Primary Sales History'!$B$4:$B$33,$B8) | BH8: =SUMIFS('Primary Sales History'!$N$4:$N$33,'Primary Sales History'!$A$4:$A$33,$A8,'Primary Sales History'!$B$4:$B$33,$B8) | BI8: =SUMIFS('Primary Sales History'!$O$4:$O$33,'Primary Sales History'!$A$4:$A$33,$A8,'Primary Sales History'!$B$4:$B$33,$B8) | BJ8: =SUMIFS('Primary Sales History'!$P$4:$P$33,'Primary Sales History'!$A$4:$A$33,$A8,'Primary Sales History'!$B$4:$B$33,$B8) | BK8: 0 | BL8: 0 | BM8: 0 | BN8: 0 | BO8: 0 | BP8: 0 | BQ8: 0 | BR8: 0 | BS8: 0 | BT8: 0
A9: Aqualogica | B9: Face | C9: Face | D9: =IFERROR(INDEX($AW9:$BT9,1,'Control Panel'!$B$8-0),0) | E9: =IFERROR(INDEX($AW9:$BT9,1,'Control Panel'!$B$8-1),0) | F9: =IFERROR(INDEX($AW9:$BT9,1,'Control Panel'!$B$8-2),0) | G9: =IFERROR(INDEX($AW9:$BT9,1,'Control Panel'!$B$8-5),0) | H9: =IFERROR(INDEX($AW9:$BT9,1,'Control Panel'!$B$8-11),0) | I9: =AVERAGE(D9,E9,F9) | J9: =(D9+E9+F9+IFERROR(INDEX($AW9:$BT9,1,'Control Panel'!$B$8-3),0)+IFERROR(INDEX($AW9:$BT9,1,'Control Panel'!$B$8-4),0)+G9)/6 | K9: =(IFERROR(INDEX($AW9:$BT9,1,'Control Panel'!$B$8-0),0)+IFERROR(INDEX($AW9:$BT9,1,'Control Panel'!$B$8-1),0)+IFERROR(INDEX($AW9:$BT9,1,'Control Panel'!$B$8-2),0)+IFERROR(INDEX($AW9:$BT9,1,'Control Panel'!$B$8-3),0)+IFERROR(INDEX($AW9:$BT9,1,'Control Panel'!$B$8-4),0)+IFERROR(INDEX($AW9:$BT9,1,'Control Panel'!$B$8-5),0)+IFERROR(INDEX($AW9:$BT9,1,'Control Panel'!$B$8-6),0)+IFERROR(INDEX($AW9:$BT9,1,'Control Panel'!$B$8-7),0)+IFERROR(INDEX($AW9:$BT9,1,'Control Panel'!$B$8-8),0)+IFERROR(INDEX($AW9:$BT9,1,'Control Panel'!$B$8-9),0)+IFERROR(INDEX($AW9:$BT9,1,'Control Panel'!$B$8-10),0)+IFERROR(INDEX($AW9:$BT9,1,'Control Panel'!$B$8-11),0))/12 | L9: =IFERROR(MAX(-'Control Panel'!$B$36,MIN('Control Panel'!$B$36,(I9-J9)/J9)),0) | M9: =(D9-G9)/5 | N9: =IFERROR(IF(H9>0,(D9/H9)^(1/12)-1,0),0) | O9: =IFERROR((IFERROR(INDEX('Seasonality Matrix'!$B$4:$M$11,MATCH($C9,'Seasonality Matrix'!$A$4:$A$11,0),MATCH('Control Panel'!$B$12,'Seasonality Matrix'!$B$3:$M$3,0)),1))/(IFERROR(AVERAGE(INDEX('Seasonality Matrix'!$B$4:$M$11,MATCH($C9,'Seasonality Matrix'!$A$4:$A$11,0),0)),1)),1) | P9: =IFERROR((IFERROR(INDEX('Seasonality Matrix'!$B$4:$M$11,MATCH($C9,'Seasonality Matrix'!$A$4:$A$11,0),MATCH('Control Panel'!$B$13,'Seasonality Matrix'!$B$3:$M$3,0)),1))/(IFERROR(AVERAGE(INDEX('Seasonality Matrix'!$B$4:$M$11,MATCH($C9,'Seasonality Matrix'!$A$4:$A$11,0),0)),1)),1) | Q9: =IFERROR((IFERROR(INDEX('Seasonality Matrix'!$B$4:$M$11,MATCH($C9,'Seasonality Matrix'!$A$4:$A$11,0),MATCH('Control Panel'!$B$14,'Seasonality Matrix'!$B$3:$M$3,0)),1))/(IFERROR(AVERAGE(INDEX('Seasonality Matrix'!$B$4:$M$11,MATCH($C9,'Seasonality Matrix'!$A$4:$A$11,0),0)),1)),1) | R9: =IFERROR(INDEX($AW9:$BT9,1,'Control Panel'!$B$9-12),0) | S9: =IFERROR(INDEX($AW9:$BT9,1,'Control Panel'!$B$10-12),0) | T9: =IFERROR(INDEX($AW9:$BT9,1,'Control Panel'!$B$11-12),0) | U9: ='Control Panel'!$B$45 | V9: =IFERROR(SUMIFS('Promotion Calendar'!$G$4:$G$12,'Promotion Calendar'!$A$4:$A$12,$A9,'Promotion Calendar'!$B$4:$B$12,$B9,'Promotion Calendar'!$C$4:$C$12,'Control Panel'!$B$4),0) | W9: =IFERROR(SUMIFS('Promotion Calendar'!$G$4:$G$12,'Promotion Calendar'!$A$4:$A$12,$A9,'Promotion Calendar'!$B$4:$B$12,$B9,'Promotion Calendar'!$C$4:$C$12,'Control Panel'!$B$6),0) | X9: =IFERROR(SUMIFS('Promotion Calendar'!$G$4:$G$12,'Promotion Calendar'!$A$4:$A$12,$A9,'Promotion Calendar'!$B$4:$B$12,$B9,'Promotion Calendar'!$C$4:$C$12,'Control Panel'!$B$7),0) | Y9: =IFERROR(SUMIFS('NPI & EPD Planning'!$I$4:$I$10,'NPI & EPD Planning'!$A$4:$A$10,$A9,'NPI & EPD Planning'!$B$4:$B$10,$B9,'NPI & EPD Planning'!$D$4:$D$10,'Control Panel'!$B$4),0) | Z9: =IFERROR(SUMIFS('NPI & EPD Planning'!$I$4:$I$10,'NPI & EPD Planning'!$A$4:$A$10,$A9,'NPI & EPD Planning'!$B$4:$B$10,$B9,'NPI & EPD Planning'!$D$4:$D$10,'Control Panel'!$B$6),0) | AA9: =IFERROR(SUMIFS('NPI & EPD Planning'!$I$4:$I$10,'NPI & EPD Planning'!$A$4:$A$10,$A9,'NPI & EPD Planning'!$B$4:$B$10,$B9,'NPI & EPD Planning'!$D$4:$D$10,'Control Panel'!$B$7),0) | AB9: =IFERROR(('Control Panel'!$B$17*(('Control Panel'!$B$28*D9+'Control Panel'!$B$29*E9+'Control Panel'!$B$30*F9)*O9)+'Control Panel'!$B$18*((('Control Panel'!$B$27*(1-'Control Panel'!$B$27)^0*IFERROR(INDEX($AW9:$BT9,1,'Control Panel'!$B$8-0),0)+'Control Panel'!$B$27*(1-'Control Panel'!$B$27)^1*IFERROR(INDEX($AW9:$BT9,1,'Control Panel'!$B$8-1),0)+'Control Panel'!$B$27*(1-'Control Panel'!$B$27)^2*IFERROR(INDEX($AW9:$BT9,1,'Control Panel'!$B$8-2),0)+'Control Panel'!$B$27*(1-'Control Panel'!$B$27)^3*IFERROR(INDEX($AW9:$BT9,1,'Control Panel'!$B$8-3),0)+'Control Panel'!$B$27*(1-'Control Panel'!$B$27)^4*IFERROR(INDEX($AW9:$BT9,1,'Control Panel'!$B$8-4),0)+'Control Panel'!$B$27*(1-'Control Panel'!$B$27)^5*IFERROR(INDEX($AW9:$BT9,1,'Control Panel'!$B$8-5),0))/(1-(1-'Control Panel'!$B$27)^6))*O9)+'Control Panel'!$B$19*((D9+M9*1)*O9)+'Control Panel'!$B$20*(K9*O9)+'Control Panel'!$B$21*(D9*(1+N9)^1*O9)+'Control Panel'!$B$22*(I9*O9)+'Control Panel'!$B$23*(R9*(1+IFERROR(D9/H9-1,0))))/'Control Panel'!$B$24,0) | AC9: =IFERROR(('Control Panel'!$B$17*(('Control Panel'!$B$28*D9+'Control Panel'!$B$29*E9+'Control Panel'!$B$30*F9)*P9)+'Control Panel'!$B$18*((('Control Panel'!$B$27*(1-'Control Panel'!$B$27)^0*IFERROR(INDEX($AW9:$BT9,1,'Control Panel'!$B$8-0),0)+'Control Panel'!$B$27*(1-'Control Panel'!$B$27)^1*IFERROR(INDEX($AW9:$BT9,1,'Control Panel'!$B$8-1),0)+'Control Panel'!$B$27*(1-'Control Panel'!$B$27)^2*IFERROR(INDEX($AW9:$BT9,1,'Control Panel'!$B$8-2),0)+'Control Panel'!$B$27*(1-'Control Panel'!$B$27)^3*IFERROR(INDEX($AW9:$BT9,1,'Control Panel'!$B$8-3),0)+'Control Panel'!$B$27*(1-'Control Panel'!$B$27)^4*IFERROR(INDEX($AW9:$BT9,1,'Control Panel'!$B$8-4),0)+'Control Panel'!$B$27*(1-'Control Panel'!$B$27)^5*IFERROR(INDEX($AW9:$BT9,1,'Control Panel'!$B$8-5),0))/(1-(1-'Control Panel'!$B$27)^6))*P9)+'Control Panel'!$B$19*((D9+M9*2)*P9)+'Control Panel'!$B$20*(K9*P9)+'Control Panel'!$B$21*(D9*(1+N9)^2*P9)+'Control Panel'!$B$22*(I9*P9)+'Control Panel'!$B$23*(S9*(1+IFERROR(D9/H9-1,0))))/'Control Panel'!$B$24,0) | AD9: =IFERROR(('Control Panel'!$B$17*(('Control Panel'!$B$28*D9+'Control Panel'!$B$29*E9+'Control Panel'!$B$30*F9)*Q9)+'Control Panel'!$B$18*((('Control Panel'!$B$27*(1-'Control Panel'!$B$27)^0*IFERROR(INDEX($AW9:$BT9,1,'Control Panel'!$B$8-0),0)+'Control Panel'!$B$27*(1-'Control Panel'!$B$27)^1*IFERROR(INDEX($AW9:$BT9,1,'Control Panel'!$B$8-1),0)+'Control Panel'!$B$27*(1-'Control Panel'!$B$27)^2*IFERROR(INDEX($AW9:$BT9,1,'Control Panel'!$B$8-2),0)+'Control Panel'!$B$27*(1-'Control Panel'!$B$27)^3*IFERROR(INDEX($AW9:$BT9,1,'Control Panel'!$B$8-3),0)+'Control Panel'!$B$27*(1-'Control Panel'!$B$27)^4*IFERROR(INDEX($AW9:$BT9,1,'Control Panel'!$B$8-4),0)+'Control Panel'!$B$27*(1-'Control Panel'!$B$27)^5*IFERROR(INDEX($AW9:$BT9,1,'Control Panel'!$B$8-5),0))/(1-(1-'Control Panel'!$B$27)^6))*Q9)+'Control Panel'!$B$19*((D9+M9*3)*Q9)+'Control Panel'!$B$20*(K9*Q9)+'Control Panel'!$B$21*(D9*(1+N9)^3*Q9)+'Control Panel'!$B$22*(I9*Q9)+'Control Panel'!$B$23*(T9*(1+IFERROR(D9/H9-1,0))))/'Control Panel'!$B$24,0) | AE9: =MAX(0,AB9*(1+U9+V9)) | AF9: =MAX(0,AC9*(1+U9+W9)) | AG9: =MAX(0,AD9*(1+U9+X9)) | AH9: =IFERROR(('Control Panel'!$B$33*AB9+'Control Panel'!$B$34*AE9+'Control Panel'!$B$35*(AB9*(1+L9+V9)))/('Control Panel'!$B$33+'Control Panel'!$B$34+'Control Panel'!$B$35),0) | AI9: =IFERROR(('Control Panel'!$B$33*AC9+'Control Panel'!$B$34*AF9+'Control Panel'!$B$35*(AC9*(1+L9+W9)))/('Control Panel'!$B$33+'Control Panel'!$B$34+'Control Panel'!$B$35),0) | AJ9: =IFERROR(('Control Panel'!$B$33*AD9+'Control Panel'!$B$34*AG9+'Control Panel'!$B$35*(AD9*(1+L9+X9)))/('Control Panel'!$B$33+'Control Panel'!$B$34+'Control Panel'!$B$35),0) | AK9: =AH9*'Control Panel'!$B$39+Y9 | AL9: =AI9*'Control Panel'!$B$39+Z9 | AM9: =AJ9*'Control Panel'!$B$39+AA9 | AN9: =AH9*'Control Panel'!$B$40+Y9 | AO9: =AI9*'Control Panel'!$B$40+Z9 | AP9: =AJ9*'Control Panel'!$B$40+AA9 | AQ9: =AH9*'Control Panel'!$B$41+Y9 | AR9: =AI9*'Control Panel'!$B$41+Z9 | AS9: =AJ9*'Control Panel'!$B$41+AA9 | AT9: =AH9*'Control Panel'!$B$42+Y9 | AU9: =AI9*'Control Panel'!$B$42+Z9 | AV9: =AJ9*'Control Panel'!$B$42+AA9 | AW9: =SUMIFS('Primary Sales History'!$C$4:$C$33,'Primary Sales History'!$A$4:$A$33,$A9,'Primary Sales History'!$B$4:$B$33,$B9) | AX9: =SUMIFS('Primary Sales History'!$D$4:$D$33,'Primary Sales History'!$A$4:$A$33,$A9,'Primary Sales History'!$B$4:$B$33,$B9) | AY9: =SUMIFS('Primary Sales History'!$E$4:$E$33,'Primary Sales History'!$A$4:$A$33,$A9,'Primary Sales History'!$B$4:$B$33,$B9) | AZ9: =SUMIFS('Primary Sales History'!$F$4:$F$33,'Primary Sales History'!$A$4:$A$33,$A9,'Primary Sales History'!$B$4:$B$33,$B9) | BA9: =SUMIFS('Primary Sales History'!$G$4:$G$33,'Primary Sales History'!$A$4:$A$33,$A9,'Primary Sales History'!$B$4:$B$33,$B9) | BB9: =SUMIFS('Primary Sales History'!$H$4:$H$33,'Primary Sales History'!$A$4:$A$33,$A9,'Primary Sales History'!$B$4:$B$33,$B9) | BC9: =SUMIFS('Primary Sales History'!$I$4:$I$33,'Primary Sales History'!$A$4:$A$33,$A9,'Primary Sales History'!$B$4:$B$33,$B9) | BD9: =SUMIFS('Primary Sales History'!$J$4:$J$33,'Primary Sales History'!$A$4:$A$33,$A9,'Primary Sales History'!$B$4:$B$33,$B9) | BE9: =SUMIFS('Primary Sales History'!$K$4:$K$33,'Primary Sales History'!$A$4:$A$33,$A9,'Primary Sales History'!$B$4:$B$33,$B9) | BF9: =SUMIFS('Primary Sales History'!$L$4:$L$33,'Primary Sales History'!$A$4:$A$33,$A9,'Primary Sales History'!$B$4:$B$33,$B9) | BG9: =SUMIFS('Primary Sales History'!$M$4:$M$33,'Primary Sales History'!$A$4:$A$33,$A9,'Primary Sales History'!$B$4:$B$33,$B9) | BH9: =SUMIFS('Primary Sales History'!$N$4:$N$33,'Primary Sales History'!$A$4:$A$33,$A9,'Primary Sales History'!$B$4:$B$33,$B9) | BI9: =SUMIFS('Primary Sales History'!$O$4:$O$33,'Primary Sales History'!$A$4:$A$33,$A9,'Primary Sales History'!$B$4:$B$33,$B9) | BJ9: =SUMIFS('Primary Sales History'!$P$4:$P$33,'Primary Sales History'!$A$4:$A$33,$A9,'Primary Sales History'!$B$4:$B$33,$B9) | BK9: 0 | BL9: 0 | BM9: 0 | BN9: 0 | BO9: 0 | BP9: 0 | BQ9: 0 | BR9: 0 | BS9: 0 | BT9: 0
A10: BBLUNT | B10: Hair Care | C10: Hair Care | D10: =IFERROR(INDEX($AW10:$BT10,1,'Control Panel'!$B$8-0),0) | E10: =IFERROR(INDEX($AW10:$BT10,1,'Control Panel'!$B$8-1),0) | F10: =IFERROR(INDEX($AW10:$BT10,1,'Control Panel'!$B$8-2),0) | G10: =IFERROR(INDEX($AW10:$BT10,1,'Control Panel'!$B$8-5),0) | H10: =IFERROR(INDEX($AW10:$BT10,1,'Control Panel'!$B$8-11),0) | I10: =AVERAGE(D10,E10,F10) | J10: =(D10+E10+F10+IFERROR(INDEX($AW10:$BT10,1,'Control Panel'!$B$8-3),0)+IFERROR(INDEX($AW10:$BT10,1,'Control Panel'!$B$8-4),0)+G10)/6 | K10: =(IFERROR(INDEX($AW10:$BT10,1,'Control Panel'!$B$8-0),0)+IFERROR(INDEX($AW10:$BT10,1,'Control Panel'!$B$8-1),0)+IFERROR(INDEX($AW10:$BT10,1,'Control Panel'!$B$8-2),0)+IFERROR(INDEX($AW10:$BT10,1,'Control Panel'!$B$8-3),0)+IFERROR(INDEX($AW10:$BT10,1,'Control Panel'!$B$8-4),0)+IFERROR(INDEX($AW10:$BT10,1,'Control Panel'!$B$8-5),0)+IFERROR(INDEX($AW10:$BT10,1,'Control Panel'!$B$8-6),0)+IFERROR(INDEX($AW10:$BT10,1,'Control Panel'!$B$8-7),0)+IFERROR(INDEX($AW10:$BT10,1,'Control Panel'!$B$8-8),0)+IFERROR(INDEX($AW10:$BT10,1,'Control Panel'!$B$8-9),0)+IFERROR(INDEX($AW10:$BT10,1,'Control Panel'!$B$8-10),0)+IFERROR(INDEX($AW10:$BT10,1,'Control Panel'!$B$8-11),0))/12 | L10: =IFERROR(MAX(-'Control Panel'!$B$36,MIN('Control Panel'!$B$36,(I10-J10)/J10)),0) | M10: =(D10-G10)/5 | N10: =IFERROR(IF(H10>0,(D10/H10)^(1/12)-1,0),0) | O10: =IFERROR((IFERROR(INDEX('Seasonality Matrix'!$B$4:$M$11,MATCH($C10,'Seasonality Matrix'!$A$4:$A$11,0),MATCH('Control Panel'!$B$12,'Seasonality Matrix'!$B$3:$M$3,0)),1))/(IFERROR(AVERAGE(INDEX('Seasonality Matrix'!$B$4:$M$11,MATCH($C10,'Seasonality Matrix'!$A$4:$A$11,0),0)),1)),1) | P10: =IFERROR((IFERROR(INDEX('Seasonality Matrix'!$B$4:$M$11,MATCH($C10,'Seasonality Matrix'!$A$4:$A$11,0),MATCH('Control Panel'!$B$13,'Seasonality Matrix'!$B$3:$M$3,0)),1))/(IFERROR(AVERAGE(INDEX('Seasonality Matrix'!$B$4:$M$11,MATCH($C10,'Seasonality Matrix'!$A$4:$A$11,0),0)),1)),1) | Q10: =IFERROR((IFERROR(INDEX('Seasonality Matrix'!$B$4:$M$11,MATCH($C10,'Seasonality Matrix'!$A$4:$A$11,0),MATCH('Control Panel'!$B$14,'Seasonality Matrix'!$B$3:$M$3,0)),1))/(IFERROR(AVERAGE(INDEX('Seasonality Matrix'!$B$4:$M$11,MATCH($C10,'Seasonality Matrix'!$A$4:$A$11,0),0)),1)),1) | R10: =IFERROR(INDEX($AW10:$BT10,1,'Control Panel'!$B$9-12),0) | S10: =IFERROR(INDEX($AW10:$BT10,1,'Control Panel'!$B$10-12),0) | T10: =IFERROR(INDEX($AW10:$BT10,1,'Control Panel'!$B$11-12),0) | U10: ='Control Panel'!$B$45 | V10: =IFERROR(SUMIFS('Promotion Calendar'!$G$4:$G$12,'Promotion Calendar'!$A$4:$A$12,$A10,'Promotion Calendar'!$B$4:$B$12,$B10,'Promotion Calendar'!$C$4:$C$12,'Control Panel'!$B$4),0) | W10: =IFERROR(SUMIFS('Promotion Calendar'!$G$4:$G$12,'Promotion Calendar'!$A$4:$A$12,$A10,'Promotion Calendar'!$B$4:$B$12,$B10,'Promotion Calendar'!$C$4:$C$12,'Control Panel'!$B$6),0) | X10: =IFERROR(SUMIFS('Promotion Calendar'!$G$4:$G$12,'Promotion Calendar'!$A$4:$A$12,$A10,'Promotion Calendar'!$B$4:$B$12,$B10,'Promotion Calendar'!$C$4:$C$12,'Control Panel'!$B$7),0) | Y10: =IFERROR(SUMIFS('NPI & EPD Planning'!$I$4:$I$10,'NPI & EPD Planning'!$A$4:$A$10,$A10,'NPI & EPD Planning'!$B$4:$B$10,$B10,'NPI & EPD Planning'!$D$4:$D$10,'Control Panel'!$B$4),0) | Z10: =IFERROR(SUMIFS('NPI & EPD Planning'!$I$4:$I$10,'NPI & EPD Planning'!$A$4:$A$10,$A10,'NPI & EPD Planning'!$B$4:$B$10,$B10,'NPI & EPD Planning'!$D$4:$D$10,'Control Panel'!$B$6),0) | AA10: =IFERROR(SUMIFS('NPI & EPD Planning'!$I$4:$I$10,'NPI & EPD Planning'!$A$4:$A$10,$A10,'NPI & EPD Planning'!$B$4:$B$10,$B10,'NPI & EPD Planning'!$D$4:$D$10,'Control Panel'!$B$7),0) | AB10: =IFERROR(('Control Panel'!$B$17*(('Control Panel'!$B$28*D10+'Control Panel'!$B$29*E10+'Control Panel'!$B$30*F10)*O10)+'Control Panel'!$B$18*((('Control Panel'!$B$27*(1-'Control Panel'!$B$27)^0*IFERROR(INDEX($AW10:$BT10,1,'Control Panel'!$B$8-0),0)+'Control Panel'!$B$27*(1-'Control Panel'!$B$27)^1*IFERROR(INDEX($AW10:$BT10,1,'Control Panel'!$B$8-1),0)+'Control Panel'!$B$27*(1-'Control Panel'!$B$27)^2*IFERROR(INDEX($AW10:$BT10,1,'Control Panel'!$B$8-2),0)+'Control Panel'!$B$27*(1-'Control Panel'!$B$27)^3*IFERROR(INDEX($AW10:$BT10,1,'Control Panel'!$B$8-3),0)+'Control Panel'!$B$27*(1-'Control Panel'!$B$27)^4*IFERROR(INDEX($AW10:$BT10,1,'Control Panel'!$B$8-4),0)+'Control Panel'!$B$27*(1-'Control Panel'!$B$27)^5*IFERROR(INDEX($AW10:$BT10,1,'Control Panel'!$B$8-5),0))/(1-(1-'Control Panel'!$B$27)^6))*O10)+'Control Panel'!$B$19*((D10+M10*1)*O10)+'Control Panel'!$B$20*(K10*O10)+'Control Panel'!$B$21*(D10*(1+N10)^1*O10)+'Control Panel'!$B$22*(I10*O10)+'Control Panel'!$B$23*(R10*(1+IFERROR(D10/H10-1,0))))/'Control Panel'!$B$24,0) | AC10: =IFERROR(('Control Panel'!$B$17*(('Control Panel'!$B$28*D10+'Control Panel'!$B$29*E10+'Control Panel'!$B$30*F10)*P10)+'Control Panel'!$B$18*((('Control Panel'!$B$27*(1-'Control Panel'!$B$27)^0*IFERROR(INDEX($AW10:$BT10,1,'Control Panel'!$B$8-0),0)+'Control Panel'!$B$27*(1-'Control Panel'!$B$27)^1*IFERROR(INDEX($AW10:$BT10,1,'Control Panel'!$B$8-1),0)+'Control Panel'!$B$27*(1-'Control Panel'!$B$27)^2*IFERROR(INDEX($AW10:$BT10,1,'Control Panel'!$B$8-2),0)+'Control Panel'!$B$27*(1-'Control Panel'!$B$27)^3*IFERROR(INDEX($AW10:$BT10,1,'Control Panel'!$B$8-3),0)+'Control Panel'!$B$27*(1-'Control Panel'!$B$27)^4*IFERROR(INDEX($AW10:$BT10,1,'Control Panel'!$B$8-4),0)+'Control Panel'!$B$27*(1-'Control Panel'!$B$27)^5*IFERROR(INDEX($AW10:$BT10,1,'Control Panel'!$B$8-5),0))/(1-(1-'Control Panel'!$B$27)^6))*P10)+'Control Panel'!$B$19*((D10+M10*2)*P10)+'Control Panel'!$B$20*(K10*P10)+'Control Panel'!$B$21*(D10*(1+N10)^2*P10)+'Control Panel'!$B$22*(I10*P10)+'Control Panel'!$B$23*(S10*(1+IFERROR(D10/H10-1,0))))/'Control Panel'!$B$24,0) | AD10: =IFERROR(('Control Panel'!$B$17*(('Control Panel'!$B$28*D10+'Control Panel'!$B$29*E10+'Control Panel'!$B$30*F10)*Q10)+'Control Panel'!$B$18*((('Control Panel'!$B$27*(1-'Control Panel'!$B$27)^0*IFERROR(INDEX($AW10:$BT10,1,'Control Panel'!$B$8-0),0)+'Control Panel'!$B$27*(1-'Control Panel'!$B$27)^1*IFERROR(INDEX($AW10:$BT10,1,'Control Panel'!$B$8-1),0)+'Control Panel'!$B$27*(1-'Control Panel'!$B$27)^2*IFERROR(INDEX($AW10:$BT10,1,'Control Panel'!$B$8-2),0)+'Control Panel'!$B$27*(1-'Control Panel'!$B$27)^3*IFERROR(INDEX($AW10:$BT10,1,'Control Panel'!$B$8-3),0)+'Control Panel'!$B$27*(1-'Control Panel'!$B$27)^4*IFERROR(INDEX($AW10:$BT10,1,'Control Panel'!$B$8-4),0)+'Control Panel'!$B$27*(1-'Control Panel'!$B$27)^5*IFERROR(INDEX($AW10:$BT10,1,'Control Panel'!$B$8-5),0))/(1-(1-'Control Panel'!$B$27)^6))*Q10)+'Control Panel'!$B$19*((D10+M10*3)*Q10)+'Control Panel'!$B$20*(K10*Q10)+'Control Panel'!$B$21*(D10*(1+N10)^3*Q10)+'Control Panel'!$B$22*(I10*Q10)+'Control Panel'!$B$23*(T10*(1+IFERROR(D10/H10-1,0))))/'Control Panel'!$B$24,0) | AE10: =MAX(0,AB10*(1+U10+V10)) | AF10: =MAX(0,AC10*(1+U10+W10)) | AG10: =MAX(0,AD10*(1+U10+X10)) | AH10: =IFERROR(('Control Panel'!$B$33*AB10+'Control Panel'!$B$34*AE10+'Control Panel'!$B$35*(AB10*(1+L10+V10)))/('Control Panel'!$B$33+'Control Panel'!$B$34+'Control Panel'!$B$35),0) | AI10: =IFERROR(('Control Panel'!$B$33*AC10+'Control Panel'!$B$34*AF10+'Control Panel'!$B$35*(AC10*(1+L10+W10)))/('Control Panel'!$B$33+'Control Panel'!$B$34+'Control Panel'!$B$35),0) | AJ10: =IFERROR(('Control Panel'!$B$33*AD10+'Control Panel'!$B$34*AG10+'Control Panel'!$B$35*(AD10*(1+L10+X10)))/('Control Panel'!$B$33+'Control Panel'!$B$34+'Control Panel'!$B$35),0) | AK10: =AH10*'Control Panel'!$B$39+Y10 | AL10: =AI10*'Control Panel'!$B$39+Z10 | AM10: =AJ10*'Control Panel'!$B$39+AA10 | AN10: =AH10*'Control Panel'!$B$40+Y10 | AO10: =AI10*'Control Panel'!$B$40+Z10 | AP10: =AJ10*'Control Panel'!$B$40+AA10 | AQ10: =AH10*'Control Panel'!$B$41+Y10 | AR10: =AI10*'Control Panel'!$B$41+Z10 | AS10: =AJ10*'Control Panel'!$B$41+AA10 | AT10: =AH10*'Control Panel'!$B$42+Y10 | AU10: =AI10*'Control Panel'!$B$42+Z10 | AV10: =AJ10*'Control Panel'!$B$42+AA10 | AW10: =SUMIFS('Primary Sales History'!$C$4:$C$33,'Primary Sales History'!$A$4:$A$33,$A10,'Primary Sales History'!$B$4:$B$33,$B10) | AX10: =SUMIFS('Primary Sales History'!$D$4:$D$33,'Primary Sales History'!$A$4:$A$33,$A10,'Primary Sales History'!$B$4:$B$33,$B10) | AY10: =SUMIFS('Primary Sales History'!$E$4:$E$33,'Primary Sales History'!$A$4:$A$33,$A10,'Primary Sales History'!$B$4:$B$33,$B10) | AZ10: =SUMIFS('Primary Sales History'!$F$4:$F$33,'Primary Sales History'!$A$4:$A$33,$A10,'Primary Sales History'!$B$4:$B$33,$B10) | BA10: =SUMIFS('Primary Sales History'!$G$4:$G$33,'Primary Sales History'!$A$4:$A$33,$A10,'Primary Sales History'!$B$4:$B$33,$B10) | BB10: =SUMIFS('Primary Sales History'!$H$4:$H$33,'Primary Sales History'!$A$4:$A$33,$A10,'Primary Sales History'!$B$4:$B$33,$B10) | BC10: =SUMIFS('Primary Sales History'!$I$4:$I$33,'Primary Sales History'!$A$4:$A$33,$A10,'Primary Sales History'!$B$4:$B$33,$B10) | BD10: =SUMIFS('Primary Sales History'!$J$4:$J$33,'Primary Sales History'!$A$4:$A$33,$A10,'Primary Sales History'!$B$4:$B$33,$B10) | BE10: =SUMIFS('Primary Sales History'!$K$4:$K$33,'Primary Sales History'!$A$4:$A$33,$A10,'Primary Sales History'!$B$4:$B$33,$B10) | BF10: =SUMIFS('Primary Sales History'!$L$4:$L$33,'Primary Sales History'!$A$4:$A$33,$A10,'Primary Sales History'!$B$4:$B$33,$B10) | BG10: =SUMIFS('Primary Sales History'!$M$4:$M$33,'Primary Sales History'!$A$4:$A$33,$A10,'Primary Sales History'!$B$4:$B$33,$B10) | BH10: =SUMIFS('Primary Sales History'!$N$4:$N$33,'Primary Sales History'!$A$4:$A$33,$A10,'Primary Sales History'!$B$4:$B$33,$B10) | BI10: =SUMIFS('Primary Sales History'!$O$4:$O$33,'Primary Sales History'!$A$4:$A$33,$A10,'Primary Sales History'!$B$4:$B$33,$B10) | BJ10: =SUMIFS('Primary Sales History'!$P$4:$P$33,'Primary Sales History'!$A$4:$A$33,$A10,'Primary Sales History'!$B$4:$B$33,$B10) | BK10: 0 | BL10: 0 | BM10: 0 | BN10: 0 | BO10: 0 | BP10: 0 | BQ10: 0 | BR10: 0 | BS10: 0 | BT10: 0
A11: Mamaearth | B11: Fragrances | C11: Fragrances | D11: =IFERROR(INDEX($AW11:$BT11,1,'Control Panel'!$B$8-0),0) | E11: =IFERROR(INDEX($AW11:$BT11,1,'Control Panel'!$B$8-1),0) | F11: =IFERROR(INDEX($AW11:$BT11,1,'Control Panel'!$B$8-2),0) | G11: =IFERROR(INDEX($AW11:$BT11,1,'Control Panel'!$B$8-5),0) | H11: =IFERROR(INDEX($AW11:$BT11,1,'Control Panel'!$B$8-11),0) | I11: =AVERAGE(D11,E11,F11) | J11: =(D11+E11+F11+IFERROR(INDEX($AW11:$BT11,1,'Control Panel'!$B$8-3),0)+IFERROR(INDEX($AW11:$BT11,1,'Control Panel'!$B$8-4),0)+G11)/6 | K11: =(IFERROR(INDEX($AW11:$BT11,1,'Control Panel'!$B$8-0),0)+IFERROR(INDEX($AW11:$BT11,1,'Control Panel'!$B$8-1),0)+IFERROR(INDEX($AW11:$BT11,1,'Control Panel'!$B$8-2),0)+IFERROR(INDEX($AW11:$BT11,1,'Control Panel'!$B$8-3),0)+IFERROR(INDEX($AW11:$BT11,1,'Control Panel'!$B$8-4),0)+IFERROR(INDEX($AW11:$BT11,1,'Control Panel'!$B$8-5),0)+IFERROR(INDEX($AW11:$BT11,1,'Control Panel'!$B$8-6),0)+IFERROR(INDEX($AW11:$BT11,1,'Control Panel'!$B$8-7),0)+IFERROR(INDEX($AW11:$BT11,1,'Control Panel'!$B$8-8),0)+IFERROR(INDEX($AW11:$BT11,1,'Control Panel'!$B$8-9),0)+IFERROR(INDEX($AW11:$BT11,1,'Control Panel'!$B$8-10),0)+IFERROR(INDEX($AW11:$BT11,1,'Control Panel'!$B$8-11),0))/12 | L11: =IFERROR(MAX(-'Control Panel'!$B$36,MIN('Control Panel'!$B$36,(I11-J11)/J11)),0) | M11: =(D11-G11)/5 | N11: =IFERROR(IF(H11>0,(D11/H11)^(1/12)-1,0),0) | O11: =IFERROR((IFERROR(INDEX('Seasonality Matrix'!$B$4:$M$11,MATCH($C11,'Seasonality Matrix'!$A$4:$A$11,0),MATCH('Control Panel'!$B$12,'Seasonality Matrix'!$B$3:$M$3,0)),1))/(IFERROR(AVERAGE(INDEX('Seasonality Matrix'!$B$4:$M$11,MATCH($C11,'Seasonality Matrix'!$A$4:$A$11,0),0)),1)),1) | P11: =IFERROR((IFERROR(INDEX('Seasonality Matrix'!$B$4:$M$11,MATCH($C11,'Seasonality Matrix'!$A$4:$A$11,0),MATCH('Control Panel'!$B$13,'Seasonality Matrix'!$B$3:$M$3,0)),1))/(IFERROR(AVERAGE(INDEX('Seasonality Matrix'!$B$4:$M$11,MATCH($C11,'Seasonality Matrix'!$A$4:$A$11,0),0)),1)),1) | Q11: =IFERROR((IFERROR(INDEX('Seasonality Matrix'!$B$4:$M$11,MATCH($C11,'Seasonality Matrix'!$A$4:$A$11,0),MATCH('Control Panel'!$B$14,'Seasonality Matrix'!$B$3:$M$3,0)),1))/(IFERROR(AVERAGE(INDEX('Seasonality Matrix'!$B$4:$M$11,MATCH($C11,'Seasonality Matrix'!$A$4:$A$11,0),0)),1)),1) | R11: =IFERROR(INDEX($AW11:$BT11,1,'Control Panel'!$B$9-12),0) | S11: =IFERROR(INDEX($AW11:$BT11,1,'Control Panel'!$B$10-12),0) | T11: =IFERROR(INDEX($AW11:$BT11,1,'Control Panel'!$B$11-12),0) | U11: ='Control Panel'!$B$45 | V11: =IFERROR(SUMIFS('Promotion Calendar'!$G$4:$G$12,'Promotion Calendar'!$A$4:$A$12,$A11,'Promotion Calendar'!$B$4:$B$12,$B11,'Promotion Calendar'!$C$4:$C$12,'Control Panel'!$B$4),0) | W11: =IFERROR(SUMIFS('Promotion Calendar'!$G$4:$G$12,'Promotion Calendar'!$A$4:$A$12,$A11,'Promotion Calendar'!$B$4:$B$12,$B11,'Promotion Calendar'!$C$4:$C$12,'Control Panel'!$B$6),0) | X11: =IFERROR(SUMIFS('Promotion Calendar'!$G$4:$G$12,'Promotion Calendar'!$A$4:$A$12,$A11,'Promotion Calendar'!$B$4:$B$12,$B11,'Promotion Calendar'!$C$4:$C$12,'Control Panel'!$B$7),0) | Y11: =IFERROR(SUMIFS('NPI & EPD Planning'!$I$4:$I$10,'NPI & EPD Planning'!$A$4:$A$10,$A11,'NPI & EPD Planning'!$B$4:$B$10,$B11,'NPI & EPD Planning'!$D$4:$D$10,'Control Panel'!$B$4),0) | Z11: =IFERROR(SUMIFS('NPI & EPD Planning'!$I$4:$I$10,'NPI & EPD Planning'!$A$4:$A$10,$A11,'NPI & EPD Planning'!$B$4:$B$10,$B11,'NPI & EPD Planning'!$D$4:$D$10,'Control Panel'!$B$6),0) | AA11: =IFERROR(SUMIFS('NPI & EPD Planning'!$I$4:$I$10,'NPI & EPD Planning'!$A$4:$A$10,$A11,'NPI & EPD Planning'!$B$4:$B$10,$B11,'NPI & EPD Planning'!$D$4:$D$10,'Control Panel'!$B$7),0) | AB11: =IFERROR(('Control Panel'!$B$17*(('Control Panel'!$B$28*D11+'Control Panel'!$B$29*E11+'Control Panel'!$B$30*F11)*O11)+'Control Panel'!$B$18*((('Control Panel'!$B$27*(1-'Control Panel'!$B$27)^0*IFERROR(INDEX($AW11:$BT11,1,'Control Panel'!$B$8-0),0)+'Control Panel'!$B$27*(1-'Control Panel'!$B$27)^1*IFERROR(INDEX($AW11:$BT11,1,'Control Panel'!$B$8-1),0)+'Control Panel'!$B$27*(1-'Control Panel'!$B$27)^2*IFERROR(INDEX($AW11:$BT11,1,'Control Panel'!$B$8-2),0)+'Control Panel'!$B$27*(1-'Control Panel'!$B$27)^3*IFERROR(INDEX($AW11:$BT11,1,'Control Panel'!$B$8-3),0)+'Control Panel'!$B$27*(1-'Control Panel'!$B$27)^4*IFERROR(INDEX($AW11:$BT11,1,'Control Panel'!$B$8-4),0)+'Control Panel'!$B$27*(1-'Control Panel'!$B$27)^5*IFERROR(INDEX($AW11:$BT11,1,'Control Panel'!$B$8-5),0))/(1-(1-'Control Panel'!$B$27)^6))*O11)+'Control Panel'!$B$19*((D11+M11*1)*O11)+'Control Panel'!$B$20*(K11*O11)+'Control Panel'!$B$21*(D11*(1+N11)^1*O11)+'Control Panel'!$B$22*(I11*O11)+'Control Panel'!$B$23*(R11*(1+IFERROR(D11/H11-1,0))))/'Control Panel'!$B$24,0) | AC11: =IFERROR(('Control Panel'!$B$17*(('Control Panel'!$B$28*D11+'Control Panel'!$B$29*E11+'Control Panel'!$B$30*F11)*P11)+'Control Panel'!$B$18*((('Control Panel'!$B$27*(1-'Control Panel'!$B$27)^0*IFERROR(INDEX($AW11:$BT11,1,'Control Panel'!$B$8-0),0)+'Control Panel'!$B$27*(1-'Control Panel'!$B$27)^1*IFERROR(INDEX($AW11:$BT11,1,'Control Panel'!$B$8-1),0)+'Control Panel'!$B$27*(1-'Control Panel'!$B$27)^2*IFERROR(INDEX($AW11:$BT11,1,'Control Panel'!$B$8-2),0)+'Control Panel'!$B$27*(1-'Control Panel'!$B$27)^3*IFERROR(INDEX($AW11:$BT11,1,'Control Panel'!$B$8-3),0)+'Control Panel'!$B$27*(1-'Control Panel'!$B$27)^4*IFERROR(INDEX($AW11:$BT11,1,'Control Panel'!$B$8-4),0)+'Control Panel'!$B$27*(1-'Control Panel'!$B$27)^5*IFERROR(INDEX($AW11:$BT11,1,'Control Panel'!$B$8-5),0))/(1-(1-'Control Panel'!$B$27)^6))*P11)+'Control Panel'!$B$19*((D11+M11*2)*P11)+'Control Panel'!$B$20*(K11*P11)+'Control Panel'!$B$21*(D11*(1+N11)^2*P11)+'Control Panel'!$B$22*(I11*P11)+'Control Panel'!$B$23*(S11*(1+IFERROR(D11/H11-1,0))))/'Control Panel'!$B$24,0) | AD11: =IFERROR(('Control Panel'!$B$17*(('Control Panel'!$B$28*D11+'Control Panel'!$B$29*E11+'Control Panel'!$B$30*F11)*Q11)+'Control Panel'!$B$18*((('Control Panel'!$B$27*(1-'Control Panel'!$B$27)^0*IFERROR(INDEX($AW11:$BT11,1,'Control Panel'!$B$8-0),0)+'Control Panel'!$B$27*(1-'Control Panel'!$B$27)^1*IFERROR(INDEX($AW11:$BT11,1,'Control Panel'!$B$8-1),0)+'Control Panel'!$B$27*(1-'Control Panel'!$B$27)^2*IFERROR(INDEX($AW11:$BT11,1,'Control Panel'!$B$8-2),0)+'Control Panel'!$B$27*(1-'Control Panel'!$B$27)^3*IFERROR(INDEX($AW11:$BT11,1,'Control Panel'!$B$8-3),0)+'Control Panel'!$B$27*(1-'Control Panel'!$B$27)^4*IFERROR(INDEX($AW11:$BT11,1,'Control Panel'!$B$8-4),0)+'Control Panel'!$B$27*(1-'Control Panel'!$B$27)^5*IFERROR(INDEX($AW11:$BT11,1,'Control Panel'!$B$8-5),0))/(1-(1-'Control Panel'!$B$27)^6))*Q11)+'Control Panel'!$B$19*((D11+M11*3)*Q11)+'Control Panel'!$B$20*(K11*Q11)+'Control Panel'!$B$21*(D11*(1+N11)^3*Q11)+'Control Panel'!$B$22*(I11*Q11)+'Control Panel'!$B$23*(T11*(1+IFERROR(D11/H11-1,0))))/'Control Panel'!$B$24,0) | AE11: =MAX(0,AB11*(1+U11+V11)) | AF11: =MAX(0,AC11*(1+U11+W11)) | AG11: =MAX(0,AD11*(1+U11+X11)) | AH11: =IFERROR(('Control Panel'!$B$33*AB11+'Control Panel'!$B$34*AE11+'Control Panel'!$B$35*(AB11*(1+L11+V11)))/('Control Panel'!$B$33+'Control Panel'!$B$34+'Control Panel'!$B$35),0) | AI11: =IFERROR(('Control Panel'!$B$33*AC11+'Control Panel'!$B$34*AF11+'Control Panel'!$B$35*(AC11*(1+L11+W11)))/('Control Panel'!$B$33+'Control Panel'!$B$34+'Control Panel'!$B$35),0) | AJ11: =IFERROR(('Control Panel'!$B$33*AD11+'Control Panel'!$B$34*AG11+'Control Panel'!$B$35*(AD11*(1+L11+X11)))/('Control Panel'!$B$33+'Control Panel'!$B$34+'Control Panel'!$B$35),0) | AK11: =AH11*'Control Panel'!$B$39+Y11 | AL11: =AI11*'Control Panel'!$B$39+Z11 | AM11: =AJ11*'Control Panel'!$B$39+AA11 | AN11: =AH11*'Control Panel'!$B$40+Y11 | AO11: =AI11*'Control Panel'!$B$40+Z11 | AP11: =AJ11*'Control Panel'!$B$40+AA11 | AQ11: =AH11*'Control Panel'!$B$41+Y11 | AR11: =AI11*'Control Panel'!$B$41+Z11 | AS11: =AJ11*'Control Panel'!$B$41+AA11 | AT11: =AH11*'Control Panel'!$B$42+Y11 | AU11: =AI11*'Control Panel'!$B$42+Z11 | AV11: =AJ11*'Control Panel'!$B$42+AA11 | AW11: =SUMIFS('Primary Sales History'!$C$4:$C$33,'Primary Sales History'!$A$4:$A$33,$A11,'Primary Sales History'!$B$4:$B$33,$B11) | AX11: =SUMIFS('Primary Sales History'!$D$4:$D$33,'Primary Sales History'!$A$4:$A$33,$A11,'Primary Sales History'!$B$4:$B$33,$B11) | AY11: =SUMIFS('Primary Sales History'!$E$4:$E$33,'Primary Sales History'!$A$4:$A$33,$A11,'Primary Sales History'!$B$4:$B$33,$B11) | AZ11: =SUMIFS('Primary Sales History'!$F$4:$F$33,'Primary Sales History'!$A$4:$A$33,$A11,'Primary Sales History'!$B$4:$B$33,$B11) | BA11: =SUMIFS('Primary Sales History'!$G$4:$G$33,'Primary Sales History'!$A$4:$A$33,$A11,'Primary Sales History'!$B$4:$B$33,$B11) | BB11: =SUMIFS('Primary Sales History'!$H$4:$H$33,'Primary Sales History'!$A$4:$A$33,$A11,'Primary Sales History'!$B$4:$B$33,$B11) | BC11: =SUMIFS('Primary Sales History'!$I$4:$I$33,'Primary Sales History'!$A$4:$A$33,$A11,'Primary Sales History'!$B$4:$B$33,$B11) | BD11: =SUMIFS('Primary Sales History'!$J$4:$J$33,'Primary Sales History'!$A$4:$A$33,$A11,'Primary Sales History'!$B$4:$B$33,$B11) | BE11: =SUMIFS('Primary Sales History'!$K$4:$K$33,'Primary Sales History'!$A$4:$A$33,$A11,'Primary Sales History'!$B$4:$B$33,$B11) | BF11: =SUMIFS('Primary Sales History'!$L$4:$L$33,'Primary Sales History'!$A$4:$A$33,$A11,'Primary Sales History'!$B$4:$B$33,$B11) | BG11: =SUMIFS('Primary Sales History'!$M$4:$M$33,'Primary Sales History'!$A$4:$A$33,$A11,'Primary Sales History'!$B$4:$B$33,$B11) | BH11: =SUMIFS('Primary Sales History'!$N$4:$N$33,'Primary Sales History'!$A$4:$A$33,$A11,'Primary Sales History'!$B$4:$B$33,$B11) | BI11: =SUMIFS('Primary Sales History'!$O$4:$O$33,'Primary Sales History'!$A$4:$A$33,$A11,'Primary Sales History'!$B$4:$B$33,$B11) | BJ11: =SUMIFS('Primary Sales History'!$P$4:$P$33,'Primary Sales History'!$A$4:$A$33,$A11,'Primary Sales History'!$B$4:$B$33,$B11) | BK11: 0 | BL11: 0 | BM11: 0 | BN11: 0 | BO11: 0 | BP11: 0 | BQ11: 0 | BR11: 0 | BS11: 0 | BT11: 0
A12: BBLUNT | B12: Styling Products | C12: Styling Products | D12: =IFERROR(INDEX($AW12:$BT12,1,'Control Panel'!$B$8-0),0) | E12: =IFERROR(INDEX($AW12:$BT12,1,'Control Panel'!$B$8-1),0) | F12: =IFERROR(INDEX($AW12:$BT12,1,'Control Panel'!$B$8-2),0) | G12: =IFERROR(INDEX($AW12:$BT12,1,'Control Panel'!$B$8-5),0) | H12: =IFERROR(INDEX($AW12:$BT12,1,'Control Panel'!$B$8-11),0) | I12: =AVERAGE(D12,E12,F12) | J12: =(D12+E12+F12+IFERROR(INDEX($AW12:$BT12,1,'Control Panel'!$B$8-3),0)+IFERROR(INDEX($AW12:$BT12,1,'Control Panel'!$B$8-4),0)+G12)/6 | K12: =(IFERROR(INDEX($AW12:$BT12,1,'Control Panel'!$B$8-0),0)+IFERROR(INDEX($AW12:$BT12,1,'Control Panel'!$B$8-1),0)+IFERROR(INDEX($AW12:$BT12,1,'Control Panel'!$B$8-2),0)+IFERROR(INDEX($AW12:$BT12,1,'Control Panel'!$B$8-3),0)+IFERROR(INDEX($AW12:$BT12,1,'Control Panel'!$B$8-4),0)+IFERROR(INDEX($AW12:$BT12,1,'Control Panel'!$B$8-5),0)+IFERROR(INDEX($AW12:$BT12,1,'Control Panel'!$B$8-6),0)+IFERROR(INDEX($AW12:$BT12,1,'Control Panel'!$B$8-7),0)+IFERROR(INDEX($AW12:$BT12,1,'Control Panel'!$B$8-8),0)+IFERROR(INDEX($AW12:$BT12,1,'Control Panel'!$B$8-9),0)+IFERROR(INDEX($AW12:$BT12,1,'Control Panel'!$B$8-10),0)+IFERROR(INDEX($AW12:$BT12,1,'Control Panel'!$B$8-11),0))/12 | L12: =IFERROR(MAX(-'Control Panel'!$B$36,MIN('Control Panel'!$B$36,(I12-J12)/J12)),0) | M12: =(D12-G12)/5 | N12: =IFERROR(IF(H12>0,(D12/H12)^(1/12)-1,0),0) | O12: =IFERROR((IFERROR(INDEX('Seasonality Matrix'!$B$4:$M$11,MATCH($C12,'Seasonality Matrix'!$A$4:$A$11,0),MATCH('Control Panel'!$B$12,'Seasonality Matrix'!$B$3:$M$3,0)),1))/(IFERROR(AVERAGE(INDEX('Seasonality Matrix'!$B$4:$M$11,MATCH($C12,'Seasonality Matrix'!$A$4:$A$11,0),0)),1)),1) | P12: =IFERROR((IFERROR(INDEX('Seasonality Matrix'!$B$4:$M$11,MATCH($C12,'Seasonality Matrix'!$A$4:$A$11,0),MATCH('Control Panel'!$B$13,'Seasonality Matrix'!$B$3:$M$3,0)),1))/(IFERROR(AVERAGE(INDEX('Seasonality Matrix'!$B$4:$M$11,MATCH($C12,'Seasonality Matrix'!$A$4:$A$11,0),0)),1)),1) | Q12: =IFERROR((IFERROR(INDEX('Seasonality Matrix'!$B$4:$M$11,MATCH($C12,'Seasonality Matrix'!$A$4:$A$11,0),MATCH('Control Panel'!$B$14,'Seasonality Matrix'!$B$3:$M$3,0)),1))/(IFERROR(AVERAGE(INDEX('Seasonality Matrix'!$B$4:$M$11,MATCH($C12,'Seasonality Matrix'!$A$4:$A$11,0),0)),1)),1) | R12: =IFERROR(INDEX($AW12:$BT12,1,'Control Panel'!$B$9-12),0) | S12: =IFERROR(INDEX($AW12:$BT12,1,'Control Panel'!$B$10-12),0) | T12: =IFERROR(INDEX($AW12:$BT12,1,'Control Panel'!$B$11-12),0) | U12: ='Control Panel'!$B$45 | V12: =IFERROR(SUMIFS('Promotion Calendar'!$G$4:$G$12,'Promotion Calendar'!$A$4:$A$12,$A12,'Promotion Calendar'!$B$4:$B$12,$B12,'Promotion Calendar'!$C$4:$C$12,'Control Panel'!$B$4),0) | W12: =IFERROR(SUMIFS('Promotion Calendar'!$G$4:$G$12,'Promotion Calendar'!$A$4:$A$12,$A12,'Promotion Calendar'!$B$4:$B$12,$B12,'Promotion Calendar'!$C$4:$C$12,'Control Panel'!$B$6),0) | X12: =IFERROR(SUMIFS('Promotion Calendar'!$G$4:$G$12,'Promotion Calendar'!$A$4:$A$12,$A12,'Promotion Calendar'!$B$4:$B$12,$B12,'Promotion Calendar'!$C$4:$C$12,'Control Panel'!$B$7),0) | Y12: =IFERROR(SUMIFS('NPI & EPD Planning'!$I$4:$I$10,'NPI & EPD Planning'!$A$4:$A$10,$A12,'NPI & EPD Planning'!$B$4:$B$10,$B12,'NPI & EPD Planning'!$D$4:$D$10,'Control Panel'!$B$4),0) | Z12: =IFERROR(SUMIFS('NPI & EPD Planning'!$I$4:$I$10,'NPI & EPD Planning'!$A$4:$A$10,$A12,'NPI & EPD Planning'!$B$4:$B$10,$B12,'NPI & EPD Planning'!$D$4:$D$10,'Control Panel'!$B$6),0) | AA12: =IFERROR(SUMIFS('NPI & EPD Planning'!$I$4:$I$10,'NPI & EPD Planning'!$A$4:$A$10,$A12,'NPI & EPD Planning'!$B$4:$B$10,$B12,'NPI & EPD Planning'!$D$4:$D$10,'Control Panel'!$B$7),0) | AB12: =IFERROR(('Control Panel'!$B$17*(('Control Panel'!$B$28*D12+'Control Panel'!$B$29*E12+'Control Panel'!$B$30*F12)*O12)+'Control Panel'!$B$18*((('Control Panel'!$B$27*(1-'Control Panel'!$B$27)^0*IFERROR(INDEX($AW12:$BT12,1,'Control Panel'!$B$8-0),0)+'Control Panel'!$B$27*(1-'Control Panel'!$B$27)^1*IFERROR(INDEX($AW12:$BT12,1,'Control Panel'!$B$8-1),0)+'Control Panel'!$B$27*(1-'Control Panel'!$B$27)^2*IFERROR(INDEX($AW12:$BT12,1,'Control Panel'!$B$8-2),0)+'Control Panel'!$B$27*(1-'Control Panel'!$B$27)^3*IFERROR(INDEX($AW12:$BT12,1,'Control Panel'!$B$8-3),0)+'Control Panel'!$B$27*(1-'Control Panel'!$B$27)^4*IFERROR(INDEX($AW12:$BT12,1,'Control Panel'!$B$8-4),0)+'Control Panel'!$B$27*(1-'Control Panel'!$B$27)^5*IFERROR(INDEX($AW12:$BT12,1,'Control Panel'!$B$8-5),0))/(1-(1-'Control Panel'!$B$27)^6))*O12)+'Control Panel'!$B$19*((D12+M12*1)*O12)+'Control Panel'!$B$20*(K12*O12)+'Control Panel'!$B$21*(D12*(1+N12)^1*O12)+'Control Panel'!$B$22*(I12*O12)+'Control Panel'!$B$23*(R12*(1+IFERROR(D12/H12-1,0))))/'Control Panel'!$B$24,0) | AC12: =IFERROR(('Control Panel'!$B$17*(('Control Panel'!$B$28*D12+'Control Panel'!$B$29*E12+'Control Panel'!$B$30*F12)*P12)+'Control Panel'!$B$18*((('Control Panel'!$B$27*(1-'Control Panel'!$B$27)^0*IFERROR(INDEX($AW12:$BT12,1,'Control Panel'!$B$8-0),0)+'Control Panel'!$B$27*(1-'Control Panel'!$B$27)^1*IFERROR(INDEX($AW12:$BT12,1,'Control Panel'!$B$8-1),0)+'Control Panel'!$B$27*(1-'Control Panel'!$B$27)^2*IFERROR(INDEX($AW12:$BT12,1,'Control Panel'!$B$8-2),0)+'Control Panel'!$B$27*(1-'Control Panel'!$B$27)^3*IFERROR(INDEX($AW12:$BT12,1,'Control Panel'!$B$8-3),0)+'Control Panel'!$B$27*(1-'Control Panel'!$B$27)^4*IFERROR(INDEX($AW12:$BT12,1,'Control Panel'!$B$8-4),0)+'Control Panel'!$B$27*(1-'Control Panel'!$B$27)^5*IFERROR(INDEX($AW12:$BT12,1,'Control Panel'!$B$8-5),0))/(1-(1-'Control Panel'!$B$27)^6))*P12)+'Control Panel'!$B$19*((D12+M12*2)*P12)+'Control Panel'!$B$20*(K12*P12)+'Control Panel'!$B$21*(D12*(1+N12)^2*P12)+'Control Panel'!$B$22*(I12*P12)+'Control Panel'!$B$23*(S12*(1+IFERROR(D12/H12-1,0))))/'Control Panel'!$B$24,0) | AD12: =IFERROR(('Control Panel'!$B$17*(('Control Panel'!$B$28*D12+'Control Panel'!$B$29*E12+'Control Panel'!$B$30*F12)*Q12)+'Control Panel'!$B$18*((('Control Panel'!$B$27*(1-'Control Panel'!$B$27)^0*IFERROR(INDEX($AW12:$BT12,1,'Control Panel'!$B$8-0),0)+'Control Panel'!$B$27*(1-'Control Panel'!$B$27)^1*IFERROR(INDEX($AW12:$BT12,1,'Control Panel'!$B$8-1),0)+'Control Panel'!$B$27*(1-'Control Panel'!$B$27)^2*IFERROR(INDEX($AW12:$BT12,1,'Control Panel'!$B$8-2),0)+'Control Panel'!$B$27*(1-'Control Panel'!$B$27)^3*IFERROR(INDEX($AW12:$BT12,1,'Control Panel'!$B$8-3),0)+'Control Panel'!$B$27*(1-'Control Panel'!$B$27)^4*IFERROR(INDEX($AW12:$BT12,1,'Control Panel'!$B$8-4),0)+'Control Panel'!$B$27*(1-'Control Panel'!$B$27)^5*IFERROR(INDEX($AW12:$BT12,1,'Control Panel'!$B$8-5),0))/(1-(1-'Control Panel'!$B$27)^6))*Q12)+'Control Panel'!$B$19*((D12+M12*3)*Q12)+'Control Panel'!$B$20*(K12*Q12)+'Control Panel'!$B$21*(D12*(1+N12)^3*Q12)+'Control Panel'!$B$22*(I12*Q12)+'Control Panel'!$B$23*(T12*(1+IFERROR(D12/H12-1,0))))/'Control Panel'!$B$24,0) | AE12: =MAX(0,AB12*(1+U12+V12)) | AF12: =MAX(0,AC12*(1+U12+W12)) | AG12: =MAX(0,AD12*(1+U12+X12)) | AH12: =IFERROR(('Control Panel'!$B$33*AB12+'Control Panel'!$B$34*AE12+'Control Panel'!$B$35*(AB12*(1+L12+V12)))/('Control Panel'!$B$33+'Control Panel'!$B$34+'Control Panel'!$B$35),0) | AI12: =IFERROR(('Control Panel'!$B$33*AC12+'Control Panel'!$B$34*AF12+'Control Panel'!$B$35*(AC12*(1+L12+W12)))/('Control Panel'!$B$33+'Control Panel'!$B$34+'Control Panel'!$B$35),0) | AJ12: =IFERROR(('Control Panel'!$B$33*AD12+'Control Panel'!$B$34*AG12+'Control Panel'!$B$35*(AD12*(1+L12+X12)))/('Control Panel'!$B$33+'Control Panel'!$B$34+'Control Panel'!$B$35),0) | AK12: =AH12*'Control Panel'!$B$39+Y12 | AL12: =AI12*'Control Panel'!$B$39+Z12 | AM12: =AJ12*'Control Panel'!$B$39+AA12 | AN12: =AH12*'Control Panel'!$B$40+Y12 | AO12: =AI12*'Control Panel'!$B$40+Z12 | AP12: =AJ12*'Control Panel'!$B$40+AA12 | AQ12: =AH12*'Control Panel'!$B$41+Y12 | AR12: =AI12*'Control Panel'!$B$41+Z12 | AS12: =AJ12*'Control Panel'!$B$41+AA12 | AT12: =AH12*'Control Panel'!$B$42+Y12 | AU12: =AI12*'Control Panel'!$B$42+Z12 | AV12: =AJ12*'Control Panel'!$B$42+AA12 | AW12: =SUMIFS('Primary Sales History'!$C$4:$C$33,'Primary Sales History'!$A$4:$A$33,$A12,'Primary Sales History'!$B$4:$B$33,$B12) | AX12: =SUMIFS('Primary Sales History'!$D$4:$D$33,'Primary Sales History'!$A$4:$A$33,$A12,'Primary Sales History'!$B$4:$B$33,$B12) | AY12: =SUMIFS('Primary Sales History'!$E$4:$E$33,'Primary Sales History'!$A$4:$A$33,$A12,'Primary Sales History'!$B$4:$B$33,$B12) | AZ12: =SUMIFS('Primary Sales History'!$F$4:$F$33,'Primary Sales History'!$A$4:$A$33,$A12,'Primary Sales History'!$B$4:$B$33,$B12) | BA12: =SUMIFS('Primary Sales History'!$G$4:$G$33,'Primary Sales History'!$A$4:$A$33,$A12,'Primary Sales History'!$B$4:$B$33,$B12) | BB12: =SUMIFS('Primary Sales History'!$H$4:$H$33,'Primary Sales History'!$A$4:$A$33,$A12,'Primary Sales History'!$B$4:$B$33,$B12) | BC12: =SUMIFS('Primary Sales History'!$I$4:$I$33,'Primary Sales History'!$A$4:$A$33,$A12,'Primary Sales History'!$B$4:$B$33,$B12) | BD12: =SUMIFS('Primary Sales History'!$J$4:$J$33,'Primary Sales History'!$A$4:$A$33,$A12,'Primary Sales History'!$B$4:$B$33,$B12) | BE12: =SUMIFS('Primary Sales History'!$K$4:$K$33,'Primary Sales History'!$A$4:$A$33,$A12,'Primary Sales History'!$B$4:$B$33,$B12) | BF12: =SUMIFS('Primary Sales History'!$L$4:$L$33,'Primary Sales History'!$A$4:$A$33,$A12,'Primary Sales History'!$B$4:$B$33,$B12) | BG12: =SUMIFS('Primary Sales History'!$M$4:$M$33,'Primary Sales History'!$A$4:$A$33,$A12,'Primary Sales History'!$B$4:$B$33,$B12) | BH12: =SUMIFS('Primary Sales History'!$N$4:$N$33,'Primary Sales History'!$A$4:$A$33,$A12,'Primary Sales History'!$B$4:$B$33,$B12) | BI12: =SUMIFS('Primary Sales History'!$O$4:$O$33,'Primary Sales History'!$A$4:$A$33,$A12,'Primary Sales History'!$B$4:$B$33,$B12) | BJ12: =SUMIFS('Primary Sales History'!$P$4:$P$33,'Primary Sales History'!$A$4:$A$33,$A12,'Primary Sales History'!$B$4:$B$33,$B12) | BK12: 0 | BL12: 0 | BM12: 0 | BN12: 0 | BO12: 0 | BP12: 0 | BQ12: 0 | BR12: 0 | BS12: 0 | BT12: 0
A13: COMPANY TOTAL | AB13: =SUM(AB4:AB12) | AC13: =SUM(AC4:AC12) | AD13: =SUM(AD4:AD12) | AE13: =SUM(AE4:AE12) | AF13: =SUM(AF4:AF12) | AG13: =SUM(AG4:AG12) | AH13: =SUM(AH4:AH12) | AI13: =SUM(AI4:AI12) | ... AV13: =SUM(AV4:AV12)

Sheet Forecast Plan Article-Chain
A1: FORECAST PLAN · Article × Brand × Chain × Region · rolling 3-month (₹ Cr)
A2: The Brand×Category forecast is split to each Article×Chain×Region line by real historical contribution % (primary Apr'25–May'26), so it reconciles exactly to the Forecast Engine. Use the column filters (Brand / Chain / Region / Article) to slice. Contribution % is editable — override a line and the plan re-weights within its Brand×Category. The '(long tail)' line per Brand×Category holds the residual so each Brand×Category still sums to 100%.
A3: Article Code | B3: Article Description | C3: Brand | D3: Category | E3: Chain | F3: Region (Zone) | G3: Hist NSV (₹Cr) | H3: Contribution % | I3: Fcst M (₹Cr) | J3: Fcst M+1 | K3: Fcst M+2 | L3: 3M Total
C4: Mamaearth | D4: Face | E4: D-Mart | F4: North | G4: 4.7593 | H4: =IFERROR(G4/SUMIFS($G$4:$G$1504,$C$4:$C$1504,$C4,$D$4:$D$1504,$D4),0) | I4: =$H4*SUMIFS('Forecast Engine'!$AK$4:$AK$12,'Forecast Engine'!$A$4:$A$12,$C4,'Forecast Engine'!$B$4:$B$12,$D4) | J4: =$H4*SUMIFS('Forecast Engine'!$AL$4:$AL$12,'Forecast Engine'!$A$4:$A$12,$C4,'Forecast Engine'!$B$4:$B$12,$D4) | K4: =$H4*SUMIFS('Forecast Engine'!$AM$4:$AM$12,'Forecast Engine'!$A$4:$A$12,$C4,'Forecast Engine'!$B$4:$B$12,$D4) | L4: =SUM(I4:K4)
C5: Mamaearth | D5: Face | E5: Reliance Retail Limited | F5: North | G5: 3.9465 | H5: =IFERROR(G5/SUMIFS($G$4:$G$1504,$C$4:$C$1504,$C5,$D$4:$D$1504,$D5),0) | I5: =$H5*SUMIFS('Forecast Engine'!$AK$4:$AK$12,'Forecast Engine'!$A$4:$A$12,$C5,'Forecast Engine'!$B$4:$B$12,$D5) | J5: =$H5*SUMIFS('Forecast Engine'!$AL$4:$AL$12,'Forecast Engine'!$A$4:$A$12,$C5,'Forecast Engine'!$B$4:$B$12,$D5) | K5: =$H5*SUMIFS('Forecast Engine'!$AM$4:$AM$12,'Forecast Engine'!$A$4:$A$12,$C5,'Forecast Engine'!$B$4:$B$12,$D5) | L5: =SUM(I5:K5)
C6: Mamaearth | D6: Face | E6: D-Mart | F6: West | G6: 3.0698 | H6: =IFERROR(G6/SUMIFS($G$4:$G$1504,$C$4:$C$1504,$C6,$D$4:$D$1504,$D6),0) | I6: =$H6*SUMIFS('Forecast Engine'!$AK$4:$AK$12,'Forecast Engine'!$A$4:$A$12,$C6,'Forecast Engine'!$B$4:$B$12,$D6) | J6: =$H6*SUMIFS('Forecast Engine'!$AL$4:$AL$12,'Forecast Engine'!$A$4:$A$12,$C6,'Forecast Engine'!$B$4:$B$12,$D6) | K6: =$H6*SUMIFS('Forecast Engine'!$AM$4:$AM$12,'Forecast Engine'!$A$4:$A$12,$C6,'Forecast Engine'!$B$4:$B$12,$D6) | L6: =SUM(I6:K6)
C7: Mamaearth | D7: Face | E7: Reliance Retail Limited | F7: East | G7: 2.6554 | H7: =IFERROR(G7/SUMIFS($G$4:$G$1504,$C$4:$C$1504,$C7,$D$4:$D$1504,$D7),0) | I7: =$H7*SUMIFS('Forecast Engine'!$AK$4:$AK$12,'Forecast Engine'!$A$4:$A$12,$C7,'Forecast Engine'!$B$4:$B$12,$D7) | J7: =$H7*SUMIFS('Forecast Engine'!$AL$4:$AL$12,'Forecast Engine'!$A$4:$A$12,$C7,'Forecast Engine'!$B$4:$B$12,$D7) | K7: =$H7*SUMIFS('Forecast Engine'!$AM$4:$AM$12,'Forecast Engine'!$A$4:$A$12,$C7,'Forecast Engine'!$B$4:$B$12,$D7) | L7: =SUM(I7:K7)
C8: Mamaearth | D8: Face | E8: Vanaja Agencies | F8: South-2 | G8: 2.4625 | H8: =IFERROR(G8/SUMIFS($G$4:$G$1504,$C$4:$C$1504,$C8,$D$4:$D$1504,$D8),0) | I8: =$H8*SUMIFS('Forecast Engine'!$AK$4:$AK$12,'Forecast Engine'!$A$4:$A$12,$C8,'Forecast Engine'!$B$4:$B$12,$D8) | J8: =$H8*SUMIFS('Forecast Engine'!$AL$4:$AL$12,'Forecast Engine'!$A$4:$A$12,$C8,'Forecast Engine'!$B$4:$B$12,$D8) | K8: =$H8*SUMIFS('Forecast Engine'!$AM$4:$AM$12,'Forecast Engine'!$A$4:$A$12,$C8,'Forecast Engine'!$B$4:$B$12,$D8) | L8: =SUM(I8:K8)
C9: Mamaearth | D9: Face | E9: JUST MARK-Dmart | F9: West | G9: 2.3006 | H9: =IFERROR(G9/SUMIFS($G$4:$G$1504,$C$4:$C$1504,$C9,$D$4:$D$1504,$D9),0) | I9: =$H9*SUMIFS('Forecast Engine'!$AK$4:$AK$12,'Forecast Engine'!$A$4:$A$12,$C9,'Forecast Engine'!$B$4:$B$12,$D9) | J9: =$H9*SUMIFS('Forecast Engine'!$AL$4:$AL$12,'Forecast Engine'!$A$4:$A$12,$C9,'Forecast Engine'!$B$4:$B$12,$D9) | K9: =$H9*SUMIFS('Forecast Engine'!$AM$4:$AM$12,'Forecast Engine'!$A$4:$A$12,$C9,'Forecast Engine'!$B$4:$B$12,$D9) | L9: =SUM(I9:K9)
C10: Mamaearth | D10: Face | E10: G.V Enterprises | F10: South-1 | G10: 2.2511 | H10: =IFERROR(G10/SUMIFS($G$4:$G$1504,$C$4:$C$1504,$C10,$D$4:$D$1504,$D10),0) | I10: =$H10*SUMIFS('Forecast Engine'!$AK$4:$AK$12,'Forecast Engine'!$A$4:$A$12,$C10,'Forecast Engine'!$B$4:$B$12,$D10) | J10: =$H10*SUMIFS('Forecast Engine'!$AL$4:$AL$12,'Forecast Engine'!$A$4:$A$12,$C10,'Forecast Engine'!$B$4:$B$12,$D10) | K10: =$H10*SUMIFS('Forecast Engine'!$AM$4:$AM$12,'Forecast Engine'!$A$4:$A$12,$C10,'Forecast Engine'!$B$4:$B$12,$D10) | L10: =SUM(I10:K10)
C11: Mamaearth | D11: Face | E11: Kiran Trading Company | F11: West | G11: 2.1098 | H11: =IFERROR(G11/SUMIFS($G$4:$G$1504,$C$4:$C$1504,$C11,$D$4:$D$1504,$D11),0) | I11: =$H11*SUMIFS('Forecast Engine'!$AK$4:$AK$12,'Forecast Engine'!$A$4:$A$12,$C11,'Forecast Engine'!$B$4:$B$12,$D11) | J11: =$H11*SUMIFS('Forecast Engine'!$AL$4:$AL$12,'Forecast Engine'!$A$4:$A$12,$C11,'Forecast Engine'!$B$4:$B$12,$D11) | K11: =$H11*SUMIFS('Forecast Engine'!$AM$4:$AM$12,'Forecast Engine'!$A$4:$A$12,$C11,'Forecast Engine'!$B$4:$B$12,$D11) | L11: =SUM(I11:K11)
C12: Mamaearth | D12: Face | E12: Sri Vijaya Durga Agencie | F12: South-2 | G12: 2.064 | H12: =IFERROR(G12/SUMIFS($G$4:$G$1504,$C$4:$C$1504,$C12,$D$4:$D$1504,$D12),0) | I12: =$H12*SUMIFS('Forecast Engine'!$AK$4:$AK$12,'Forecast Engine'!$A$4:$A$12,$C12,'Forecast Engine'!$B$4:$B$12,$D12) | J12: =$H12*SUMIFS('Forecast Engine'!$AL$4:$AL$12,'Forecast Engine'!$A$4:$A$12,$C12,'Forecast Engine'!$B$4:$B$12,$D12) | K12: =$H12*SUMIFS('Forecast Engine'!$AM$4:$AM$12,'Forecast Engine'!$A$4:$A$12,$C12,'Forecast Engine'!$B$4:$B$12,$D12) | L12: =SUM(I12:K12)
A13: 10101163 | B13: Rice Dewy Bright Face wash | C13: Mamaearth | D13: Face | E13: Reliance Retail Limited | F13: North | G13: 1.9436 | H13: =IFERROR(G13/SUMIFS($G$4:$G$1504,$C$4:$C$1504,$C13,$D$4:$D$1504,$D13),0) | I13: =$H13*SUMIFS('Forecast Engine'!$AK$4:$AK$12,'Forecast Engine'!$A$4:$A$12,$C13,'Forecast Engine'!$B$4:$B$12,$D13) | J13: =$H13*SUMIFS('Forecast Engine'!$AL$4:$AL$12,'Forecast Engine'!$A$4:$A$12,$C13,'Forecast Engine'!$B$4:$B$12,$D13) | K13: =$H13*SUMIFS('Forecast Engine'!$AM$4:$AM$12,'Forecast Engine'!$A$4:$A$12,$C13,'Forecast Engine'!$B$4:$B$12,$D13) | L13: =SUM(I13:K13)
C14: Mamaearth | D14: Face | E14: Nykaa E-Retail Limited | F14: East | G14: 1.9417 | H14: =IFERROR(G14/SUMIFS($G$4:$G$1504,$C$4:$C$1504,$C14,$D$4:$D$1504,$D14),0) | I14: =$H14*SUMIFS('Forecast Engine'!$AK$4:$AK$12,'Forecast Engine'!$A$4:$A$12,$C14,'Forecast Engine'!$B$4:$B$12,$D14) | J14: =$H14*SUMIFS('Forecast Engine'!$AL$4:$AL$12,'Forecast Engine'!$A$4:$A$12,$C14,'Forecast Engine'!$B$4:$B$12,$D14) | K14: =$H14*SUMIFS('Forecast Engine'!$AM$4:$AM$12,'Forecast Engine'!$A$4:$A$12,$C14,'Forecast Engine'!$B$4:$B$12,$D14) | L14: =SUM(I14:K14)
C15: Mamaearth | D15: Face | E15: D-Mart | F15: South-1 | G15: 1.8707 | H15: =IFERROR(G15/SUMIFS($G$4:$G$1504,$C$4:$C$1504,$C15,$D$4:$D$1504,$D15),0) | I15: =$H15*SUMIFS('Forecast Engine'!$AK$4:$AK$12,'Forecast Engine'!$A$4:$A$12,$C15,'Forecast Engine'!$B$4:$B$12,$D15) | J15: =$H15*SUMIFS('Forecast Engine'!$AL$4:$AL$12,'Forecast Engine'!$A$4:$A$12,$C15,'Forecast Engine'!$B$4:$B$12,$D15) | K15: =$H15*SUMIFS('Forecast Engine'!$AM$4:$AM$12,'Forecast Engine'!$A$4:$A$12,$C15,'Forecast Engine'!$B$4:$B$12,$D15) | L15: =SUM(I15:K15)
A16: 10101163 | B16: Rice Dewy Bright Face wash | C16: Mamaearth | D16: Face | E16: D-Mart | F16: North | G16: 1.8599 | H16: =IFERROR(G16/SUMIFS($G$4:$G$1504,$C$4:$C$1504,$C16,$D$4:$D$1504,$D16),0) | I16: =$H16*SUMIFS('Forecast Engine'!$AK$4:$AK$12,'Forecast Engine'!$A$4:$A$12,$C16,'Forecast Engine'!$B$4:$B$12,$D16) | J16: =$H16*SUMIFS('Forecast Engine'!$AL$4:$AL$12,'Forecast Engine'!$A$4:$A$12,$C16,'Forecast Engine'!$B$4:$B$12,$D16) | K16: =$H16*SUMIFS('Forecast Engine'!$AM$4:$AM$12,'Forecast Engine'!$A$4:$A$12,$C16,'Forecast Engine'!$B$4:$B$12,$D16) | L16: =SUM(I16:K16)
A17: 10100695 | B17: ME Ubtan Natural Glow Face Wash With Turmeric & | C17: Mamaearth | D17: Face | E17: Reliance Retail Limited | F17: North | G17: 1.7703 | H17: =IFERROR(G17/SUMIFS($G$4:$G$1504,$C$4:$C$1504,$C17,$D$4:$D$1504,$D17),0) | I17: =$H17*SUMIFS('Forecast Engine'!$AK$4:$AK$12,'Forecast Engine'!$A$4:$A$12,$C17,'Forecast Engine'!$B$4:$B$12,$D17) | J17: =$H17*SUMIFS('Forecast Engine'!$AL$4:$AL$12,'Forecast Engine'!$A$4:$A$12,$C17,'Forecast Engine'!$B$4:$B$12,$D17) | K17: =$H17*SUMIFS('Forecast Engine'!$AM$4:$AM$12,'Forecast Engine'!$A$4:$A$12,$C17,'Forecast Engine'!$B$4:$B$12,$D17) | L17: =SUM(I17:K17)
A18: 10101163 | B18: Rice Dewy Bright Face wash | C18: Mamaearth | D18: Face | E18: D-Mart | F18: West | G18: 1.6422 | H18: =IFERROR(G18/SUMIFS($G$4:$G$1504,$C$4:$C$1504,$C18,$D$4:$D$1504,$D18),0) | I18: =$H18*SUMIFS('Forecast Engine'!$AK$4:$AK$12,'Forecast Engine'!$A$4:$A$12,$C18,'Forecast Engine'!$B$4:$B$12,$D18) | J18: =$H18*SUMIFS('Forecast Engine'!$AL$4:$AL$12,'Forecast Engine'!$A$4:$A$12,$C18,'Forecast Engine'!$B$4:$B$12,$D18) | K18: =$H18*SUMIFS('Forecast Engine'!$AM$4:$AM$12,'Forecast Engine'!$A$4:$A$12,$C18,'Forecast Engine'!$B$4:$B$12,$D18) | L18: =SUM(I18:K18)
A19: 10100695 | B19: ME Ubtan Natural Glow Face Wash With Turmeric & | C19: Mamaearth | D19: Face | E19: Reliance Retail Limited | F19: East | G19: 1.6209 | H19: =IFERROR(G19/SUMIFS($G$4:$G$1504,$C$4:$C$1504,$C19,$D$4:$D$1504,$D19),0) | I19: =$H19*SUMIFS('Forecast Engine'!$AK$4:$AK$12,'Forecast Engine'!$A$4:$A$12,$C19,'Forecast Engine'!$B$4:$B$12,$D19) | J19: =$H19*SUMIFS('Forecast Engine'!$AL$4:$AL$12,'Forecast Engine'!$A$4:$A$12,$C19,'Forecast Engine'!$B$4:$B$12,$D19) | K19: =$H19*SUMIFS('Forecast Engine'!$AM$4:$AM$12,'Forecast Engine'!$A$4:$A$12,$C19,'Forecast Engine'!$B$4:$B$12,$D19) | L19: =SUM(I19:K19)
C20: Mamaearth | D20: Face | E20: Reliance Retail Limited | F20: South-1 | G20: 1.5858 | H20: =IFERROR(G20/SUMIFS($G$4:$G$1504,$C$4:$C$1504,$C20,$D$4:$D$1504,$D20),0) | I20: =$H20*SUMIFS('Forecast Engine'!$AK$4:$AK$12,'Forecast Engine'!$A$4:$A$12,$C20,'Forecast Engine'!$B$4:$B$12,$D20) | J20: =$H20*SUMIFS('Forecast Engine'!$AL$4:$AL$12,'Forecast Engine'!$A$4:$A$12,$C20,'Forecast Engine'!$B$4:$B$12,$D20) | K20: =$H20*SUMIFS('Forecast Engine'!$AM$4:$AM$12,'Forecast Engine'!$A$4:$A$12,$C20,'Forecast Engine'!$B$4:$B$12,$D20) | L20: =SUM(I20:K20)
A21: 10101163 | B21: Rice Dewy Bright Face wash | C21: Mamaearth | D21: Face | E21: Kiran Trading Company | F21: West | G21: 1.5833 | H21: =IFERROR(G21/SUMIFS($G$4:$G$1504,$C$4:$C$1504,$C21,$D$4:$D$1504,$D21),0) | I21: =$H21*SUMIFS('Forecast Engine'!$AK$4:$AK$12,'Forecast Engine'!$A$4:$A$12,$C21,'Forecast Engine'!$B$4:$B$12,$D21) | J21: =$H21*SUMIFS('Forecast Engine'!$AL$4:$AL$12,'Forecast Engine'!$A$4:$A$12,$C21,'Forecast Engine'!$B$4:$B$12,$D21) | K21: =$H21*SUMIFS('Forecast Engine'!$AM$4:$AM$12,'Forecast Engine'!$A$4:$A$12,$C21,'Forecast Engine'!$B$4:$B$12,$D21) | L21: =SUM(I21:K21)
C22: Mamaearth | D22: Face | E22: Reliance Retail Limited | F22: West | G22: 1.5476 | H22: =IFERROR(G22/SUMIFS($G$4:$G$1504,$C$4:$C$1504,$C22,$D$4:$D$1504,$D22),0) | I22: =$H22*SUMIFS('Forecast Engine'!$AK$4:$AK$12,'Forecast Engine'!$A$4:$A$12,$C22,'Forecast Engine'!$B$4:$B$12,$D22) | J22: =$H22*SUMIFS('Forecast Engine'!$AL$4:$AL$12,'Forecast Engine'!$A$4:$A$12,$C22,'Forecast Engine'!$B$4:$B$12,$D22) | K22: =$H22*SUMIFS('Forecast Engine'!$AM$4:$AM$12,'Forecast Engine'!$A$4:$A$12,$C22,'Forecast Engine'!$B$4:$B$12,$D22) | L22: =SUM(I22:K22)
A23: 10101163 | B23: Rice Dewy Bright Face wash | C23: Mamaearth | D23: Face | E23: JUST MARK-Dmart | F23: West | G23: 1.5139 | H23: =IFERROR(G23/SUMIFS($G$4:$G$1504,$C$4:$C$1504,$C23,$D$4:$D$1504,$D23),0) | I23: =$H23*SUMIFS('Forecast Engine'!$AK$4:$AK$12,'Forecast Engine'!$A$4:$A$12,$C23,'Forecast Engine'!$B$4:$B$12,$D23) | J23: =$H23*SUMIFS('Forecast Engine'!$AL$4:$AL$12,'Forecast Engine'!$A$4:$A$12,$C23,'Forecast Engine'!$B$4:$B$12,$D23) | K23: =$H23*SUMIFS('Forecast Engine'!$AM$4:$AM$12,'Forecast Engine'!$A$4:$A$12,$C23,'Forecast Engine'!$B$4:$B$12,$D23) | L23: =SUM(I23:K23)
C24: Mamaearth | D24: Face | E24: Apollo Healthco | F24: South-1 | G24: 1.485 | H24: =IFERROR(G24/SUMIFS($G$4:$G$1504,$C$4:$C$1504,$C24,$D$4:$D$1504,$D24),0) | I24: =$H24*SUMIFS('Forecast Engine'!$AK$4:$AK$12,'Forecast Engine'!$A$4:$A$12,$C24,'Forecast Engine'!$B$4:$B$12,$D24) | J24: =$H24*SUMIFS('Forecast Engine'!$AL$4:$AL$12,'Forecast Engine'!$A$4:$A$12,$C24,'Forecast Engine'!$B$4:$B$12,$D24) | K24: =$H24*SUMIFS('Forecast Engine'!$AM$4:$AM$12,'Forecast Engine'!$A$4:$A$12,$C24,'Forecast Engine'!$B$4:$B$12,$D24) | L24: =SUM(I24:K24)
A25: 10101163 | B25: Rice Dewy Bright Face wash | C25: Mamaearth | D25: Face | E25: Reliance Retail Limited | F25: East | G25: 1.282 | H25: =IFERROR(G25/SUMIFS($G$4:$G$1504,$C$4:$C$1504,$C25,$D$4:$D$1504,$D25),0) | I25: =$H25*SUMIFS('Forecast Engine'!$AK$4:$AK$12,'Forecast Engine'!$A$4:$A$12,$C25,'Forecast Engine'!$B$4:$B$12,$D25) | J25: =$H25*SUMIFS('Forecast Engine'!$AL$4:$AL$12,'Forecast Engine'!$A$4:$A$12,$C25,'Forecast Engine'!$B$4:$B$12,$D25) | K25: =$H25*SUMIFS('Forecast Engine'!$AM$4:$AM$12,'Forecast Engine'!$A$4:$A$12,$C25,'Forecast Engine'!$B$4:$B$12,$D25) | L25: =SUM(I25:K25)
C26: Mamaearth | D26: Face | E26: Nykaa E-Retail Limited | F26: North | G26: 1.1904 | H26: =IFERROR(G26/SUMIFS($G$4:$G$1504,$C$4:$C$1504,$C26,$D$4:$D$1504,$D26),0) | I26: =$H26*SUMIFS('Forecast Engine'!$AK$4:$AK$12,'Forecast Engine'!$A$4:$A$12,$C26,'Forecast Engine'!$B$4:$B$12,$D26) | J26: =$H26*SUMIFS('Forecast Engine'!$AL$4:$AL$12,'Forecast Engine'!$A$4:$A$12,$C26,'Forecast Engine'!$B$4:$B$12,$D26) | K26: =$H26*SUMIFS('Forecast Engine'!$AM$4:$AM$12,'Forecast Engine'!$A$4:$A$12,$C26,'Forecast Engine'!$B$4:$B$12,$D26) | L26: =SUM(I26:K26)
A27: 10100695 | B27: ME Ubtan Natural Glow Face Wash With Turmeric & | C27: Mamaearth | D27: Face | E27: D-Mart | F27: West | G27: 1.1779 | H27: =IFERROR(G27/SUMIFS($G$4:$G$1504,$C$4:$C$1504,$C27,$D$4:$D$1504,$D27),0) | I27: =$H27*SUMIFS('Forecast Engine'!$AK$4:$AK$12,'Forecast Engine'!$A$4:$A$12,$C27,'Forecast Engine'!$B$4:$B$12,$D27) | J27: =$H27*SUMIFS('Forecast Engine'!$AL$4:$AL$12,'Forecast Engine'!$A$4:$A$12,$C27,'Forecast Engine'!$B$4:$B$12,$D27) | K27: =$H27*SUMIFS('Forecast Engine'!$AM$4:$AM$12,'Forecast Engine'!$A$4:$A$12,$C27,'Forecast Engine'!$B$4:$B$12,$D27) | L27: =SUM(I27:K27)
C28: Mamaearth | D28: Face | E28: Apollo Healthco | F28: North | G28: 1.1331 | H28: =IFERROR(G28/SUMIFS($G$4:$G$1504,$C$4:$C$1504,$C28,$D$4:$D$1504,$D28),0) | I28: =$H28*SUMIFS('Forecast Engine'!$AK$4:$AK$12,'Forecast Engine'!$A$4:$A$12,$C28,'Forecast Engine'!$B$4:$B$12,$D28) | J28: =$H28*SUMIFS('Forecast Engine'!$AL$4:$AL$12,'Forecast Engine'!$A$4:$A$12,$C28,'Forecast Engine'!$B$4:$B$12,$D28) | K28: =$H28*SUMIFS('Forecast Engine'!$AM$4:$AM$12,'Forecast Engine'!$A$4:$A$12,$C28,'Forecast Engine'!$B$4:$B$12,$D28) | L28: =SUM(I28:K28)
A29: 10101163 | B29: Rice Dewy Bright Face wash | C29: Mamaearth | D29: Face | E29: Apollo Healthco | F29: South-1 | G29: 1.0456 | H29: =IFERROR(G29/SUMIFS($G$4:$G$1504,$C$4:$C$1504,$C29,$D$4:$D$1504,$D29),0) | I29: =$H29*SUMIFS('Forecast Engine'!$AK$4:$AK$12,'Forecast Engine'!$A$4:$A$12,$C29,'Forecast Engine'!$B$4:$B$12,$D29) | J29: =$H29*SUMIFS('Forecast Engine'!$AL$4:$AL$12,'Forecast Engine'!$A$4:$A$12,$C29,'Forecast Engine'!$B$4:$B$12,$D29) | K29: =$H29*SUMIFS('Forecast Engine'!$AM$4:$AM$12,'Forecast Engine'!$A$4:$A$12,$C29,'Forecast Engine'!$B$4:$B$12,$D29) | L29: =SUM(I29:K29)
A30: 10100062 | B30: Mamaearth Ultra Light Indian Sunscreen with Carr | C30: Mamaearth | D30: Face | E30: D-Mart | F30: North | G30: 0.998 | H30: =IFERROR(G30/SUMIFS($G$4:$G$1504,$C$4:$C$1504,$C30,$D$4:$D$1504,$D30),0) | I30: =$H30*SUMIFS('Forecast Engine'!$AK$4:$AK$12,'Forecast Engine'!$A$4:$A$12,$C30,'Forecast Engine'!$B$4:$B$12,$D30) | J30: =$H30*SUMIFS('Forecast Engine'!$AL$4:$AL$12,'Forecast Engine'!$A$4:$A$12,$C30,'Forecast Engine'!$B$4:$B$12,$D30) | K30: =$H30*SUMIFS('Forecast Engine'!$AM$4:$AM$12,'Forecast Engine'!$A$4:$A$12,$C30,'Forecast Engine'!$B$4:$B$12,$D30) | L30: =SUM(I30:K30)
A31: 10100695 | B31: ME Ubtan Natural Glow Face Wash With Turmeric & | C31: Mamaearth | D31: Face | E31: D-Mart | F31: North | G31: 0.9924 | H31: =IFERROR(G31/SUMIFS($G$4:$G$1504,$C$4:$C$1504,$C31,$D$4:$D$1504,$D31),0) | I31: =$H31*SUMIFS('Forecast Engine'!$AK$4:$AK$12,'Forecast Engine'!$A$4:$A$12,$C31,'Forecast Engine'!$B$4:$B$12,$D31) | J31: =$H31*SUMIFS('Forecast Engine'!$AL$4:$AL$12,'Forecast Engine'!$A$4:$A$12,$C31,'Forecast Engine'!$B$4:$B$12,$D31) | K31: =$H31*SUMIFS('Forecast Engine'!$AM$4:$AM$12,'Forecast Engine'!$A$4:$A$12,$C31,'Forecast Engine'!$B$4:$B$12,$D31) | L31: =SUM(I31:K31)
A32: 10101163 | B32: Rice Dewy Bright Face wash | C32: Mamaearth | D32: Face | E32: Sri Vijaya Durga Agencie | F32: South-2 | G32: 0.93 | H32: =IFERROR(G32/SUMIFS($G$4:$G$1504,$C$4:$C$1504,$C32,$D$4:$D$1504,$D32),0) | I32: =$H32*SUMIFS('Forecast Engine'!$AK$4:$AK$12,'Forecast Engine'!$A$4:$A$12,$C32,'Forecast Engine'!$B$4:$B$12,$D32) | J32: =$H32*SUMIFS('Forecast Engine'!$AL$4:$AL$12,'Forecast Engine'!$A$4:$A$12,$C32,'Forecast Engine'!$B$4:$B$12,$D32) | K32: =$H32*SUMIFS('Forecast Engine'!$AM$4:$AM$12,'Forecast Engine'!$A$4:$A$12,$C32,'Forecast Engine'!$B$4:$B$12,$D32) | L32: =SUM(I32:K32)
A33: 10100695 | B33: ME Ubtan Natural Glow Face Wash With Turmeric & | C33: Mamaearth | D33: Face | E33: Reliance Retail Limited | F33: West | G33: 0.9157 | H33: =IFERROR(G33/SUMIFS($G$4:$G$1504,$C$4:$C$1504,$C33,$D$4:$D$1504,$D33),0) | I33: =$H33*SUMIFS('Forecast Engine'!$AK$4:$AK$12,'Forecast Engine'!$A$4:$A$12,$C33,'Forecast Engine'!$B$4:$B$12,$D33) | J33: =$H33*SUMIFS('Forecast Engine'!$AL$4:$AL$12,'Forecast Engine'!$A$4:$A$12,$C33,'Forecast Engine'!$B$4:$B$12,$D33) | K33: =$H33*SUMIFS('Forecast Engine'!$AM$4:$AM$12,'Forecast Engine'!$A$4:$A$12,$C33,'Forecast Engine'!$B$4:$B$12,$D33) | L33: =SUM(I33:K33)
C34: Mamaearth | D34: Face | E34: D.L. Sales - MT | F34: East | G34: 0.8395 | H34: =IFERROR(G34/SUMIFS($G$4:$G$1504,$C$4:$C$1504,$C34,$D$4:$D$1504,$D34),0) | I34: =$H34*SUMIFS('Forecast Engine'!$AK$4:$AK$12,'Forecast Engine'!$A$4:$A$12,$C34,'Forecast Engine'!$B$4:$B$12,$D34) | J34: =$H34*SUMIFS('Forecast Engine'!$AL$4:$AL$12,'Forecast Engine'!$A$4:$A$12,$C34,'Forecast Engine'!$B$4:$B$12,$D34) | K34: =$H34*SUMIFS('Forecast Engine'!$AM$4:$AM$12,'Forecast Engine'!$A$4:$A$12,$C34,'Forecast Engine'!$B$4:$B$12,$D34) | L34: =SUM(I34:K34)
A35: 10100695 | B35: ME Ubtan Natural Glow Face Wash With Turmeric & | C35: Mamaearth | D35: Face | E35: JUST MARK-Dmart | F35: West | G35: 0.8389 | H35: =IFERROR(G35/SUMIFS($G$4:$G$1504,$C$4:$C$1504,$C35,$D$4:$D$1504,$D35),0) | I35: =$H35*SUMIFS('Forecast Engine'!$AK$4:$AK$12,'Forecast Engine'!$A$4:$A$12,$C35,'Forecast Engine'!$B$4:$B$12,$D35) | J35: =$H35*SUMIFS('Forecast Engine'!$AL$4:$AL$12,'Forecast Engine'!$A$4:$A$12,$C35,'Forecast Engine'!$B$4:$B$12,$D35) | K35: =$H35*SUMIFS('Forecast Engine'!$AM$4:$AM$12,'Forecast Engine'!$A$4:$A$12,$C35,'Forecast Engine'!$B$4:$B$12,$D35) | L35: =SUM(I35:K35)
A36: 10101163 | B36: Rice Dewy Bright Face wash | C36: Mamaearth | D36: Face | E36: Reliance Retail Limited | F36: West | G36: 0.8314 | H36: =IFERROR(G36/SUMIFS($G$4:$G$1504,$C$4:$C$1504,$C36,$D$4:$D$1504,$D36),0) | I36: =$H36*SUMIFS('Forecast Engine'!$AK$4:$AK$12,'Forecast Engine'!$A$4:$A$12,$C36,'Forecast Engine'!$B$4:$B$12,$D36) | J36: =$H36*SUMIFS('Forecast Engine'!$AL$4:$AL$12,'Forecast Engine'!$A$4:$A$12,$C36,'Forecast Engine'!$B$4:$B$12,$D36) | K36: =$H36*SUMIFS('Forecast Engine'!$AM$4:$AM$12,'Forecast Engine'!$A$4:$A$12,$C36,'Forecast Engine'!$B$4:$B$12,$D36) | L36: =SUM(I36:K36)
C37: Mamaearth | D37: Face | E37: Sancus Networks Private | F37: North | G37: 0.8184 | H37: =IFERROR(G37/SUMIFS($G$4:$G$1504,$C$4:$C$1504,$C37,$D$4:$D$1504,$D37),0) | I37: =$H37*SUMIFS('Forecast Engine'!$AK$4:$AK$12,'Forecast Engine'!$A$4:$A$12,$C37,'Forecast Engine'!$B$4:$B$12,$D37) | J37: =$H37*SUMIFS('Forecast Engine'!$AL$4:$AL$12,'Forecast Engine'!$A$4:$A$12,$C37,'Forecast Engine'!$B$4:$B$12,$D37) | K37: =$H37*SUMIFS('Forecast Engine'!$AM$4:$AM$12,'Forecast Engine'!$A$4:$A$12,$C37,'Forecast Engine'!$B$4:$B$12,$D37) | L37: =SUM(I37:K37)
C38: Mamaearth | D38: Face | E38: Balaji Associates Distri | F38: East | G38: 0.7827 | H38: =IFERROR(G38/SUMIFS($G$4:$G$1504,$C$4:$C$1504,$C38,$D$4:$D$1504,$D38),0) | I38: =$H38*SUMIFS('Forecast Engine'!$AK$4:$AK$12,'Forecast Engine'!$A$4:$A$12,$C38,'Forecast Engine'!$B$4:$B$12,$D38) | J38: =$H38*SUMIFS('Forecast Engine'!$AL$4:$AL$12,'Forecast Engine'!$A$4:$A$12,$C38,'Forecast Engine'!$B$4:$B$12,$D38) | K38: =$H38*SUMIFS('Forecast Engine'!$AM$4:$AM$12,'Forecast Engine'!$A$4:$A$12,$C38,'Forecast Engine'!$B$4:$B$12,$D38) | L38: =SUM(I38:K38)
A39: 10101163 | B39: Rice Dewy Bright Face wash | C39: Mamaearth | D39: Face | E39: Apollo Healthco | F39: South-2 | G39: 0.7147 | H39: =IFERROR(G39/SUMIFS($G$4:$G$1504,$C$4:$C$1504,$C39,$D$4:$D$1504,$D39),0) | I39: =$H39*SUMIFS('Forecast Engine'!$AK$4:$AK$12,'Forecast Engine'!$A$4:$A$12,$C39,'Forecast Engine'!$B$4:$B$12,$D39) | J39: =$H39*SUMIFS('Forecast Engine'!$AL$4:$AL$12,'Forecast Engine'!$A$4:$A$12,$C39,'Forecast Engine'!$B$4:$B$12,$D39) | K39: =$H39*SUMIFS('Forecast Engine'!$AM$4:$AM$12,'Forecast Engine'!$A$4:$A$12,$C39,'Forecast Engine'!$B$4:$B$12,$D39) | L39: =SUM(I39:K39)
C40: Mamaearth | D40: Face | E40: Apollo Healthco | F40: South-2 | G40: 0.7005 | H40: =IFERROR(G40/SUMIFS($G$4:$G$1504,$C$4:$C$1504,$C40,$D$4:$D$1504,$D40),0) | I40: =$H40*SUMIFS('Forecast Engine'!$AK$4:$AK$12,'Forecast Engine'!$A$4:$A$12,$C40,'Forecast Engine'!$B$4:$B$12,$D40) | J40: =$H40*SUMIFS('Forecast Engine'!$AL$4:$AL$12,'Forecast Engine'!$A$4:$A$12,$C40,'Forecast Engine'!$B$4:$B$12,$D40) | K40: =$H40*SUMIFS('Forecast Engine'!$AM$4:$AM$12,'Forecast Engine'!$A$4:$A$12,$C40,'Forecast Engine'!$B$4:$B$12,$D40) | L40: =SUM(I40:K40)
C41: Mamaearth | D41: Face | E41: VISHAL ENTERPRISES | F41: West | G41: 0.7003 | H41: =IFERROR(G41/SUMIFS($G$4:$G$1504,$C$4:$C$1504,$C41,$D$4:$D$1504,$D41),0) | I41: =$H41*SUMIFS('Forecast Engine'!$AK$4:$AK$12,'Forecast Engine'!$A$4:$A$12,$C41,'Forecast Engine'!$B$4:$B$12,$D41) | J41: =$H41*SUMIFS('Forecast Engine'!$AL$4:$AL$12,'Forecast Engine'!$A$4:$A$12,$C41,'Forecast Engine'!$B$4:$B$12,$D41) | K41: =$H41*SUMIFS('Forecast Engine'!$AM$4:$AM$12,'Forecast Engine'!$A$4:$A$12,$C41,'Forecast Engine'!$B$4:$B$12,$D41) | L41: =SUM(I41:K41)
C42: Mamaearth | D42: Face | E42: Apollo Healthco | F42: East | G42: 0.6787 | H42: =IFERROR(G42/SUMIFS($G$4:$G$1504,$C$4:$C$1504,$C42,$D$4:$D$1504,$D42),0) | I42: =$H42*SUMIFS('Forecast Engine'!$AK$4:$AK$12,'Forecast Engine'!$A$4:$A$12,$C42,'Forecast Engine'!$B$4:$B$12,$D42) | J42: =$H42*SUMIFS('Forecast Engine'!$AL$4:$AL$12,'Forecast Engine'!$A$4:$A$12,$C42,'Forecast Engine'!$B$4:$B$12,$D42) | K42: =$H42*SUMIFS('Forecast Engine'!$AM$4:$AM$12,'Forecast Engine'!$A$4:$A$12,$C42,'Forecast Engine'!$B$4:$B$12,$D42) | L42: =SUM(I42:K42)
A43: 10100618 | B43: Rice Face Wash 100 ml | C43: Mamaearth | D43: Face | E43: Sri Vijaya Durga Agencie | F43: South-2 | G43: 0.6773 | H43: =IFERROR(G43/SUMIFS($G$4:$G$1504,$C$4:$C$1504,$C43,$D$4:$D$1504,$D43),0) | I43: =$H43*SUMIFS('Forecast Engine'!$AK$4:$AK$12,'Forecast Engine'!$A$4:$A$12,$C43,'Forecast Engine'!$B$4:$B$12,$D43) | J43: =$H43*SUMIFS('Forecast Engine'!$AL$4:$AL$12,'Forecast Engine'!$A$4:$A$12,$C43,'Forecast Engine'!$B$4:$B$12,$D43) | K43: =$H43*SUMIFS('Forecast Engine'!$AM$4:$AM$12,'Forecast Engine'!$A$4:$A$12,$C43,'Forecast Engine'!$B$4:$B$12,$D43) | L43: =SUM(I43:K43)
A44: 10100695 | B44: ME Ubtan Natural Glow Face Wash With Turmeric & | C44: Mamaearth | D44: Face | E44: Kiran Trading Company | F44: West | G44: 0.6715 | H44: =IFERROR(G44/SUMIFS($G$4:$G$1504,$C$4:$C$1504,$C44,$D$4:$D$1504,$D44),0) | I44: =$H44*SUMIFS('Forecast Engine'!$AK$4:$AK$12,'Forecast Engine'!$A$4:$A$12,$C44,'Forecast Engine'!$B$4:$B$12,$D44) | J44: =$H44*SUMIFS('Forecast Engine'!$AL$4:$AL$12,'Forecast Engine'!$A$4:$A$12,$C44,'Forecast Engine'!$B$4:$B$12,$D44) | K44: =$H44*SUMIFS('Forecast Engine'!$AM$4:$AM$12,'Forecast Engine'!$A$4:$A$12,$C44,'Forecast Engine'!$B$4:$B$12,$D44) | L44: =SUM(I44:K44)
A45: 10100062 | B45: Mamaearth Ultra Light Indian Sunscreen with Carr | C45: Mamaearth | D45: Face | E45: Kiran Trading Company | F45: West | G45: 0.6546 | H45: =IFERROR(G45/SUMIFS($G$4:$G$1504,$C$4:$C$1504,$C45,$D$4:$D$1504,$D45),0) | I45: =$H45*SUMIFS('Forecast Engine'!$AK$4:$AK$12,'Forecast Engine'!$A$4:$A$12,$C45,'Forecast Engine'!$B$4:$B$12,$D45) | J45: =$H45*SUMIFS('Forecast Engine'!$AL$4:$AL$12,'Forecast Engine'!$A$4:$A$12,$C45,'Forecast Engine'!$B$4:$B$12,$D45) | K45: =$H45*SUMIFS('Forecast Engine'!$AM$4:$AM$12,'Forecast Engine'!$A$4:$A$12,$C45,'Forecast Engine'!$B$4:$B$12,$D45) | L45: =SUM(I45:K45)
C46: Mamaearth | D46: Face | E46: M/S KOTTARAM BUSINESS | F46: South-1 | G46: 0.6518 | H46: =IFERROR(G46/SUMIFS($G$4:$G$1504,$C$4:$C$1504,$C46,$D$4:$D$1504,$D46),0) | I46: =$H46*SUMIFS('Forecast Engine'!$AK$4:$AK$12,'Forecast Engine'!$A$4:$A$12,$C46,'Forecast Engine'!$B$4:$B$12,$D46) | J46: =$H46*SUMIFS('Forecast Engine'!$AL$4:$AL$12,'Forecast Engine'!$A$4:$A$12,$C46,'Forecast Engine'!$B$4:$B$12,$D46) | K46: =$H46*SUMIFS('Forecast Engine'!$AM$4:$AM$12,'Forecast Engine'!$A$4:$A$12,$C46,'Forecast Engine'!$B$4:$B$12,$D46) | L46: =SUM(I46:K46)
A47: 10101163 | B47: Rice Dewy Bright Face wash | C47: Mamaearth | D47: Face | E47: D-Mart | F47: South-1 | G47: 0.6223 | H47: =IFERROR(G47/SUMIFS($G$4:$G$1504,$C$4:$C$1504,$C47,$D$4:$D$1504,$D47),0) | I47: =$H47*SUMIFS('Forecast Engine'!$AK$4:$AK$12,'Forecast Engine'!$A$4:$A$12,$C47,'Forecast Engine'!$B$4:$B$12,$D47) | J47: =$H47*SUMIFS('Forecast Engine'!$AL$4:$AL$12,'Forecast Engine'!$A$4:$A$12,$C47,'Forecast Engine'!$B$4:$B$12,$D47) | K47: =$H47*SUMIFS('Forecast Engine'!$AM$4:$AM$12,'Forecast Engine'!$A$4:$A$12,$C47,'Forecast Engine'!$B$4:$B$12,$D47) | L47: =SUM(I47:K47)
C48: Mamaearth | D48: Face | E48: JUST MARK-D-Mart | F48: West | G48: 0.6147 | H48: =IFERROR(G48/SUMIFS($G$4:$G$1504,$C$4:$C$1504,$C48,$D$4:$D$1504,$D48),0) | I48: =$H48*SUMIFS('Forecast Engine'!$AK$4:$AK$12,'Forecast Engine'!$A$4:$A$12,$C48,'Forecast Engine'!$B$4:$B$12,$D48) | J48: =$H48*SUMIFS('Forecast Engine'!$AL$4:$AL$12,'Forecast Engine'!$A$4:$A$12,$C48,'Forecast Engine'!$B$4:$B$12,$D48) | K48: =$H48*SUMIFS('Forecast Engine'!$AM$4:$AM$12,'Forecast Engine'!$A$4:$A$12,$C48,'Forecast Engine'!$B$4:$B$12,$D48) | L48: =SUM(I48:K48)
A49: 10100062 | B49: Mamaearth Ultra Light Indian Sunscreen with Carr | C49: Mamaearth | D49: Face | E49: JUST MARK-Dmart | F49: West | G49: 0.605 | H49: =IFERROR(G49/SUMIFS($G$4:$G$1504,$C$4:$C$1504,$C49,$D$4:$D$1504,$D49),0) | I49: =$H49*SUMIFS('Forecast Engine'!$AK$4:$AK$12,'Forecast Engine'!$A$4:$A$12,$C49,'Forecast Engine'!$B$4:$B$12,$D49) | J49: =$H49*SUMIFS('Forecast Engine'!$AL$4:$AL$12,'Forecast Engine'!$A$4:$A$12,$C49,'Forecast Engine'!$B$4:$B$12,$D49) | K49: =$H49*SUMIFS('Forecast Engine'!$AM$4:$AM$12,'Forecast Engine'!$A$4:$A$12,$C49,'Forecast Engine'!$B$4:$B$12,$D49) | L49: =SUM(I49:K49)
A50: 10101163 | B50: Rice Dewy Bright Face wash | C50: Mamaearth | D50: Face | E50: D-Mart | F50: South-2 | G50: 0.5983 | H50: =IFERROR(G50/SUMIFS($G$4:$G$1504,$C$4:$C$1504,$C50,$D$4:$D$1504,$D50),0) | I50: =$H50*SUMIFS('Forecast Engine'!$AK$4:$AK$12,'Forecast Engine'!$A$4:$A$12,$C50,'Forecast Engine'!$B$4:$B$12,$D50) | J50: =$H50*SUMIFS('Forecast Engine'!$AL$4:$AL$12,'Forecast Engine'!$A$4:$A$12,$C50,'Forecast Engine'!$B$4:$B$12,$D50) | K50: =$H50*SUMIFS('Forecast Engine'!$AM$4:$AM$12,'Forecast Engine'!$A$4:$A$12,$C50,'Forecast Engine'!$B$4:$B$12,$D50) | L50: =SUM(I50:K50)
C51: Mamaearth | D51: Face | E51: Apollo Healthco | F51: West | G51: 0.5562 | H51: =IFERROR(G51/SUMIFS($G$4:$G$1504,$C$4:$C$1504,$C51,$D$4:$D$1504,$D51),0) | I51: =$H51*SUMIFS('Forecast Engine'!$AK$4:$AK$12,'Forecast Engine'!$A$4:$A$12,$C51,'Forecast Engine'!$B$4:$B$12,$D51) | J51: =$H51*SUMIFS('Forecast Engine'!$AL$4:$AL$12,'Forecast Engine'!$A$4:$A$12,$C51,'Forecast Engine'!$B$4:$B$12,$D51) | K51: =$H51*SUMIFS('Forecast Engine'!$AM$4:$AM$12,'Forecast Engine'!$A$4:$A$12,$C51,'Forecast Engine'!$B$4:$B$12,$D51) | L51: =SUM(I51:K51)
C52: Mamaearth | D52: Face | E52: Nykaa E-Retail Limited | F52: South-1 | G52: 0.5423 | H52: =IFERROR(G52/SUMIFS($G$4:$G$1504,$C$4:$C$1504,$C52,$D$4:$D$1504,$D52),0) | I52: =$H52*SUMIFS('Forecast Engine'!$AK$4:$AK$12,'Forecast Engine'!$A$4:$A$12,$C52,'Forecast Engine'!$B$4:$B$12,$D52) | J52: =$H52*SUMIFS('Forecast Engine'!$AL$4:$AL$12,'Forecast Engine'!$A$4:$A$12,$C52,'Forecast Engine'!$B$4:$B$12,$D52) | K52: =$H52*SUMIFS('Forecast Engine'!$AM$4:$AM$12,'Forecast Engine'!$A$4:$A$12,$C52,'Forecast Engine'!$B$4:$B$12,$D52) | L52: =SUM(I52:K52)
C53: Mamaearth | D53: Face | E53: Wellness Forever | F53: West | G53: 0.537 | H53: =IFERROR(G53/SUMIFS($G$4:$G$1504,$C$4:$C$1504,$C53,$D$4:$D$1504,$D53),0) | I53: =$H53*SUMIFS('Forecast Engine'!$AK$4:$AK$12,'Forecast Engine'!$A$4:$A$12,$C53,'Forecast Engine'!$B$4:$B$12,$D53) | J53: =$H53*SUMIFS('Forecast Engine'!$AL$4:$AL$12,'Forecast Engine'!$A$4:$A$12,$C53,'Forecast Engine'!$B$4:$B$12,$D53) | K53: =$H53*SUMIFS('Forecast Engine'!$AM$4:$AM$12,'Forecast Engine'!$A$4:$A$12,$C53,'Forecast Engine'!$B$4:$B$12,$D53) | L53: =SUM(I53:K53)
A54: 10100695 | B54: ME Ubtan Natural Glow Face Wash With Turmeric & | C54: Mamaearth | D54: Face | E54: Reliance Retail Limited | F54: South-1 | G54: 0.5246 | H54: =IFERROR(G54/SUMIFS($G$4:$G$1504,$C$4:$C$1504,$C54,$D$4:$D$1504,$D54),0) | I54: =$H54*SUMIFS('Forecast Engine'!$AK$4:$AK$12,'Forecast Engine'!$A$4:$A$12,$C54,'Forecast Engine'!$B$4:$B$12,$D54) | J54: =$H54*SUMIFS('Forecast Engine'!$AL$4:$AL$12,'Forecast Engine'!$A$4:$A$12,$C54,'Forecast Engine'!$B$4:$B$12,$D54) | K54: =$H54*SUMIFS('Forecast Engine'!$AM$4:$AM$12,'Forecast Engine'!$A$4:$A$12,$C54,'Forecast Engine'!$B$4:$B$12,$D54) | L54: =SUM(I54:K54)
C55: Mamaearth | D55: Face | E55: Nykaa E-Retail Limited | F55: West | G55: 0.5185 | H55: =IFERROR(G55/SUMIFS($G$4:$G$1504,$C$4:$C$1504,$C55,$D$4:$D$1504,$D55),0) | I55: =$H55*SUMIFS('Forecast Engine'!$AK$4:$AK$12,'Forecast Engine'!$A$4:$A$12,$C55,'Forecast Engine'!$B$4:$B$12,$D55) | J55: =$H55*SUMIFS('Forecast Engine'!$AL$4:$AL$12,'Forecast Engine'!$A$4:$A$12,$C55,'Forecast Engine'!$B$4:$B$12,$D55) | K55: =$H55*SUMIFS('Forecast Engine'!$AM$4:$AM$12,'Forecast Engine'!$A$4:$A$12,$C55,'Forecast Engine'!$B$4:$B$12,$D55) | L55: =SUM(I55:K55)
A56: 10101163 | B56: Rice Dewy Bright Face wash | C56: Mamaearth | D56: Face | E56: Reliance Retail Limited | F56: South-1 | G56: 0.5069 | H56: =IFERROR(G56/SUMIFS($G$4:$G$1504,$C$4:$C$1504,$C56,$D$4:$D$1504,$D56),0) | I56: =$H56*SUMIFS('Forecast Engine'!$AK$4:$AK$12,'Forecast Engine'!$A$4:$A$12,$C56,'Forecast Engine'!$B$4:$B$12,$D56) | J56: =$H56*SUMIFS('Forecast Engine'!$AL$4:$AL$12,'Forecast Engine'!$A$4:$A$12,$C56,'Forecast Engine'!$B$4:$B$12,$D56) | K56: =$H56*SUMIFS('Forecast Engine'!$AM$4:$AM$12,'Forecast Engine'!$A$4:$A$12,$C56,'Forecast Engine'!$B$4:$B$12,$D56) | L56: =SUM(I56:K56)
A57: 10101166 | B57: Vitamin C Face Wash 150 ml | C57: Mamaearth | D57: Face | E57: Apollo Healthco | F57: South-1 | G57: 0.5016 | H57: =IFERROR(G57/SUMIFS($G$4:$G$1504,$C$4:$C$1504,$C57,$D$4:$D$1504,$D57),0) | I57: =$H57*SUMIFS('Forecast Engine'!$AK$4:$AK$12,'Forecast Engine'!$A$4:$A$12,$C57,'Forecast Engine'!$B$4:$B$12,$D57) | J57: =$H57*SUMIFS('Forecast Engine'!$AL$4:$AL$12,'Forecast Engine'!$A$4:$A$12,$C57,'Forecast Engine'!$B$4:$B$12,$D57) | K57: =$H57*SUMIFS('Forecast Engine'!$AM$4:$AM$12,'Forecast Engine'!$A$4:$A$12,$C57,'Forecast Engine'!$B$4:$B$12,$D57) | L57: =SUM(I57:K57)
A58: 10100618 | B58: Rice Face Wash 100 ml | C58: Mamaearth | D58: Face | E58: Nykaa E-Retail Limited | F58: East | G58: 0.4928 | H58: =IFERROR(G58/SUMIFS($G$4:$G$1504,$C$4:$C$1504,$C58,$D$4:$D$1504,$D58),0) | I58: =$H58*SUMIFS('Forecast Engine'!$AK$4:$AK$12,'Forecast Engine'!$A$4:$A$12,$C58,'Forecast Engine'!$B$4:$B$12,$D58) | J58: =$H58*SUMIFS('Forecast Engine'!$AL$4:$AL$12,'Forecast Engine'!$A$4:$A$12,$C58,'Forecast Engine'!$B$4:$B$12,$D58) | K58: =$H58*SUMIFS('Forecast Engine'!$AM$4:$AM$12,'Forecast Engine'!$A$4:$A$12,$C58,'Forecast Engine'!$B$4:$B$12,$D58) | L58: =SUM(I58:K58)
A59: 10100062 | B59: Mamaearth Ultra Light Indian Sunscreen with Carr | C59: Mamaearth | D59: Face | E59: D-Mart | F59: South-1 | G59: 0.4658 | H59: =IFERROR(G59/SUMIFS($G$4:$G$1504,$C$4:$C$1504,$C59,$D$4:$D$1504,$D59),0) | I59: =$H59*SUMIFS('Forecast Engine'!$AK$4:$AK$12,'Forecast Engine'!$A$4:$A$12,$C59,'Forecast Engine'!$B$4:$B$12,$D59) | J59: =$H59*SUMIFS('Forecast Engine'!$AL$4:$AL$12,'Forecast Engine'!$A$4:$A$12,$C59,'Forecast Engine'!$B$4:$B$12,$D59) | K59: =$H59*SUMIFS('Forecast Engine'!$AM$4:$AM$12,'Forecast Engine'!$A$4:$A$12,$C59,'Forecast Engine'!$B$4:$B$12,$D59) | L59: =SUM(I59:K59)
A60: 10100618 | B60: Rice Face Wash 100 ml | C60: Mamaearth | D60: Face | E60: D-Mart | F60: North | G60: 0.4577 | H60: =IFERROR(G60/SUMIFS($G$4:$G$1504,$C$4:$C$1504,$C60,$D$4:$D$1504,$D60),0) | I60: =$H60*SUMIFS('Forecast Engine'!$AK$4:$AK$12,'Forecast Engine'!$A$4:$A$12,$C60,'Forecast Engine'!$B$4:$B$12,$D60) | J60: =$H60*SUMIFS('Forecast Engine'!$AL$4:$AL$12,'Forecast Engine'!$A$4:$A$12,$C60,'Forecast Engine'!$B$4:$B$12,$D60) | K60: =$H60*SUMIFS('Forecast Engine'!$AM$4:$AM$12,'Forecast Engine'!$A$4:$A$12,$C60,'Forecast Engine'!$B$4:$B$12,$D60) | L60: =SUM(I60:K60)
C61: Mamaearth | D61: Face | E61: Kiran Trading Company-So | F61: West | G61: 0.4573 | H61: =IFERROR(G61/SUMIFS($G$4:$G$1504,$C$4:$C$1504,$C61,$D$4:$D$1504,$D61),0) | I61: =$H61*SUMIFS('Forecast Engine'!$AK$4:$AK$12,'Forecast Engine'!$A$4:$A$12,$C61,'Forecast Engine'!$B$4:$B$12,$D61) | J61: =$H61*SUMIFS('Forecast Engine'!$AL$4:$AL$12,'Forecast Engine'!$A$4:$A$12,$C61,'Forecast Engine'!$B$4:$B$12,$D61) | K61: =$H61*SUMIFS('Forecast Engine'!$AM$4:$AM$12,'Forecast Engine'!$A$4:$A$12,$C61,'Forecast Engine'!$B$4:$B$12,$D61) | L61: =SUM(I61:K61)
A62: 10100062 | B62: Mamaearth Ultra Light Indian Sunscreen with Carr | C62: Mamaearth | D62: Face | E62: D-Mart | F62: West | G62: 0.4494 | H62: =IFERROR(G62/SUMIFS($G$4:$G$1504,$C$4:$C$1504,$C62,$D$4:$D$1504,$D62),0) | I62: =$H62*SUMIFS('Forecast Engine'!$AK$4:$AK$12,'Forecast Engine'!$A$4:$A$12,$C62,'Forecast Engine'!$B$4:$B$12,$D62) | J62: =$H62*SUMIFS('Forecast Engine'!$AL$4:$AL$12,'Forecast Engine'!$A$4:$A$12,$C62,'Forecast Engine'!$B$4:$B$12,$D62) | K62: =$H62*SUMIFS('Forecast Engine'!$AM$4:$AM$12,'Forecast Engine'!$A$4:$A$12,$C62,'Forecast Engine'!$B$4:$B$12,$D62) | L62: =SUM(I62:K62)
C63: Mamaearth | D63: Face | E63: Az Enterprises | F63: South-1 | G63: 0.4403 | H63: =IFERROR(G63/SUMIFS($G$4:$G$1504,$C$4:$C$1504,$C63,$D$4:$D$1504,$D63),0) | I63: =$H63*SUMIFS('Forecast Engine'!$AK$4:$AK$12,'Forecast Engine'!$A$4:$A$12,$C63,'Forecast Engine'!$B$4:$B$12,$D63) | J63: =$H63*SUMIFS('Forecast Engine'!$AL$4:$AL$12,'Forecast Engine'!$A$4:$A$12,$C63,'Forecast Engine'!$B$4:$B$12,$D63) | K63: =$H63*SUMIFS('Forecast Engine'!$AM$4:$AM$12,'Forecast Engine'!$A$4:$A$12,$C63,'Forecast Engine'!$B$4:$B$12,$D63) | L63: =SUM(I63:K63)
A64: 10101163 | B64: Rice Dewy Bright Face wash | C64: Mamaearth | D64: Face | E64: G.V Enterprises | F64: South-1 | G64: 0.4393 | H64: =IFERROR(G64/SUMIFS($G$4:$G$1504,$C$4:$C$1504,$C64,$D$4:$D$1504,$D64),0) | I64: =$H64*SUMIFS('Forecast Engine'!$AK$4:$AK$12,'Forecast Engine'!$A$4:$A$12,$C64,'Forecast Engine'!$B$4:$B$12,$D64) | J64: =$H64*SUMIFS('Forecast Engine'!$AL$4:$AL$12,'Forecast Engine'!$A$4:$A$12,$C64,'Forecast Engine'!$B$4:$B$12,$D64) | K64: =$H64*SUMIFS('Forecast Engine'!$AM$4:$AM$12,'Forecast Engine'!$A$4:$A$12,$C64,'Forecast Engine'!$B$4:$B$12,$D64) | L64: =SUM(I64:K64)
A65: 10100062 | B65: Mamaearth Ultra Light Indian Sunscreen with Carr | C65: Mamaearth | D65: Face | E65: Reliance Retail Limited | F65: North | G65: 0.432 | H65: =IFERROR(G65/SUMIFS($G$4:$G$1504,$C$4:$C$1504,$C65,$D$4:$D$1504,$D65),0) | I65: =$H65*SUMIFS('Forecast Engine'!$AK$4:$AK$12,'Forecast Engine'!$A$4:$A$12,$C65,'Forecast Engine'!$B$4:$B$12,$D65) | J65: =$H65*SUMIFS('Forecast Engine'!$AL$4:$AL$12,'Forecast Engine'!$A$4:$A$12,$C65,'Forecast Engine'!$B$4:$B$12,$D65) | K65: =$H65*SUMIFS('Forecast Engine'!$AM$4:$AM$12,'Forecast Engine'!$A$4:$A$12,$C65,'Forecast Engine'!$B$4:$B$12,$D65) | L65: =SUM(I65:K65)
A66: 10101163 | B66: Rice Dewy Bright Face wash | C66: Mamaearth | D66: Face | E66: Apollo Healthco | F66: North | G66: 0.4238 | H66: =IFERROR(G66/SUMIFS($G$4:$G$1504,$C$4:$C$1504,$C66,$D$4:$D$1504,$D66),0) | I66: =$H66*SUMIFS('Forecast Engine'!$AK$4:$AK$12,'Forecast Engine'!$A$4:$A$12,$C66,'Forecast Engine'!$B$4:$B$12,$D66) | J66: =$H66*SUMIFS('Forecast Engine'!$AL$4:$AL$12,'Forecast Engine'!$A$4:$A$12,$C66,'Forecast Engine'!$B$4:$B$12,$D66) | K66: =$H66*SUMIFS('Forecast Engine'!$AM$4:$AM$12,'Forecast Engine'!$A$4:$A$12,$C66,'Forecast Engine'!$B$4:$B$12,$D66) | L66: =SUM(I66:K66)
A67: 10100695 | B67: ME Ubtan Natural Glow Face Wash With Turmeric & | C67: Mamaearth | D67: Face | E67: D-Mart | F67: South-1 | G67: 0.4214 | H67: =IFERROR(G67/SUMIFS($G$4:$G$1504,$C$4:$C$1504,$C67,$D$4:$D$1504,$D67),0) | I67: =$H67*SUMIFS('Forecast Engine'!$AK$4:$AK$12,'Forecast Engine'!$A$4:$A$12,$C67,'Forecast Engine'!$B$4:$B$12,$D67) | J67: =$H67*SUMIFS('Forecast Engine'!$AL$4:$AL$12,'Forecast Engine'!$A$4:$A$12,$C67,'Forecast Engine'!$B$4:$B$12,$D67) | K67: =$H67*SUMIFS('Forecast Engine'!$AM$4:$AM$12,'Forecast Engine'!$A$4:$A$12,$C67,'Forecast Engine'!$B$4:$B$12,$D67) | L67: =SUM(I67:K67)
C68: Mamaearth | D68: Face | E68: Walmart-CNC | F68: North | G68: 0.3894 | H68: =IFERROR(G68/SUMIFS($G$4:$G$1504,$C$4:$C$1504,$C68,$D$4:$D$1504,$D68),0) | I68: =$H68*SUMIFS('Forecast Engine'!$AK$4:$AK$12,'Forecast Engine'!$A$4:$A$12,$C68,'Forecast Engine'!$B$4:$B$12,$D68) | J68: =$H68*SUMIFS('Forecast Engine'!$AL$4:$AL$12,'Forecast Engine'!$A$4:$A$12,$C68,'Forecast Engine'!$B$4:$B$12,$D68) | K68: =$H68*SUMIFS('Forecast Engine'!$AM$4:$AM$12,'Forecast Engine'!$A$4:$A$12,$C68,'Forecast Engine'!$B$4:$B$12,$D68) | L68: =SUM(I68:K68)
A69: 10100035 | B69: ME Ubtan Natural Glow Face Wash With Turmeric & | C69: Mamaearth | D69: Face | E69: D-Mart | F69: West | G69: 0.363 | H69: =IFERROR(G69/SUMIFS($G$4:$G$1504,$C$4:$C$1504,$C69,$D$4:$D$1504,$D69),0) | I69: =$H69*SUMIFS('Forecast Engine'!$AK$4:$AK$12,'Forecast Engine'!$A$4:$A$12,$C69,'Forecast Engine'!$B$4:$B$12,$D69) | J69: =$H69*SUMIFS('Forecast Engine'!$AL$4:$AL$12,'Forecast Engine'!$A$4:$A$12,$C69,'Forecast Engine'!$B$4:$B$12,$D69) | K69: =$H69*SUMIFS('Forecast Engine'!$AM$4:$AM$12,'Forecast Engine'!$A$4:$A$12,$C69,'Forecast Engine'!$B$4:$B$12,$D69) | L69: =SUM(I69:K69)
A70: 10100062 | B70: Mamaearth Ultra Light Indian Sunscreen with Carr | C70: Mamaearth | D70: Face | E70: G.V Enterprises | F70: South-1 | G70: 0.3589 | H70: =IFERROR(G70/SUMIFS($G$4:$G$1504,$C$4:$C$1504,$C70,$D$4:$D$1504,$D70),0) | I70: =$H70*SUMIFS('Forecast Engine'!$AK$4:$AK$12,'Forecast Engine'!$A$4:$A$12,$C70,'Forecast Engine'!$B$4:$B$12,$D70) | J70: =$H70*SUMIFS('Forecast Engine'!$AL$4:$AL$12,'Forecast Engine'!$A$4:$A$12,$C70,'Forecast Engine'!$B$4:$B$12,$D70) | K70: =$H70*SUMIFS('Forecast Engine'!$AM$4:$AM$12,'Forecast Engine'!$A$4:$A$12,$C70,'Forecast Engine'!$B$4:$B$12,$D70) | L70: =SUM(I70:K70)
A71: 10100035 | B71: ME Ubtan Natural Glow Face Wash With Turmeric & | C71: Mamaearth | D71: Face | E71: JUST MARK-Dmart | F71: West | G71: 0.3582 | H71: =IFERROR(G71/SUMIFS($G$4:$G$1504,$C$4:$C$1504,$C71,$D$4:$D$1504,$D71),0) | I71: =$H71*SUMIFS('Forecast Engine'!$AK$4:$AK$12,'Forecast Engine'!$A$4:$A$12,$C71,'Forecast Engine'!$B$4:$B$12,$D71) | J71: =$H71*SUMIFS('Forecast Engine'!$AL$4:$AL$12,'Forecast Engine'!$A$4:$A$12,$C71,'Forecast Engine'!$B$4:$B$12,$D71) | K71: =$H71*SUMIFS('Forecast Engine'!$AM$4:$AM$12,'Forecast Engine'!$A$4:$A$12,$C71,'Forecast Engine'!$B$4:$B$12,$D71) | L71: =SUM(I71:K71)
A72: 10100955 | B72: Multani Mitti Face Wash 100 ml | C72: Mamaearth | D72: Face | E72: G.V Enterprises | F72: South-1 | G72: 0.3563 | H72: =IFERROR(G72/SUMIFS($G$4:$G$1504,$C$4:$C$1504,$C72,$D$4:$D$1504,$D72),0) | I72: =$H72*SUMIFS('Forecast Engine'!$AK$4:$AK$12,'Forecast Engine'!$A$4:$A$12,$C72,'Forecast Engine'!$B$4:$B$12,$D72) | J72: =$H72*SUMIFS('Forecast Engine'!$AL$4:$AL$12,'Forecast Engine'!$A$4:$A$12,$C72,'Forecast Engine'!$B$4:$B$12,$D72) | K72: =$H72*SUMIFS('Forecast Engine'!$AM$4:$AM$12,'Forecast Engine'!$A$4:$A$12,$C72,'Forecast Engine'!$B$4:$B$12,$D72) | L72: =SUM(I72:K72)
A73: 10100062 | B73: Mamaearth Ultra Light Indian Sunscreen with Carr | C73: Mamaearth | D73: Face | E73: Apollo Healthco | F73: South-1 | G73: 0.355 | H73: =IFERROR(G73/SUMIFS($G$4:$G$1504,$C$4:$C$1504,$C73,$D$4:$D$1504,$D73),0) | I73: =$H73*SUMIFS('Forecast Engine'!$AK$4:$AK$12,'Forecast Engine'!$A$4:$A$12,$C73,'Forecast Engine'!$B$4:$B$12,$D73) | J73: =$H73*SUMIFS('Forecast Engine'!$AL$4:$AL$12,'Forecast Engine'!$A$4:$A$12,$C73,'Forecast Engine'!$B$4:$B$12,$D73) | K73: =$H73*SUMIFS('Forecast Engine'!$AM$4:$AM$12,'Forecast Engine'!$A$4:$A$12,$C73,'Forecast Engine'!$B$4:$B$12,$D73) | L73: =SUM(I73:K73)
A74: 10100695 | B74: ME Ubtan Natural Glow Face Wash With Turmeric & | C74: Mamaearth | D74: Face | E74: Sri Vijaya Durga Agencie | F74: South-2 | G74: 0.3505 | H74: =IFERROR(G74/SUMIFS($G$4:$G$1504,$C$4:$C$1504,$C74,$D$4:$D$1504,$D74),0) | I74: =$H74*SUMIFS('Forecast Engine'!$AK$4:$AK$12,'Forecast Engine'!$A$4:$A$12,$C74,'Forecast Engine'!$B$4:$B$12,$D74) | J74: =$H74*SUMIFS('Forecast Engine'!$AL$4:$AL$12,'Forecast Engine'!$A$4:$A$12,$C74,'Forecast Engine'!$B$4:$B$12,$D74) | K74: =$H74*SUMIFS('Forecast Engine'!$AM$4:$AM$12,'Forecast Engine'!$A$4:$A$12,$C74,'Forecast Engine'!$B$4:$B$12,$D74) | L74: =SUM(I74:K74)
A75: 10100912 | B75: Vitamin C Daily Glow Sunscreen 50 g | C75: Mamaearth | D75: Face | E75: Reliance Retail Limited | F75: North | G75: 0.3495 | H75: =IFERROR(G75/SUMIFS($G$4:$G$1504,$C$4:$C$1504,$C75,$D$4:$D$1504,$D75),0) | I75: =$H75*SUMIFS('Forecast Engine'!$AK$4:$AK$12,'Forecast Engine'!$A$4:$A$12,$C75,'Forecast Engine'!$B$4:$B$12,$D75) | J75: =$H75*SUMIFS('Forecast Engine'!$AL$4:$AL$12,'Forecast Engine'!$A$4:$A$12,$C75,'Forecast Engine'!$B$4:$B$12,$D75) | K75: =$H75*SUMIFS('Forecast Engine'!$AM$4:$AM$12,'Forecast Engine'!$A$4:$A$12,$C75,'Forecast Engine'!$B$4:$B$12,$D75) | L75: =SUM(I75:K75)
C76: Mamaearth | D76: Face | E76: CHHABRA TRADERS | F76: North | G76: 0.344 | H76: =IFERROR(G76/SUMIFS($G$4:$G$1504,$C$4:$C$1504,$C76,$D$4:$D$1504,$D76),0) | I76: =$H76*SUMIFS('Forecast Engine'!$AK$4:$AK$12,'Forecast Engine'!$A$4:$A$12,$C76,'Forecast Engine'!$B$4:$B$12,$D76) | J76: =$H76*SUMIFS('Forecast Engine'!$AL$4:$AL$12,'Forecast Engine'!$A$4:$A$12,$C76,'Forecast Engine'!$B$4:$B$12,$D76) | K76: =$H76*SUMIFS('Forecast Engine'!$AM$4:$AM$12,'Forecast Engine'!$A$4:$A$12,$C76,'Forecast Engine'!$B$4:$B$12,$D76) | L76: =SUM(I76:K76)
A77: 10101163 | B77: Rice Dewy Bright Face wash | C77: Mamaearth | D77: Face | E77: JUST MARK-D-Mart | F77: West | G77: 0.3383 | H77: =IFERROR(G77/SUMIFS($G$4:$G$1504,$C$4:$C$1504,$C77,$D$4:$D$1504,$D77),0) | I77: =$H77*SUMIFS('Forecast Engine'!$AK$4:$AK$12,'Forecast Engine'!$A$4:$A$12,$C77,'Forecast Engine'!$B$4:$B$12,$D77) | J77: =$H77*SUMIFS('Forecast Engine'!$AL$4:$AL$12,'Forecast Engine'!$A$4:$A$12,$C77,'Forecast Engine'!$B$4:$B$12,$D77) | K77: =$H77*SUMIFS('Forecast Engine'!$AM$4:$AM$12,'Forecast Engine'!$A$4:$A$12,$C77,'Forecast Engine'!$B$4:$B$12,$D77) | L77: =SUM(I77:K77)
A78: 10100121 | B78: Vitamin C Face Wash with Vitamin C and Turmeric | C78: Mamaearth | D78: Face | E78: D-Mart | F78: North | G78: 0.3297 | H78: =IFERROR(G78/SUMIFS($G$4:$G$1504,$C$4:$C$1504,$C78,$D$4:$D$1504,$D78),0) | I78: =$H78*SUMIFS('Forecast Engine'!$AK$4:$AK$12,'Forecast Engine'!$A$4:$A$12,$C78,'Forecast Engine'!$B$4:$B$12,$D78) | J78: =$H78*SUMIFS('Forecast Engine'!$AL$4:$AL$12,'Forecast Engine'!$A$4:$A$12,$C78,'Forecast Engine'!$B$4:$B$12,$D78) | K78: =$H78*SUMIFS('Forecast Engine'!$AM$4:$AM$12,'Forecast Engine'!$A$4:$A$12,$C78,'Forecast Engine'!$B$4:$B$12,$D78) | L78: =SUM(I78:K78)
C79: Mamaearth | D79: Face | E79: PRAGATI SALES-D-MART | F79: West | G79: 0.3282 | H79: =IFERROR(G79/SUMIFS($G$4:$G$1504,$C$4:$C$1504,$C79,$D$4:$D$1504,$D79),0) | I79: =$H79*SUMIFS('Forecast Engine'!$AK$4:$AK$12,'Forecast Engine'!$A$4:$A$12,$C79,'Forecast Engine'!$B$4:$B$12,$D79) | J79: =$H79*SUMIFS('Forecast Engine'!$AL$4:$AL$12,'Forecast Engine'!$A$4:$A$12,$C79,'Forecast Engine'!$B$4:$B$12,$D79) | K79: =$H79*SUMIFS('Forecast Engine'!$AM$4:$AM$12,'Forecast Engine'!$A$4:$A$12,$C79,'Forecast Engine'!$B$4:$B$12,$D79) | L79: =SUM(I79:K79)
A80: 10100618 | B80: Rice Face Wash 100 ml | C80: Mamaearth | D80: Face | E80: D-Mart | F80: West | G80: 0.3275 | H80: =IFERROR(G80/SUMIFS($G$4:$G$1504,$C$4:$C$1504,$C80,$D$4:$D$1504,$D80),0) | I80: =$H80*SUMIFS('Forecast Engine'!$AK$4:$AK$12,'Forecast Engine'!$A$4:$A$12,$C80,'Forecast Engine'!$B$4:$B$12,$D80) | J80: =$H80*SUMIFS('Forecast Engine'!$AL$4:$AL$12,'Forecast Engine'!$A$4:$A$12,$C80,'Forecast Engine'!$B$4:$B$12,$D80) | K80: =$H80*SUMIFS('Forecast Engine'!$AM$4:$AM$12,'Forecast Engine'!$A$4:$A$12,$C80,'Forecast Engine'!$B$4:$B$12,$D80) | L80: =SUM(I80:K80)
A81: 10100035 | B81: ME Ubtan Natural Glow Face Wash With Turmeric & | C81: Mamaearth | D81: Face | E81: Nykaa E-Retail Limited | F81: East | G81: 0.326 | H81: =IFERROR(G81/SUMIFS($G$4:$G$1504,$C$4:$C$1504,$C81,$D$4:$D$1504,$D81),0) | I81: =$H81*SUMIFS('Forecast Engine'!$AK$4:$AK$12,'Forecast Engine'!$A$4:$A$12,$C81,'Forecast Engine'!$B$4:$B$12,$D81) | J81: =$H81*SUMIFS('Forecast Engine'!$AL$4:$AL$12,'Forecast Engine'!$A$4:$A$12,$C81,'Forecast Engine'!$B$4:$B$12,$D81) | K81: =$H81*SUMIFS('Forecast Engine'!$AM$4:$AM$12,'Forecast Engine'!$A$4:$A$12,$C81,'Forecast Engine'!$B$4:$B$12,$D81) | L81: =SUM(I81:K81)
A82: 10101163 | B82: Rice Dewy Bright Face wash | C82: Mamaearth | D82: Face | E82: Apollo Healthco | F82: East | G82: 0.3237 | H82: =IFERROR(G82/SUMIFS($G$4:$G$1504,$C$4:$C$1504,$C82,$D$4:$D$1504,$D82),0) | I82: =$H82*SUMIFS('Forecast Engine'!$AK$4:$AK$12,'Forecast Engine'!$A$4:$A$12,$C82,'Forecast Engine'!$B$4:$B$12,$D82) | J82: =$H82*SUMIFS('Forecast Engine'!$AL$4:$AL$12,'Forecast Engine'!$A$4:$A$12,$C82,'Forecast Engine'!$B$4:$B$12,$D82) | K82: =$H82*SUMIFS('Forecast Engine'!$AM$4:$AM$12,'Forecast Engine'!$A$4:$A$12,$C82,'Forecast Engine'!$B$4:$B$12,$D82) | L82: =SUM(I82:K82)
A83: 10101163 | B83: Rice Dewy Bright Face wash | C83: Mamaearth | D83: Face | E83: Apollo Healthco | F83: West | G83: 0.3216 | H83: =IFERROR(G83/SUMIFS($G$4:$G$1504,$C$4:$C$1504,$C83,$D$4:$D$1504,$D83),0) | I83: =$H83*SUMIFS('Forecast Engine'!$AK$4:$AK$12,'Forecast Engine'!$A$4:$A$12,$C83,'Forecast Engine'!$B$4:$B$12,$D83) | J83: =$H83*SUMIFS('Forecast Engine'!$AL$4:$AL$12,'Forecast Engine'!$A$4:$A$12,$C83,'Forecast Engine'!$B$4:$B$12,$D83) | K83: =$H83*SUMIFS('Forecast Engine'!$AM$4:$AM$12,'Forecast Engine'!$A$4:$A$12,$C83,'Forecast Engine'!$B$4:$B$12,$D83) | L83: =SUM(I83:K83)
A84: 10100618 | B84: Rice Face Wash 100 ml | C84: Mamaearth | D84: Face | E84: G.V Enterprises | F84: South-1 | G84: 0.3206 | H84: =IFERROR(G84/SUMIFS($G$4:$G$1504,$C$4:$C$1504,$C84,$D$4:$D$1504,$D84),0) | I84: =$H84*SUMIFS('Forecast Engine'!$AK$4:$AK$12,'Forecast Engine'!$A$4:$A$12,$C84,'Forecast Engine'!$B$4:$B$12,$D84) | J84: =$H84*SUMIFS('Forecast Engine'!$AL$4:$AL$12,'Forecast Engine'!$A$4:$A$12,$C84,'Forecast Engine'!$B$4:$B$12,$D84) | K84: =$H84*SUMIFS('Forecast Engine'!$AM$4:$AM$12,'Forecast Engine'!$A$4:$A$12,$C84,'Forecast Engine'!$B$4:$B$12,$D84) | L84: =SUM(I84:K84)
A85: 10101163 | B85: Rice Dewy Bright Face wash | C85: Mamaearth | D85: Face | E85: Kiran Trading Company-So | F85: West | G85: 0.311 | H85: =IFERROR(G85/SUMIFS($G$4:$G$1504,$C$4:$C$1504,$C85,$D$4:$D$1504,$D85),0) | I85: =$H85*SUMIFS('Forecast Engine'!$AK$4:$AK$12,'Forecast Engine'!$A$4:$A$12,$C85,'Forecast Engine'!$B$4:$B$12,$D85) | J85: =$H85*SUMIFS('Forecast Engine'!$AL$4:$AL$12,'Forecast Engine'!$A$4:$A$12,$C85,'Forecast Engine'!$B$4:$B$12,$D85) | K85: =$H85*SUMIFS('Forecast Engine'!$AM$4:$AM$12,'Forecast Engine'!$A$4:$A$12,$C85,'Forecast Engine'!$B$4:$B$12,$D85) | L85: =SUM(I85:K85)
A86: 10101166 | B86: Vitamin C Face Wash 150 ml | C86: Mamaearth | D86: Face | E86: Apollo Healthco | F86: East | G86: 0.3091 | H86: =IFERROR(G86/SUMIFS($G$4:$G$1504,$C$4:$C$1504,$C86,$D$4:$D$1504,$D86),0) | I86: =$H86*SUMIFS('Forecast Engine'!$AK$4:$AK$12,'Forecast Engine'!$A$4:$A$12,$C86,'Forecast Engine'!$B$4:$B$12,$D86) | J86: =$H86*SUMIFS('Forecast Engine'!$AL$4:$AL$12,'Forecast Engine'!$A$4:$A$12,$C86,'Forecast Engine'!$B$4:$B$12,$D86) | K86: =$H86*SUMIFS('Forecast Engine'!$AM$4:$AM$12,'Forecast Engine'!$A$4:$A$12,$C86,'Forecast Engine'!$B$4:$B$12,$D86) | L86: =SUM(I86:K86)
A87: 10100618 | B87: Rice Face Wash 100 ml | C87: Mamaearth | D87: Face | E87: Nykaa E-Retail Limited | F87: North | G87: 0.3068 | H87: =IFERROR(G87/SUMIFS($G$4:$G$1504,$C$4:$C$1504,$C87,$D$4:$D$1504,$D87),0) | I87: =$H87*SUMIFS('Forecast Engine'!$AK$4:$AK$12,'Forecast Engine'!$A$4:$A$12,$C87,'Forecast Engine'!$B$4:$B$12,$D87) | J87: =$H87*SUMIFS('Forecast Engine'!$AL$4:$AL$12,'Forecast Engine'!$A$4:$A$12,$C87,'Forecast Engine'!$B$4:$B$12,$D87) | K87: =$H87*SUMIFS('Forecast Engine'!$AM$4:$AM$12,'Forecast Engine'!$A$4:$A$12,$C87,'Forecast Engine'!$B$4:$B$12,$D87) | L87: =SUM(I87:K87)
A88: 10100035 | B88: ME Ubtan Natural Glow Face Wash With Turmeric & | C88: Mamaearth | D88: Face | E88: D-Mart | F88: North | G88: 0.2939 | H88: =IFERROR(G88/SUMIFS($G$4:$G$1504,$C$4:$C$1504,$C88,$D$4:$D$1504,$D88),0) | I88: =$H88*SUMIFS('Forecast Engine'!$AK$4:$AK$12,'Forecast Engine'!$A$4:$A$12,$C88,'Forecast Engine'!$B$4:$B$12,$D88) | J88: =$H88*SUMIFS('Forecast Engine'!$AL$4:$AL$12,'Forecast Engine'!$A$4:$A$12,$C88,'Forecast Engine'!$B$4:$B$12,$D88) | K88: =$H88*SUMIFS('Forecast Engine'!$AM$4:$AM$12,'Forecast Engine'!$A$4:$A$12,$C88,'Forecast Engine'!$B$4:$B$12,$D88) | L88: =SUM(I88:K88)
C89: Mamaearth | D89: Face | E89: Arc Foods And Beverages | F89: South-1 | G89: 0.2927 | H89: =IFERROR(G89/SUMIFS($G$4:$G$1504,$C$4:$C$1504,$C89,$D$4:$D$1504,$D89),0) | I89: =$H89*SUMIFS('Forecast Engine'!$AK$4:$AK$12,'Forecast Engine'!$A$4:$A$12,$C89,'Forecast Engine'!$B$4:$B$12,$D89) | J89: =$H89*SUMIFS('Forecast Engine'!$AL$4:$AL$12,'Forecast Engine'!$A$4:$A$12,$C89,'Forecast Engine'!$B$4:$B$12,$D89) | K89: =$H89*SUMIFS('Forecast Engine'!$AM$4:$AM$12,'Forecast Engine'!$A$4:$A$12,$C89,'Forecast Engine'!$B$4:$B$12,$D89) | L89: =SUM(I89:K89)
A90: 10100912 | B90: Vitamin C Daily Glow Sunscreen 50 g | C90: Mamaearth | D90: Face | E90: D-Mart | F90: North | G90: 0.2885 | H90: =IFERROR(G90/SUMIFS($G$4:$G$1504,$C$4:$C$1504,$C90,$D$4:$D$1504,$D90),0) | I90: =$H90*SUMIFS('Forecast Engine'!$AK$4:$AK$12,'Forecast Engine'!$A$4:$A$12,$C90,'Forecast Engine'!$B$4:$B$12,$D90) | J90: =$H90*SUMIFS('Forecast Engine'!$AL$4:$AL$12,'Forecast Engine'!$A$4:$A$12,$C90,'Forecast Engine'!$B$4:$B$12,$D90) | K90: =$H90*SUMIFS('Forecast Engine'!$AM$4:$AM$12,'Forecast Engine'!$A$4:$A$12,$C90,'Forecast Engine'!$B$4:$B$12,$D90) | L90: =SUM(I90:K90)
A91: 10100121 | B91: Vitamin C Face Wash with Vitamin C and Turmeric | C91: Mamaearth | D91: Face | E91: Reliance Retail Limited | F91: North | G91: 0.2854 | H91: =IFERROR(G91/SUMIFS($G$4:$G$1504,$C$4:$C$1504,$C91,$D$4:$D$1504,$D91),0) | I91: =$H91*SUMIFS('Forecast Engine'!$AK$4:$AK$12,'Forecast Engine'!$A$4:$A$12,$C91,'Forecast Engine'!$B$4:$B$12,$D91) | J91: =$H91*SUMIFS('Forecast Engine'!$AL$4:$AL$12,'Forecast Engine'!$A$4:$A$12,$C91,'Forecast Engine'!$B$4:$B$12,$D91) | K91: =$H91*SUMIFS('Forecast Engine'!$AM$4:$AM$12,'Forecast Engine'!$A$4:$A$12,$C91,'Forecast Engine'!$B$4:$B$12,$D91) | L91: =SUM(I91:K91)
A92: 10101322 | B92: Vitamin C Daily Glow Light Moisturizing Cream 20 | C92: Mamaearth | D92: Face | E92: D-Mart | F92: North | G92: 0.2834 | H92: =IFERROR(G92/SUMIFS($G$4:$G$1504,$C$4:$C$1504,$C92,$D$4:$D$1504,$D92),0) | I92: =$H92*SUMIFS('Forecast Engine'!$AK$4:$AK$12,'Forecast Engine'!$A$4:$A$12,$C92,'Forecast Engine'!$B$4:$B$12,$D92) | J92: =$H92*SUMIFS('Forecast Engine'!$AL$4:$AL$12,'Forecast Engine'!$A$4:$A$12,$C92,'Forecast Engine'!$B$4:$B$12,$D92) | K92: =$H92*SUMIFS('Forecast Engine'!$AM$4:$AM$12,'Forecast Engine'!$A$4:$A$12,$C92,'Forecast Engine'!$B$4:$B$12,$D92) | L92: =SUM(I92:K92)
A93: 10101272 | B93: Rice Face Wash 50 ml | C93: Mamaearth | D93: Face | E93: Reliance Retail Limited | F93: North | G93: 0.2787 | H93: =IFERROR(G93/SUMIFS($G$4:$G$1504,$C$4:$C$1504,$C93,$D$4:$D$1504,$D93),0) | I93: =$H93*SUMIFS('Forecast Engine'!$AK$4:$AK$12,'Forecast Engine'!$A$4:$A$12,$C93,'Forecast Engine'!$B$4:$B$12,$D93) | J93: =$H93*SUMIFS('Forecast Engine'!$AL$4:$AL$12,'Forecast Engine'!$A$4:$A$12,$C93,'Forecast Engine'!$B$4:$B$12,$D93) | K93: =$H93*SUMIFS('Forecast Engine'!$AM$4:$AM$12,'Forecast Engine'!$A$4:$A$12,$C93,'Forecast Engine'!$B$4:$B$12,$D93) | L93: =SUM(I93:K93)
A94: 10101163 | B94: Rice Dewy Bright Face wash | C94: Mamaearth | D94: Face | E94: Balaji Associates Distri | F94: East | G94: 0.2772 | H94: =IFERROR(G94/SUMIFS($G$4:$G$1504,$C$4:$C$1504,$C94,$D$4:$D$1504,$D94),0) | I94: =$H94*SUMIFS('Forecast Engine'!$AK$4:$AK$12,'Forecast Engine'!$A$4:$A$12,$C94,'Forecast Engine'!$B$4:$B$12,$D94) | J94: =$H94*SUMIFS('Forecast Engine'!$AL$4:$AL$12,'Forecast Engine'!$A$4:$A$12,$C94,'Forecast Engine'!$B$4:$B$12,$D94) | K94: =$H94*SUMIFS('Forecast Engine'!$AM$4:$AM$12,'Forecast Engine'!$A$4:$A$12,$C94,'Forecast Engine'!$B$4:$B$12,$D94) | L94: =SUM(I94:K94)
A95: 10100695 | B95: ME Ubtan Natural Glow Face Wash With Turmeric & | C95: Mamaearth | D95: Face | E95: Vanaja Agencies | F95: South-2 | G95: 0.2765 | H95: =IFERROR(G95/SUMIFS($G$4:$G$1504,$C$4:$C$1504,$C95,$D$4:$D$1504,$D95),0) | I95: =$H95*SUMIFS('Forecast Engine'!$AK$4:$AK$12,'Forecast Engine'!$A$4:$A$12,$C95,'Forecast Engine'!$B$4:$B$12,$D95) | J95: =$H95*SUMIFS('Forecast Engine'!$AL$4:$AL$12,'Forecast Engine'!$A$4:$A$12,$C95,'Forecast Engine'!$B$4:$B$12,$D95) | K95: =$H95*SUMIFS('Forecast Engine'!$AM$4:$AM$12,'Forecast Engine'!$A$4:$A$12,$C95,'Forecast Engine'!$B$4:$B$12,$D95) | L95: =SUM(I95:K95)
A96: 10101166 | B96: Vitamin C Face Wash 150 ml | C96: Mamaearth | D96: Face | E96: Apollo Healthco | F96: South-2 | G96: 0.2765 | H96: =IFERROR(G96/SUMIFS($G$4:$G$1504,$C$4:$C$1504,$C96,$D$4:$D$1504,$D96),0) | I96: =$H96*SUMIFS('Forecast Engine'!$AK$4:$AK$12,'Forecast Engine'!$A$4:$A$12,$C96,'Forecast Engine'!$B$4:$B$12,$D96) | J96: =$H96*SUMIFS('Forecast Engine'!$AL$4:$AL$12,'Forecast Engine'!$A$4:$A$12,$C96,'Forecast Engine'!$B$4:$B$12,$D96) | K96: =$H96*SUMIFS('Forecast Engine'!$AM$4:$AM$12,'Forecast Engine'!$A$4:$A$12,$C96,'Forecast Engine'!$B$4:$B$12,$D96) | L96: =SUM(I96:K96)
A97: 10100695 | B97: ME Ubtan Natural Glow Face Wash With Turmeric & | C97: Mamaearth | D97: Face | E97: D-Mart | F97: South-2 | G97: 0.2763 | H97: =IFERROR(G97/SUMIFS($G$4:$G$1504,$C$4:$C$1504,$C97,$D$4:$D$1504,$D97),0) | I97: =$H97*SUMIFS('Forecast Engine'!$AK$4:$AK$12,'Forecast Engine'!$A$4:$A$12,$C97,'Forecast Engine'!$B$4:$B$12,$D97) | J97: =$H97*SUMIFS('Forecast Engine'!$AL$4:$AL$12,'Forecast Engine'!$A$4:$A$12,$C97,'Forecast Engine'!$B$4:$B$12,$D97) | K97: =$H97*SUMIFS('Forecast Engine'!$AM$4:$AM$12,'Forecast Engine'!$A$4:$A$12,$C97,'Forecast Engine'!$B$4:$B$12,$D97) | L97: =SUM(I97:K97)
A98: 10100618 | B98: Rice Face Wash 100 ml | C98: Mamaearth | D98: Face | E98: Wellness Forever | F98: West | G98: 0.2731 | H98: =IFERROR(G98/SUMIFS($G$4:$G$1504,$C$4:$C$1504,$C98,$D$4:$D$1504,$D98),0) | I98: =$H98*SUMIFS('Forecast Engine'!$AK$4:$AK$12,'Forecast Engine'!$A$4:$A$12,$C98,'Forecast Engine'!$B$4:$B$12,$D98) | J98: =$H98*SUMIFS('Forecast Engine'!$AL$4:$AL$12,'Forecast Engine'!$A$4:$A$12,$C98,'Forecast Engine'!$B$4:$B$12,$D98) | K98: =$H98*SUMIFS('Forecast Engine'!$AM$4:$AM$12,'Forecast Engine'!$A$4:$A$12,$C98,'Forecast Engine'!$B$4:$B$12,$D98) | L98: =SUM(I98:K98)
A99: 10100062 | B99: Mamaearth Ultra Light Indian Sunscreen with Carr | C99: Mamaearth | D99: Face | E99: Reliance Retail Limited | F99: East | G99: 0.271 | H99: =IFERROR(G99/SUMIFS($G$4:$G$1504,$C$4:$C$1504,$C99,$D$4:$D$1504,$D99),0) | I99: =$H99*SUMIFS('Forecast Engine'!$AK$4:$AK$12,'Forecast Engine'!$A$4:$A$12,$C99,'Forecast Engine'!$B$4:$B$12,$D99) | J99: =$H99*SUMIFS('Forecast Engine'!$AL$4:$AL$12,'Forecast Engine'!$A$4:$A$12,$C99,'Forecast Engine'!$B$4:$B$12,$D99) | K99: =$H99*SUMIFS('Forecast Engine'!$AM$4:$AM$12,'Forecast Engine'!$A$4:$A$12,$C99,'Forecast Engine'!$B$4:$B$12,$D99) | L99: =SUM(I99:K99)
A100: 10100912 | B100: Vitamin C Daily Glow Sunscreen 50 g | C100: Mamaearth | D100: Face | E100: Nykaa E-Retail Limited | F100: East | G100: 0.2663 | H100: =IFERROR(G100/SUMIFS($G$4:$G$1504,$C$4:$C$1504,$C100,$D$4:$D$1504,$D100),0) | I100: =$H100*SUMIFS('Forecast Engine'!$AK$4:$AK$12,'Forecast Engine'!$A$4:$A$12,$C100,'Forecast Engine'!$B$4:$B$12,$D100) | J100: =$H100*SUMIFS('Forecast Engine'!$AL$4:$AL$12,'Forecast Engine'!$A$4:$A$12,$C100,'Forecast Engine'!$B$4:$B$12,$D100) | K100: =$H100*SUMIFS('Forecast Engine'!$AM$4:$AM$12,'Forecast Engine'!$A$4:$A$12,$C100,'Forecast Engine'!$B$4:$B$12,$D100) | L100: =SUM(I100:K100)
...

Sheet Scenario Summary
A1: SCENARIO SUMMARY · Base / Optimistic / Conservative side-by-side (₹ Cr)
A2: Company rolling 3-month forecast under all three scenarios, vs target. Switch the driver on Control Panel → these recompute instantly.
A3: Scenario | B3: Month M | C3: Month M+1 | D3: Month M+2 | E3: 3-Month Total
A4: Live month → | B4: ='Control Panel'!$B$4 | C4: ='Control Panel'!$B$6 | D4: ='Control Panel'!$B$7
A5: Base Case | B5: ='Forecast Engine'!$AK$13 | C5: ='Forecast Engine'!$AL$13 | D5: ='Forecast Engine'!$AM$13 | E5: =SUM(B5:D5)
A6: Optimistic Case | B6: ='Forecast Engine'!$AN$13 | C6: ='Forecast Engine'!$AO$13 | D6: ='Forecast Engine'!$AP$13 | E6: =SUM(B6:D6)
A7: Conservative Case | B7: ='Forecast Engine'!$AQ$13 | C7: ='Forecast Engine'!$AR$13 | D7: ='Forecast Engine'!$AS$13 | E7: =SUM(B7:D7)
A8: Target (from plan) | B8: =IFERROR(SUMIFS('Monthly Target Upload'!$D$4:$D$15,'Monthly Target Upload'!$A$4:$A$15,'Control Panel'!$B$4),0) | C8: =IFERROR(SUMIFS('Monthly Target Upload'!$D$4:$D$15,'Monthly Target Upload'!$A$4:$A$15,'Control Panel'!$B$6),0) | D8: =IFERROR(SUMIFS('Monthly Target Upload'!$D$4:$D$15,'Monthly Target Upload'!$A$4:$A$15,'Control Panel'!$B$7),0) | E8: =SUM(B8:D8)
A9: Base vs Target (gap) | B9: =B5-B8 | C9: =C5-C8 | D9: =D5-D8 | E9: =SUM(B9:D9)
A11: Brand-level Base-case forecast (3-month total, ₹ Cr)
A12: Brand | B12: M | C12: M+1 | D12: M+2 | E12: 3M Total | F12: % of Company
A13: Mamaearth | B13: =SUMIFS('Forecast Engine'!$AK$4:$AK$12,'Forecast Engine'!$A$4:$A$12,$A13) | C13: =SUMIFS('Forecast Engine'!$AL$4:$AL$12,'Forecast Engine'!$A$4:$A$12,$A13) | D13: =SUMIFS('Forecast Engine'!$AM$4:$AM$12,'Forecast Engine'!$A$4:$A$12,$A13) | E13: =SUM(B13:D13) | F13: =IFERROR(E13/SUM($E$13:$E$16),0)
A14: The Derma Co. | B14: =SUMIFS('Forecast Engine'!$AK$4:$AK$12,'Forecast Engine'!$A$4:$A$12,$A14) | C14: =SUMIFS('Forecast Engine'!$AL$4:$AL$12,'Forecast Engine'!$A$4:$A$12,$A14) | D14: =SUMIFS('Forecast Engine'!$AM$4:$AM$12,'Forecast Engine'!$A$4:$A$12,$A14) | E14: =SUM(B14:D14) | F14: =IFERROR(E14/SUM($E$13:$E$16),0)
A15: Aqualogica | B15: =SUMIFS('Forecast Engine'!$AK$4:$AK$12,'Forecast Engine'!$A$4:$A$12,$A15) | C15: =SUMIFS('Forecast Engine'!$AL$4:$AL$12,'Forecast Engine'!$A$4:$A$12,$A15) | D15: =SUMIFS('Forecast Engine'!$AM$4:$AM$12,'Forecast Engine'!$A$4:$A$12,$A15) | E15: =SUM(B15:D15) | F15: =IFERROR(E15/SUM($E$13:$E$16),0)
A16: BBLUNT | B16: =SUMIFS('Forecast Engine'!$AK$4:$AK$12,'Forecast Engine'!$A$4:$A$12,$A16) | C16: =SUMIFS('Forecast Engine'!$AL$4:$AL$12,'Forecast Engine'!$A$4:$A$12,$A16) | D16: =SUMIFS('Forecast Engine'!$AM$4:$AM$12,'Forecast Engine'!$A$4:$A$12,$A16) | E16: =SUM(B16:D16) | F16: =IFERROR(E16/SUM($E$13:$E$16),0)

Sheet AI Business Insights
A1: AI BUSINESS INSIGHTS · auto-generated executive commentary
A2: Sentences below are live formulas over the forecast, target and accuracy engines — they update as inputs change. Green = opportunity, red = risk.
A3: Portfolio headline
A4: ="Selected scenario ("&'Control Panel'!$B$5&") projects ₹"&TEXT(('Forecast Engine'!$AT$13+'Forecast Engine'!$AU$13+'Forecast Engine'!$AV$13),"0.0")&" Cr over "&'Control Panel'!$B$4&"–"&'Control Panel'!$B$7&" vs ₹"&TEXT((SUMIFS('Monthly Target Upload'!$D$4:$D$15,'Monthly Target Upload'!$A$4:$A$15,'Control Panel'!$B$4)+SUMIFS('Monthly Target Upload'!$D$4:$D$15,'Monthly Target Upload'!$A$4:$A$15,'Control Panel'!$B$6)+SUMIFS('Monthly Target Upload'!$D$4:$D$15,'Monthly Target Upload'!$A$4:$A$15,'Control Panel'!$B$7)),"0.0")&" Cr target — a "&IF(('Forecast Engine'!$AT$13+'Forecast Engine'!$AU$13+'Forecast Engine'!$AV$13)>=(SUMIFS('Monthly Target Upload'!$D$4:$D$15,'Monthly Target Upload'!$A$4:$A$15,'Control Panel'!$B$4)+SUMIFS('Monthly Target Upload'!$D$4:$D$15,'Monthly Target Upload'!$A$4:$A$15,'Control Panel'!$B$6)+SUMIFS('Monthly Target Upload'!$D$4:$D$15,'Monthly Target Upload'!$A$4:$A$15,'Control Panel'!$B$7)),"surplus of ₹","gap of ₹")&TEXT(ABS(('Forecast Engine'!$AT$13+'Forecast Engine'!$AU$13+'Forecast Engine'!$AV$13)-(SUMIFS('Monthly Target Upload'!$D$4:$D$15,'Monthly Target Upload'!$A$4:$A$15,'Control Panel'!$B$4)+SUMIFS('Monthly Target Upload'!$D$4:$D$15,'Monthly Target Upload'!$A$4:$A$15,'Control Panel'!$B$6)+SUMIFS('Monthly Target Upload'!$D$4:$D$15,'Monthly Target Upload'!$A$4:$A$15,'Control Panel'!$B$7))),"0.0")&" Cr ("&TEXT(IFERROR(('Forecast Engine'!$AT$13+'Forecast Engine'!$AU$13+'Forecast Engine'!$AV$13)/(SUMIFS('Monthly Target Upload'!$D$4:$D$15,'Monthly Target Upload'!$A$4:$A$15,'Control Panel'!$B$4)+SUMIFS('Monthly Target Upload'!$D$4:$D$15,'Monthly Target Upload'!$A$4:$A$15,'Control Panel'!$B$6)+SUMIFS('Monthly Target Upload'!$D$4:$D$15,'Monthly Target Upload'!$A$4:$A$15,'Control Panel'!$B$7))-1,0),"+0.0%;-0.0%")&")."
A6: Brand signals (momentum, inventory, target risk)
A7: Brand | B7: Base 3M (₹ Cr) | C7: Momentum | D7: Commentary
A8: Mamaearth | B8: =SUMIFS('Forecast Engine'!$AK$4:$AK$12,'Forecast Engine'!$A$4:$A$12,$A8)+SUMIFS('Forecast Engine'!$AL$4:$AL$12,'Forecast Engine'!$A$4:$A$12,$A8)+SUMIFS('Forecast Engine'!$AM$4:$AM$12,'Forecast Engine'!$A$4:$A$12,$A8) | C8: =IFERROR(SUMIFS('Forecast Engine'!$AH$4:$AH$12,'Forecast Engine'!$A$4:$A$12,$A8)/SUMIFS('Forecast Engine'!$AB$4:$AB$12,'Forecast Engine'!$A$4:$A$12,$A8)-1,0) | D8: =IF(C8>=0.03,"Positive momentum — protect availability & raise safety stock.",IF(C8<=-0.03,"Losing momentum — review promo depth, assortment & competitive activity.","Stable trajectory — hold plan, monitor sell-through."))
A9: The Derma Co. | B9: =SUMIFS('Forecast Engine'!$AK$4:$AK$12,'Forecast Engine'!$A$4:$A$12,$A9)+SUMIFS('Forecast Engine'!$AL$4:$AL$12,'Forecast Engine'!$A$4:$A$12,$A9)+SUMIFS('Forecast Engine'!$AM$4:$AM$12,'Forecast Engine'!$A$4:$A$12,$A9) | C9: =IFERROR(SUMIFS('Forecast Engine'!$AH$4:$AH$12,'Forecast Engine'!$A$4:$A$12,$A9)/SUMIFS('Forecast Engine'!$AB$4:$AB$12,'Forecast Engine'!$A$4:$A$12,$A9)-1,0) | D9: =IF(C9>=0.03,"Positive momentum — protect availability & raise safety stock.",IF(C9<=-0.03,"Losing momentum — review promo depth, assortment & competitive activity.","Stable trajectory — hold plan, monitor sell-through."))
A10: Aqualogica | B10: =SUMIFS('Forecast Engine'!$AK$4:$AK$12,'Forecast Engine'!$A$4:$A$12,$A10)+SUMIFS('Forecast Engine'!$AL$4:$AL$12,'Forecast Engine'!$A$4:$A$12,$A10)+SUMIFS('Forecast Engine'!$AM$4:$AM$12,'Forecast Engine'!$A$4:$A$12,$A10) | C10: =IFERROR(SUMIFS('Forecast Engine'!$AH$4:$AH$12,'Forecast Engine'!$A$4:$A$12,$A10)/SUMIFS('Forecast Engine'!$AB$4:$AB$12,'Forecast Engine'!$A$4:$A$12,$A10)-1,0) | D10: =IF(C10>=0.03,"Positive momentum — protect availability & raise safety stock.",IF(C10<=-0.03,"Losing momentum — review promo depth, assortment & competitive activity.","Stable trajectory — hold plan, monitor sell-through."))
A11: BBLUNT | B11: =SUMIFS('Forecast Engine'!$AK$4:$AK$12,'Forecast Engine'!$A$4:$A$12,$A11)+SUMIFS('Forecast Engine'!$AL$4:$AL$12,'Forecast Engine'!$A$4:$A$12,$A11)+SUMIFS('Forecast Engine'!$AM$4:$AM$12,'Forecast Engine'!$A$4:$A$12,$A11) | C11: =IFERROR(SUMIFS('Forecast Engine'!$AH$4:$AH$12,'Forecast Engine'!$A$4:$A$12,$A11)/SUMIFS('Forecast Engine'!$AB$4:$AB$12,'Forecast Engine'!$A$4:$A$12,$A11)-1,0) | D11: =IF(C11>=0.03,"Positive momentum — protect availability & raise safety stock.",IF(C11<=-0.03,"Losing momentum — review promo depth, assortment & competitive activity.","Stable trajectory — hold plan, monitor sell-through."))
A13: Warehouse & supply flags
A14: ="Warehouses see the Warehouse Optimization tab for overload alerts. Peak utilisation is driven by the Base forecast against capacity set on the Control Panel."
A16: Recommended actions
A17: =IF(('Forecast Engine'!$AT$13+'Forecast Engine'!$AU$13+'Forecast Engine'!$AV$13)<(SUMIFS('Monthly Target Upload'!$D$4:$D$15,'Monthly Target Upload'!$A$4:$A$15,'Control Panel'!$B$4)+SUMIFS('Monthly Target Upload'!$D$4:$D$15,'Monthly Target Upload'!$A$4:$A$15,'Control Panel'!$B$6)+SUMIFS('Monthly Target Upload'!$D$4:$D$15,'Monthly Target Upload'!$A$4:$A$15,'Control Panel'!$B$7)),"1 · Close the ₹"&TEXT((SUMIFS('Monthly Target Upload'!$D$4:$D$15,'Monthly Target Upload'!$A$4:$A$15,'Control Panel'!$B$4)+SUMIFS('Monthly Target Upload'!$D$4:$D$15,'Monthly Target Upload'!$A$4:$A$15,'Control Panel'!$B$6)+SUMIFS('Monthly Target Upload'!$D$4:$D$15,'Monthly Target Upload'!$A$4:$A$15,'Control Panel'!$B$7))-('Forecast Engine'!$AT$13+'Forecast Engine'!$AU$13+'Forecast Engine'!$AV$13),"0.0")&" Cr gap: raise trade support on top-mix brands and pull forward NPI loading.","1 · Forecast ahead of target — protect service levels and lock incremental supply.")
A18: ="2 · Prioritise safety stock for positive-momentum brands (see brand table above)."
A19: ="3 · Reallocate dispatch away from any warehouse above 100% utilisation (Warehouse Optimization tab)."
A20: ="4 · Distributors tagged High Service Risk / High Inventory in Distributor Intelligence need corrective ordering plans."
A21: =IF('Forecast Accuracy'!$B$18>0.2,"5 · Model WMAPE above 20% — refine method weights / add business overrides for volatile SKUs.","5 · Forecast accuracy within tolerance — maintain current method weights.")

Sheet Demand Planner Workbench
A1: DEMAND PLANNER WORKBENCH · manual overrides with audit trail
A2: Planners adjust the forecast at any level and record WHY. 'System Forecast' looks up the engine (Brand×Category); 'Final' uses the override when present; Variance + audit columns preserve the trail. This mirrors SAP IBP / Kinaxis / Blue Yonder override handling.
A3: Date | B3: Planner | C3: Level | D3: Key (Brand or Brand|Category) | E3: Target Month | F3: System Forecast (₹ Cr) | G3: Override (₹ Cr) | H3: Final (₹ Cr) | I3: Variance | J3: Reason
A4: 2026-06-01 | B4: S. Aswal | C4: Brand|Category | D4: Mamaearth|Sun Care | E4: Jun'26 | F4: =IFERROR(IF($E4='Control Panel'!$B$4,IF(ISNUMBER(SEARCH("|",$D4)),SUMIFS('Forecast Engine'!$AK$4:$AK$12,'Forecast Engine'!$A$4:$A$12,LEFT($D4,IFERROR(SEARCH("|",$D4)-1,LEN($D4))),'Forecast Engine'!$B$4:$B$12,MID($D4,IFERROR(SEARCH("|",$D4)+1,LEN($D4)+1),50)),SUMIFS('Forecast Engine'!$AK$4:$AK$12,'Forecast Engine'!$A$4:$A$12,LEFT($D4,IFERROR(SEARCH("|",$D4)-1,LEN($D4))))),IF($E4='Control Panel'!$B$6,IF(ISNUMBER(SEARCH("|",$D4)),SUMIFS('Forecast Engine'!$AL$4:$AL$12,'Forecast Engine'!$A$4:$A$12,LEFT($D4,IFERROR(SEARCH("|",$D4)-1,LEN($D4))),'Forecast Engine'!$B$4:$B$12,MID($D4,IFERROR(SEARCH("|",$D4)+1,LEN($D4)+1),50)),SUMIFS('Forecast Engine'!$AL$4:$AL$12,'Forecast Engine'!$A$4:$A$12,LEFT($D4,IFERROR(SEARCH("|",$D4)-1,LEN($D4))))),IF($E4='Control Panel'!$B$7,IF(ISNUMBER(SEARCH("|",$D4)),SUMIFS('Forecast Engine'!$AM$4:$AM$12,'Forecast Engine'!$A$4:$A$12,LEFT($D4,IFERROR(SEARCH("|",$D4)-1,LEN($D4))),'Forecast Engine'!$B$4:$B$12,MID($D4,IFERROR(SEARCH("|",$D4)+1,LEN($D4)+1),50)),SUMIFS('Forecast Engine'!$AM$4:$AM$12,'Forecast Engine'!$A$4:$A$12,LEFT($D4,IFERROR(SEARCH("|",$D4)-1,LEN($D4))))),0))),0) | G4: 2.5 | H4: =IF(G4<>"",G4,F4) | I4: =IFERROR(H4/F4-1,0) | J4: Promotion
A5: 2026-06-01 | B5: S. Aswal | C5: Brand | D5: The Derma Co. | E5: Jul'26 | F5: =IFERROR(IF($E5='Control Panel'!$B$4,IF(ISNUMBER(SEARCH("|",$D5)),SUMIFS('Forecast Engine'!$AK$4:$AK$12,'Forecast Engine'!$A$4:$A$12,LEFT($D5,IFERROR(SEARCH("|",$D5)-1,LEN($D5))),'Forecast Engine'!$B$4:$B$12,MID($D5,IFERROR(SEARCH("|",$D5)+1,LEN($D5)+1),50)),SUMIFS('Forecast Engine'!$AK$4:$AK$12,'Forecast Engine'!$A$4:$A$12,LEFT($D5,IFERROR(SEARCH("|",$D5)-1,LEN($D5))))),IF($E5='Control Panel'!$B$6,IF(ISNUMBER(SEARCH("|",$D5)),SUMIFS('Forecast Engine'!$AL$4:$AL$12,'Forecast Engine'!$A$4:$A$12,LEFT($D5,IFERROR(SEARCH("|",$D5)-1,LEN($D5))),'Forecast Engine'!$B$4:$B$12,MID($D5,IFERROR(SEARCH("|",$D5)+1,LEN($D5)+1),50)),SUMIFS('Forecast Engine'!$AL$4:$AL$12,'Forecast Engine'!$A$4:$A$12,LEFT($D5,IFERROR(SEARCH("|",$D5)-1,LEN($D5))))),IF($E5='Control Panel'!$B$7,IF(ISNUMBER(SEARCH("|",$D5)),SUMIFS('Forecast Engine'!$AM$4:$AM$12,'Forecast Engine'!$A$4:$A$12,LEFT($D5,IFERROR(SEARCH("|",$D5)-1,LEN($D5))),'Forecast Engine'!$B$4:$B$12,MID($D5,IFERROR(SEARCH("|",$D5)+1,LEN($D5)+1),50)),SUMIFS('Forecast Engine'!$AM$4:$AM$12,'Forecast Engine'!$A$4:$A$12,LEFT($D5,IFERROR(SEARCH("|",$D5)-1,LEN($D5))))),0))),0) | H5: =IF(G5<>"",G5,F5) | I5: =IFERROR(H5/F5-1,0) | J5: Listing Expansion
F6: =IFERROR(IF($E6='Control Panel'!$B$4,IF(ISNUMBER(SEARCH("|",$D6)),SUMIFS('Forecast Engine'!$AK$4:$AK$12,'Forecast Engine'!$A$4:$A$12,LEFT($D6,IFERROR(SEARCH("|",$D6)-1,LEN($D6))),'Forecast Engine'!$B$4:$B$12,MID($D6,IFERROR(SEARCH("|",$D6)+1,LEN($D6)+1),50)),SUMIFS('Forecast Engine'!$AK$4:$AK$12,'Forecast Engine'!$A$4:$A$12,LEFT($D6,IFERROR(SEARCH("|",$D6)-1,LEN($D6))))),IF($E6='Control Panel'!$B$6,IF(ISNUMBER(SEARCH("|",$D6)),SUMIFS('Forecast Engine'!$AL$4:$AL$12,'Forecast Engine'!$A$4:$A$12,LEFT($D6,IFERROR(SEARCH("|",$D6)-1,LEN($D6))),'Forecast Engine'!$B$4:$B$12,MID($D6,IFERROR(SEARCH("|",$D6)+1,LEN($D6)+1),50)),SUMIFS('Forecast Engine'!$AL$4:$AL$12,'Forecast Engine'!$A$4:$A$12,LEFT($D6,IFERROR(SEARCH("|",$D6)-1,LEN($D6))))),IF($E6='Control Panel'!$B$7,IF(ISNUMBER(SEARCH("|",$D6)),SUMIFS('Forecast Engine'!$AM$4:$AM$12,'Forecast Engine'!$A$4:$A$12,LEFT($D6,IFERROR(SEARCH("|",$D6)-1,LEN($D6))),'Forecast Engine'!$B$4:$B$12,MID($D6,IFERROR(SEARCH("|",$D6)+1,LEN($D6)+1),50)),SUMIFS('Forecast Engine'!$AM$4:$AM$12,'Forecast Engine'!$A$4:$A$12,LEFT($D6,IFERROR(SEARCH("|",$D6)-1,LEN($D6))))),0))),0) | H6: =IF(G6<>"",G6,F6) | I6: =IFERROR(H6/F6-1,0)
F7: =IFERROR(IF($E7='Control Panel'!$B$4,IF(ISNUMBER(SEARCH("|",$D7)),SUMIFS('Forecast Engine'!$AK$4:$AK$12,'Forecast Engine'!$A$4:$A$12,LEFT($D7,IFERROR(SEARCH("|",$D7)-1,LEN($D7))),'Forecast Engine'!$B$4:$B$12,MID($D7,IFERROR(SEARCH("|",$D7)+1,LEN($D7)+1),50)),SUMIFS('Forecast Engine'!$AK$4:$AK$12,'Forecast Engine'!$A$4:$A$12,LEFT($D7,IFERROR(SEARCH("|",$D7)-1,LEN($D7))))),IF($E7='Control Panel'!$B$6,IF(ISNUMBER(SEARCH("|",$D7)),SUMIFS('Forecast Engine'!$AL$4:$AL$12,'Forecast Engine'!$A$4:$A$12,LEFT($D7,IFERROR(SEARCH("|",$D7)-1,LEN($D7))),'Forecast Engine'!$B$4:$B$12,MID($D7,IFERROR(SEARCH("|",$D7)+1,LEN($D7)+1),50)),SUMIFS('Forecast Engine'!$AL$4:$AL$12,'Forecast Engine'!$A$4:$A$12,LEFT($D7,IFERROR(SEARCH("|",$D7)-1,LEN($D7))))),IF($E7='Control Panel'!$B$7,IF(ISNUMBER(SEARCH("|",$D7)),SUMIFS('Forecast Engine'!$AM$4:$AM$12,'Forecast Engine'!$A$4:$A$12,LEFT($D7,IFERROR(SEARCH("|",$D7)-1,LEN($D7))),'Forecast Engine'!$B$4:$B$12,MID($D7,IFERROR(SEARCH("|",$D7)+1,LEN($D7)+1),50)),SUMIFS('Forecast Engine'!$AM$4:$AM$12,'Forecast Engine'!$A$4:$A$12,LEFT($D7,IFERROR(SEARCH("|",$D7)-1,LEN($D7))))),0))),0) | H7: =IF(G7<>"",G7,F7) | I7: =IFERROR(H7/F7-1,0)
F8: =IFERROR(IF($E8='Control Panel'!$B$4,IF(ISNUMBER(SEARCH("|",$D8)),SUMIFS('Forecast Engine'!$AK$4:$AK$12,'Forecast Engine'!$A$4:$A$12,LEFT($D8,IFERROR(SEARCH("|",$D8)-1,LEN($D8))),'Forecast Engine'!$B$4:$B$12,MID($D8,IFERROR(SEARCH("|",$D8)+1,LEN($D8)+1),50)),SUMIFS('Forecast Engine'!$AK$4:$AK$12,'Forecast Engine'!$A$4:$A$12,LEFT($D8,IFERROR(SEARCH("|",$D8)-1,LEN($D8))))),IF($E8='Control Panel'!$B$6,IF(ISNUMBER(SEARCH("|",$D8)),SUMIFS('Forecast Engine'!$AL$4:$AL$12,'Forecast Engine'!$A$4:$A$12,LEFT($D8,IFERROR(SEARCH("|",$D8)-1,LEN($D8))),'Forecast Engine'!$B$4:$B$12,MID($D8,IFERROR(SEARCH("|",$D8)+1,LEN($D8)+1),50)),SUMIFS('Forecast Engine'!$AL$4:$AL$12,'Forecast Engine'!$A$4:$A$12,LEFT($D8,IFERROR(SEARCH("|",$D8)-1,LEN($D8))))),IF($E8='Control Panel'!$B$7,IF(ISNUMBER(SEARCH("|",$D8)),SUMIFS('Forecast Engine'!$AM$4:$AM$12,'Forecast Engine'!$A$4:$A$12,LEFT($D8,IFERROR(SEARCH("|",$D8)-1,LEN($D8))),'Forecast Engine'!$B$4:$B$12,MID($D8,IFERROR(SEARCH("|",$D8)+1,LEN($D8)+1),50)),SUMIFS('Forecast Engine'!$AM$4:$AM$12,'Forecast Engine'!$A$4:$A$12,LEFT($D8,IFERROR(SEARCH("|",$D8)-1,LEN($D8))))),0))),0) | H8: =IF(G8<>"",G8,F8) | I8: =IFERROR(H8/F8-1,0)
F9: =IFERROR(IF($E9='Control Panel'!$B$4,IF(ISNUMBER(SEARCH("|",$D9)),SUMIFS('Forecast Engine'!$AK$4:$AK$12,'Forecast Engine'!$A$4:$A$12,LEFT($D9,IFERROR(SEARCH("|",$D9)-1,LEN($D9))),'Forecast Engine'!$B$4:$B$12,MID($D9,IFERROR(SEARCH("|",$D9)+1,LEN($D9)+1),50)),SUMIFS('Forecast Engine'!$AK$4:$AK$12,'Forecast Engine'!$A$4:$A$12,LEFT($D9,IFERROR(SEARCH("|",$D9)-1,LEN($D9))))),IF($E9='Control Panel'!$B$6,IF(ISNUMBER(SEARCH("|",$D9)),SUMIFS('Forecast Engine'!$AL$4:$AL$12,'Forecast Engine'!$A$4:$A$12,LEFT($D9,IFERROR(SEARCH("|",$D9)-1,LEN($D9))),'Forecast Engine'!$B$4:$B$12,MID($D9,IFERROR(SEARCH("|",$D9)+1,LEN($D9)+1),50)),SUMIFS('Forecast Engine'!$AL$4:$AL$12,'Forecast Engine'!$A$4:$A$12,LEFT($D9,IFERROR(SEARCH("|",$D9)-1,LEN($D9))))),IF($E9='Control Panel'!$B$7,IF(ISNUMBER(SEARCH("|",$D9)),SUMIFS('Forecast Engine'!$AM$4:$AM$12,'Forecast Engine'!$A$4:$A$12,LEFT($D9,IFERROR(SEARCH("|",$D9)-1,LEN($D9))),'Forecast Engine'!$B$4:$B$12,MID($D9,IFERROR(SEARCH("|",$D9)+1,LEN($D9)+1),50)),SUMIFS('Forecast Engine'!$AM$4:$AM$12,'Forecast Engine'!$A$4:$A$12,LEFT($D9,IFERROR(SEARCH("|",$D9)-1,LEN($D9))))),0))),0) | H9: =IF(G9<>"",G9,F9) | I9: =IFERROR(H9/F9-1,0)
F10: =IFERROR(IF($E10='Control Panel'!$B$4,IF(ISNUMBER(SEARCH("|",$D10)),SUMIFS('Forecast Engine'!$AK$4:$AK$12,'Forecast Engine'!$A$4:$A$12,LEFT($D10,IFERROR(SEARCH("|",$D10)-1,LEN($D10))),'Forecast Engine'!$B$4:$B$12,MID($D10,IFERROR(SEARCH("|",$D10)+1,LEN($D10)+1),50)),SUMIFS('Forecast Engine'!$AK$4:$AK$12,'Forecast Engine'!$A$4:$A$12,LEFT($D10,IFERROR(SEARCH("|",$D10)-1,LEN($D10))))),IF($E10='Control Panel'!$B$6,IF(ISNUMBER(SEARCH("|",$D10)),SUMIFS('Forecast Engine'!$AL$4:$AL$12,'Forecast Engine'!$A$4:$A$12,LEFT($D10,IFERROR(SEARCH("|",$D10)-1,LEN($D10))),'Forecast Engine'!$B$4:$B$12,MID($D10,IFERROR(SEARCH("|",$D10)+1,LEN($D10)+1),50)),SUMIFS('Forecast Engine'!$AL$4:$AL$12,'Forecast Engine'!$A$4:$A$12,LEFT($D10,IFERROR(SEARCH("|",$D10)-1,LEN($D10))))),IF($E10='Control Panel'!$B$7,IF(ISNUMBER(SEARCH("|",$D10)),SUMIFS('Forecast Engine'!$AM$4:$AM$12,'Forecast Engine'!$A$4:$A$12,LEFT($D10,IFERROR(SEARCH("|",$D10)-1,LEN($D10))),'Forecast Engine'!$B$4:$B$12,MID($D10,IFERROR(SEARCH("|",$D10)+1,LEN($D10)+1),50)),SUMIFS('Forecast Engine'!$AM$4:$AM$12,'Forecast Engine'!$A$4:$A$12,LEFT($D10,IFERROR(SEARCH("|",$D10)-1,LEN($D10))))),0))),0) | H10: =IF(G10<>"",G10,F10) | I10: =IFERROR(H10/F10-1,0)
F11: =IFERROR(IF($E11='Control Panel'!$B$4,IF(ISNUMBER(SEARCH("|",$D11)),SUMIFS('Forecast Engine'!$AK$4:$AK$12,'Forecast Engine'!$A$4:$A$12,LEFT($D11,IFERROR(SEARCH("|",$D11)-1,LEN($D11))),'Forecast Engine'!$B$4:$B$12,MID($D11,IFERROR(SEARCH("|",$D11)+1,LEN($D11)+1),50)),SUMIFS('Forecast Engine'!$AK$4:$AK$12,'Forecast Engine'!$A$4:$A$12,LEFT($D11,IFERROR(SEARCH("|",$D11)-1,LEN($D11))))),IF($E11='Control Panel'!$B$6,IF(ISNUMBER(SEARCH("|",$D11)),SUMIFS('Forecast Engine'!$AL$4:$AL$12,'Forecast Engine'!$A$4:$A$12,LEFT($D11,IFERROR(SEARCH("|",$D11)-1,LEN($D11))),'Forecast Engine'!$B$4:$B$12,MID($D11,IFERROR(SEARCH("|",$D11)+1,LEN($D11)+1),50)),SUMIFS('Forecast Engine'!$AL$4:$AL$12,'Forecast Engine'!$A$4:$A$12,LEFT($D11,IFERROR(SEARCH("|",$D11)-1,LEN($D11))))),IF($E11='Control Panel'!$B$7,IF(ISNUMBER(SEARCH("|",$D11)),SUMIFS('Forecast Engine'!$AM$4:$AM$12,'Forecast Engine'!$A$4:$A$12,LEFT($D11,IFERROR(SEARCH("|",$D11)-1,LEN($D11))),'Forecast Engine'!$B$4:$B$12,MID($D11,IFERROR(SEARCH("|",$D11)+1,LEN($D11)+1),50)),SUMIFS('Forecast Engine'!$AM$4:$AM$12,'Forecast Engine'!$A$4:$A$12,LEFT($D11,IFERROR(SEARCH("|",$D11)-1,LEN($D11))))),0))),0) | H11: =IF(G11<>"",G11,F11) | I11: =IFERROR(H11/F11-1,0)
F12: =IFERROR(IF($E12='Control Panel'!$B$4,IF(ISNUMBER(SEARCH("|",$D12)),SUMIFS('Forecast Engine'!$AK$4:$AK$12,'Forecast Engine'!$A$4:$A$12,LEFT($D12,IFERROR(SEARCH("|",$D12)-1,LEN($D12))),'Forecast Engine'!$B$4:$B$12,MID($D12,IFERROR(SEARCH("|",$D12)+1,LEN($D12)+1),50)),SUMIFS('Forecast Engine'!$AK$4:$AK$12,'Forecast Engine'!$A$4:$A$12,LEFT($D12,IFERROR(SEARCH("|",$D12)-1,LEN($D12))))),IF($E12='Control Panel'!$B$6,IF(ISNUMBER(SEARCH("|",$D12)),SUMIFS('Forecast Engine'!$AL$4:$AL$12,'Forecast Engine'!$A$4:$A$12,LEFT($D12,IFERROR(SEARCH("|",$D12)-1,LEN($D12))),'Forecast Engine'!$B$4:$B$12,MID($D12,IFERROR(SEARCH("|",$D12)+1,LEN($D12)+1),50)),SUMIFS('Forecast Engine'!$AL$4:$AL$12,'Forecast Engine'!$A$4:$A$12,LEFT($D12,IFERROR(SEARCH("|",$D12)-1,LEN($D12))))),IF($E12='Control Panel'!$B$7,IF(ISNUMBER(SEARCH("|",$D12)),SUMIFS('Forecast Engine'!$AM$4:$AM$12,'Forecast Engine'!$A$4:$A$12,LEFT($D12,IFERROR(SEARCH("|",$D12)-1,LEN($D12))),'Forecast Engine'!$B$4:$B$12,MID($D12,IFERROR(SEARCH("|",$D12)+1,LEN($D12)+1),50)),SUMIFS('Forecast Engine'!$AM$4:$AM$12,'Forecast Engine'!$A$4:$A$12,LEFT($D12,IFERROR(SEARCH("|",$D12)-1,LEN($D12))))),0))),0) | H12: =IF(G12<>"",G12,F12) | I12: =IFERROR(H12/F12-1,0)
F13: =IFERROR(IF($E13='Control Panel'!$B$4,IF(ISNUMBER(SEARCH("|",$D13)),SUMIFS('Forecast Engine'!$AK$4:$AK$12,'Forecast Engine'!$A$4:$A$12,LEFT($D13,IFERROR(SEARCH("|",$D13)-1,LEN($D13))),'Forecast Engine'!$B$4:$B$12,MID($D13,IFERROR(SEARCH("|",$D13)+1,LEN($D13)+1),50)),SUMIFS('Forecast Engine'!$AK$4:$AK$12,'Forecast Engine'!$A$4:$A$12,LEFT($D13,IFERROR(SEARCH("|",$D13)-1,LEN($D13))))),IF($E13='Control Panel'!$B$6,IF(ISNUMBER(SEARCH("|",$D13)),SUMIFS('Forecast Engine'!$AL$4:$AL$12,'Forecast Engine'!$A$4:$A$12,LEFT($D13,IFERROR(SEARCH("|",$D13)-1,LEN($D13))),'Forecast Engine'!$B$4:$B$12,MID($D13,IFERROR(SEARCH("|",$D13)+1,LEN($D13)+1),50)),SUMIFS('Forecast Engine'!$AL$4:$AL$12,'Forecast Engine'!$A$4:$A$12,LEFT($D13,IFERROR(SEARCH("|",$D13)-1,LEN($D13))))),IF($E13='Control Panel'!$B$7,IF(ISNUMBER(SEARCH("|",$D13)),SUMIFS('Forecast Engine'!$AM$4:$AM$12,'Forecast Engine'!$A$4:$A$12,LEFT($D13,IFERROR(SEARCH("|",$D13)-1,LEN($D13))),'Forecast Engine'!$B$4:$B$12,MID($D13,IFERROR(SEARCH("|",$D13)+1,LEN($D13)+1),50)),SUMIFS('Forecast Engine'!$AM$4:$AM$12,'Forecast Engine'!$A$4:$A$12,LEFT($D13,IFERROR(SEARCH("|",$D13)-1,LEN($D13))))),0))),0) | H13: =IF(G13<>"",G13,F13) | I13: =IFERROR(H13/F13-1,0)
F14: =IFERROR(IF($E14='Control Panel'!$B$4,IF(ISNUMBER(SEARCH("|",$D14)),SUMIFS('Forecast Engine'!$AK$4:$AK$12,'Forecast Engine'!$A$4:$A$12,LEFT($D14,IFERROR(SEARCH("|",$D14)-1,LEN($D14))),'Forecast Engine'!$B$4:$B$12,MID($D14,IFERROR(SEARCH("|",$D14)+1,LEN($D14)+1),50)),SUMIFS('Forecast Engine'!$AK$4:$AK$12,'Forecast Engine'!$A$4:$A$12,LEFT($D14,IFERROR(SEARCH("|",$D14)-1,LEN($D14))))),IF($E14='Control Panel'!$B$6,IF(ISNUMBER(SEARCH("|",$D14)),SUMIFS('Forecast Engine'!$AL$4:$AL$12,'Forecast Engine'!$A$4:$A$12,LEFT($D14,IFERROR(SEARCH("|",$D14)-1,LEN($D14))),'Forecast Engine'!$B$4:$B$12,MID($D14,IFERROR(SEARCH("|",$D14)+1,LEN($D14)+1),50)),SUMIFS('Forecast Engine'!$AL$4:$AL$12,'Forecast Engine'!$A$4:$A$12,LEFT($D14,IFERROR(SEARCH("|",$D14)-1,LEN($D14))))),IF($E14='Control Panel'!$B$7,IF(ISNUMBER(SEARCH("|",$D14)),SUMIFS('Forecast Engine'!$AM$4:$AM$12,'Forecast Engine'!$A$4:$A$12,LEFT($D14,IFERROR(SEARCH("|",$D14)-1,LEN($D14))),'Forecast Engine'!$B$4:$B$12,MID($D14,IFERROR(SEARCH("|",$D14)+1,LEN($D14)+1),50)),SUMIFS('Forecast Engine'!$AM$4:$AM$12,'Forecast Engine'!$A$4:$A$12,LEFT($D14,IFERROR(SEARCH("|",$D14)-1,LEN($D14))))),0))),0) | H14: =IF(G14<>"",G14,F14) | I14: =IFERROR(H14/F14-1,0)
F15: =IFERROR(IF($E15='Control Panel'!$B$4,IF(ISNUMBER(SEARCH("|",$D15)),SUMIFS('Forecast Engine'!$AK$4:$AK$12,'Forecast Engine'!$A$4:$A$12,LEFT($D15,IFERROR(SEARCH("|",$D15)-1,LEN($D15))),'Forecast Engine'!$B$4:$B$12,MID($D15,IFERROR(SEARCH("|",$D15)+1,LEN($D15)+1),50)),SUMIFS('Forecast Engine'!$AK$4:$AK$12,'Forecast Engine'!$A$4:$A$12,LEFT($D15,IFERROR(SEARCH("|",$D15)-1,LEN($D15))))),IF($E15='Control Panel'!$B$6,IF(ISNUMBER(SEARCH("|",$D15)),SUMIFS('Forecast Engine'!$AL$4:$AL$12,'Forecast Engine'!$A$4:$A$12,LEFT($D15,IFERROR(SEARCH("|",$D15)-1,LEN($D15))),'Forecast Engine'!$B$4:$B$12,MID($D15,IFERROR(SEARCH("|",$D15)+1,LEN($D15)+1),50)),SUMIFS('Forecast Engine'!$AL$4:$AL$12,'Forecast Engine'!$A$4:$A$12,LEFT($D15,IFERROR(SEARCH("|",$D15)-1,LEN($D15))))),IF($E15='Control Panel'!$B$7,IF(ISNUMBER(SEARCH("|",$D15)),SUMIFS('Forecast Engine'!$AM$4:$AM$12,'Forecast Engine'!$A$4:$A$12,LEFT($D15,IFERROR(SEARCH("|",$D15)-1,LEN($D15))),'Forecast Engine'!$B$4:$B$12,MID($D15,IFERROR(SEARCH("|",$D15)+1,LEN($D15)+1),50)),SUMIFS('Forecast Engine'!$AM$4:$AM$12,'Forecast Engine'!$A$4:$A$12,LEFT($D15,IFERROR(SEARCH("|",$D15)-1,LEN($D15))))),0))),0) | H15: =IF(G15<>"",G15,F15) | I15: =IFERROR(H15/F15-1,0)
F16: =IFERROR(IF($E16='Control Panel'!$B$4,IF(ISNUMBER(SEARCH("|",$D16)),SUMIFS('Forecast Engine'!$AK$4:$AK$12,'Forecast Engine'!$A$4:$A$12,LEFT($D16,IFERROR(SEARCH("|",$D16)-1,LEN($D16))),'Forecast Engine'!$B$4:$B$12,MID($D16,IFERROR(SEARCH("|",$D16)+1,LEN($D16)+1),50)),SUMIFS('Forecast Engine'!$AK$4:$AK$12,'Forecast Engine'!$A$4:$A$12,LEFT($D16,IFERROR(SEARCH("|",$D16)-1,LEN($D16))))),IF($E16='Control Panel'!$B$6,IF(ISNUMBER(SEARCH("|",$D16)),SUMIFS('Forecast Engine'!$AL$4:$AL$12,'Forecast Engine'!$A$4:$A$12,LEFT($D16,IFERROR(SEARCH("|",$D16)-1,LEN($D16))),'Forecast Engine'!$B$4:$B$12,MID($D16,IFERROR(SEARCH("|",$D16)+1,LEN($D16)+1),50)),SUMIFS('Forecast Engine'!$AL$4:$AL$12,'Forecast Engine'!$A$4:$A$12,LEFT($D16,IFERROR(SEARCH("|",$D16)-1,LEN($D16))))),IF($E16='Control Panel'!$B$7,IF(ISNUMBER(SEARCH("|",$D16)),SUMIFS('Forecast Engine'!$AM$4:$AM$12,'Forecast Engine'!$A$4:$A$12,LEFT($D16,IFERROR(SEARCH("|",$D16)-1,LEN($D16))),'Forecast Engine'!$B$4:$B$12,MID($D16,IFERROR(SEARCH("|",$D16)+1,LEN($D16)+1),50)),SUMIFS('Forecast Engine'!$AM$4:$AM$12,'Forecast Engine'!$A$4:$A$12,LEFT($D16,IFERROR(SEARCH("|",$D16)-1,LEN($D16))))),0))),0) | H16: =IF(G16<>"",G16,F16) | I16: =IFERROR(H16/F16-1,0)
F17: =IFERROR(IF($E17='Control Panel'!$B$4,IF(ISNUMBER(SEARCH("|",$D17)),SUMIFS('Forecast Engine'!$AK$4:$AK$12,'Forecast Engine'!$A$4:$A$12,LEFT($D17,IFERROR(SEARCH("|",$D17)-1,LEN($D17))),'Forecast Engine'!$B$4:$B$12,MID($D17,IFERROR(SEARCH("|",$D17)+1,LEN($D17)+1),50)),SUMIFS('Forecast Engine'!$AK$4:$AK$12,'Forecast Engine'!$A$4:$A$12,LEFT($D17,IFERROR(SEARCH("|",$D17)-1,LEN($D17))))),IF($E17='Control Panel'!$B$6,IF(ISNUMBER(SEARCH("|",$D17)),SUMIFS('Forecast Engine'!$AL$4:$AL$12,'Forecast Engine'!$A$4:$A$12,LEFT($D17,IFERROR(SEARCH("|",$D17)-1,LEN($D17))),'Forecast Engine'!$B$4:$B$12,MID($D17,IFERROR(SEARCH("|",$D17)+1,LEN($D17)+1),50)),SUMIFS('Forecast Engine'!$AL$4:$AL$12,'Forecast Engine'!$A$4:$A$12,LEFT($D17,IFERROR(SEARCH("|",$D17)-1,LEN($D17))))),IF($E17='Control Panel'!$B$7,IF(ISNUMBER(SEARCH("|",$D17)),SUMIFS('Forecast Engine'!$AM$4:$AM$12,'Forecast Engine'!$A$4:$A$12,LEFT($D17,IFERROR(SEARCH("|",$D17)-1,LEN($D17))),'Forecast Engine'!$B$4:$B$12,MID($D17,IFERROR(SEARCH("|",$D17)+1,LEN($D17)+1),50)),SUMIFS('Forecast Engine'!$AM$4:$AM$12,'Forecast Engine'!$A$4:$A$12,LEFT($D17,IFERROR(SEARCH("|",$D17)-1,LEN($D17))))),0))),0) | H17: =IF(G17<>"",G17,F17) | I17: =IFERROR(H17/F17-1,0)
E19: Total override impact (₹ Cr): | H19: =SUMPRODUCT((G4:G17<>"")*(H4:H17-F4:F17))

Sheet Business_Event_Master
A1: BUSINESS_EVENT_MASTER · one row per business activity (only Approved rows affect forecast)
A2: Enter events at any grain. Incremental demand is computed automatically from % uplift, fixed additional qty, and/or distribution gain (stores × units), weighted by Confidence × Priority × Seasonality and shaped by the ramp/decay curves. Baseline is never overwritten.
A3: Event ID | B3: Event Name | C3: Event Type | D3: Start Month | E3: End Month | F3: Chain | G3: Brand | H3: Category | I3: Article | J3: Region | K3: Zone | L3: State | M3: Distributor | N3: Warehouse | O3: Method | P3: Expected Uplift % | Q3: Additional Qty | R3: New Stores | S3: Units/Store | T3: Confidence % | U3: Priority | V3: Approved By | W3: Status | X3: Family | Y3: idxS | Z3: idxE | AA3: Prio Wt | AB3: Lib Uplift | AC3: Base Uplift | AD3: Eff·M | AE3: Eff·M+1 | AF3: Eff·M+2 | AG3: Abs·M ₹Cr | AH3: Abs·M+1 | AI3: Abs·M+2 | AJ3: ln·M | AK3: ln·M+1 | AL3: ln·M+2 | AM3: Horizon Incr ₹Cr | AN3: Incr Qty
A4: EV01 | B4: Summer Sunscreen NPI (SPF60) | C4: NPI Launch | D4: Jun'26 | E4: Aug'26 | F4: Reliance Retail | G4: Mamaearth | H4: Face | I4: ME Sunscreen SPF60 50g | J4: West | K4: West | L4: Maharashtra | M4: Reliance DC Mumbai | N4: Mumbai | O4: Percentage | T4: 0.85 | U4: Critical | V4: Sales Head | W4: Approved | X4: =IF((ISNUMBER(SEARCH("NPI",C4))+ISNUMBER(SEARCH("Launch",C4))+ISNUMBER(SEARCH("Relaunch",C4))+ISNUMBER(SEARCH("Listing",C4))+ISNUMBER(SEARCH("Distribution",C4))+ISNUMBER(SEARCH("Store",C4))+ISNUMBER(SEARCH("Warehouse",C4))+ISNUMBER(SEARCH("Distributor",C4))+ISNUMBER(SEARCH("Market",C4))+ISNUMBER(SEARCH("Export",C4))+ISNUMBER(SEARCH("Institutional",C4)))>0,"RAMP","DECAY") | Y4: =IFERROR(MATCH(D4,Calendar!$B$3:$B$38,0),0) | Z4: =IFERROR(MATCH(E4,Calendar!$B$3:$B$38,0),Y4) | AA4: =IFERROR(INDEX('Event Settings'!$B$11:$B$14,MATCH(U4,'Event Settings'!$A$11:$A$14,0)),0.5) | AB4: =IFERROR(INDEX('Chain Event Library'!$C$4:$C$19,MATCH(F4&"|"&C4,'Chain Event Library'!$E$4:$E$19,0)),IFERROR(INDEX('Article Event Library'!$C$4:$C$13,MATCH(H4&"|"&C4,'Article Event Library'!$E$4:$E$13,0)),0)) | AC4: =IF(P4<>"",P4,AB4) | AD4: =IF(W4="Approved",1,0)*AC4*T4*AA4*(IFERROR(INDEX('Seasonality Matrix'!$B$4:$M$11,MATCH(H4,'Seasonality Matrix'!$A$4:$A$11,0),MATCH('Control Panel'!$B$12,'Seasonality Matrix'!$B$3:$M$3,0))/IFERROR(INDEX('Seasonality Matrix'!$N$4:$N$11,MATCH(H4,'Seasonality Matrix'!$A$4:$A$11,0)),1),1))*(IF(X4="RAMP",IF('Control Panel'!$B$9-Y4<0,0,INDEX('Event Settings'!$B$18:$B$23,MIN('Control Panel'!$B$9-Y4+1,6))),IF('Control Panel'!$B$9<Y4,0,IF('Control Panel'!$B$9<=Z4,1,IFERROR(INDEX('Event Settings'!$B$27:$B$30,MIN('Control Panel'!$B$9-Z4+1,4)),0))))) | AE4: =IF(W4="Approved",1,0)*AC4*T4*AA4*(IFERROR(INDEX('Seasonality Matrix'!$B$4:$M$11,MATCH(H4,'Seasonality Matrix'!$A$4:$A$11,0),MATCH('Control Panel'!$B$13,'Seasonality Matrix'!$B$3:$M$3,0))/IFERROR(INDEX('Seasonality Matrix'!$N$4:$N$11,MATCH(H4,'Seasonality Matrix'!$A$4:$A$11,0)),1),1))*(IF(X4="RAMP",IF('Control Panel'!$B$10-Y4<0,0,INDEX('Event Settings'!$B$18:$B$23,MIN('Control Panel'!$B$10-Y4+1,6))),IF('Control Panel'!$B$10<Y4,0,IF('Control Panel'!$B$10<=Z4,1,IFERROR(INDEX('Event Settings'!$B$27:$B$30,MIN('Control Panel'!$B$10-Z4+1,4)),0))))) | AF4: =IF(W4="Approved",1,0)*AC4*T4*AA4*(IFERROR(INDEX('Seasonality Matrix'!$B$4:$M$11,MATCH(H4,'Seasonality Matrix'!$A$4:$A$11,0),MATCH('Control Panel'!$B$14,'Seasonality Matrix'!$B$3:$M$3,0))/IFERROR(INDEX('Seasonality Matrix'!$N$4:$N$11,MATCH(H4,'Seasonality Matrix'!$A$4:$A$11,0)),1),1))*(IF(X4="RAMP",IF('Control Panel'!$B$11-Y4<0,0,INDEX('Event Settings'!$B$18:$B$23,MIN('Control Panel'!$B$11-Y4+1,6))),IF('Control Panel'!$B$11<Y4,0,IF('Control Panel'!$B$11<=Z4,1,IFERROR(INDEX('Event Settings'!$B$27:$B$30,MIN('Control Panel'!$B$11-Z4+1,4)),0))))) | AG4: =IF(W4="Approved",1,0)*(Q4*'Event Settings'!$B$4/10000000*(IF('Control Panel'!$B$9=Y4,1,0))+R4*S4*'Event Settings'!$B$4/10000000*(IF(X4="RAMP",IF('Control Panel'!$B$9-Y4<0,0,INDEX('Event Settings'!$B$18:$B$23,MIN('Control Panel'!$B$9-Y4+1,6))),IF('Control Panel'!$B$9<Y4,0,IF('Control Panel'!$B$9<=Z4,1,IFERROR(INDEX('Event Settings'!$B$27:$B$30,MIN('Control Panel'!$B$9-Z4+1,4)),0)))))) | AH4: =IF(W4="Approved",1,0)*(Q4*'Event Settings'!$B$4/10000000*(IF('Control Panel'!$B$10=Y4,1,0))+R4*S4*'Event Settings'!$B$4/10000000*(IF(X4="RAMP",IF('Control Panel'!$B$10-Y4<0,0,INDEX('Event Settings'!$B$18:$B$23,MIN('Control Panel'!$B$10-Y4+1,6))),IF('Control Panel'!$B$10<Y4,0,IF('Control Panel'!$B$10<=Z4,1,IFERROR(INDEX('Event Settings'!$B$27:$B$30,MIN('Control Panel'!$B$10-Z4+1,4)),0)))))) | AI4: =IF(W4="Approved",1,0)*(Q4*'Event Settings'!$B$4/10000000*(IF('Control Panel'!$B$11=Y4,1,0))+R4*S4*'Event Settings'!$B$4/10000000*(IF(X4="RAMP",IF('Control Panel'!$B$11-Y4<0,0,INDEX('Event Settings'!$B$18:$B$23,MIN('Control Panel'!$B$11-Y4+1,6))),IF('Control Panel'!$B$11<Y4,0,IF('Control Panel'!$B$11<=Z4,1,IFERROR(INDEX('Event Settings'!$B$27:$B$30,MIN('Control Panel'!$B$11-Z4+1,4)),0)))))) | AJ4: =IF(AD4>-1,LN(1+AD4),0) | AK4: =IF(AE4>-1,LN(1+AE4),0) | AL4: =IF(AF4>-1,LN(1+AF4),0) | AM4: =SUMIFS('Forecast Engine'!$AK$4:$AK$12,'Forecast Engine'!$A$4:$A$12,G4,'Forecast Engine'!$B$4:$B$12,H4)*AD4+SUMIFS('Forecast Engine'!$AL$4:$AL$12,'Forecast Engine'!$A$4:$A$12,G4,'Forecast Engine'!$B$4:$B$12,H4)*AE4+SUMIFS('Forecast Engine'!$AM$4:$AM$12,'Forecast Engine'!$A$4:$A$12,G4,'Forecast Engine'!$B$4:$B$12,H4)*AF4+AG4+AH4+AI4 | AN4: =IFERROR(AM4*10000000/'Event Settings'!$B$4,0)
A5: EV02 | B5: Summer Seasonal Push | C5: Seasonal Push | D5: Jun'26 | E5: Jul'26 | F5: Reliance Retail | G5: Mamaearth | H5: Face | I5: Sunscreen range | J5: West | K5: West | L5: Maharashtra | M5: Reliance DC Mumbai | N5: Mumbai | O5: Percentage | P5: 0.15 | T5: 0.8 | U5: High | V5: KAM | W5: Approved | X5: =IF((ISNUMBER(SEARCH("NPI",C5))+ISNUMBER(SEARCH("Launch",C5))+ISNUMBER(SEARCH("Relaunch",C5))+ISNUMBER(SEARCH("Listing",C5))+ISNUMBER(SEARCH("Distribution",C5))+ISNUMBER(SEARCH("Store",C5))+ISNUMBER(SEARCH("Warehouse",C5))+ISNUMBER(SEARCH("Distributor",C5))+ISNUMBER(SEARCH("Market",C5))+ISNUMBER(SEARCH("Export",C5))+ISNUMBER(SEARCH("Institutional",C5)))>0,"RAMP","DECAY") | Y5: =IFERROR(MATCH(D5,Calendar!$B$3:$B$38,0),0) | Z5: =IFERROR(MATCH(E5,Calendar!$B$3:$B$38,0),Y5) | AA5: =IFERROR(INDEX('Event Settings'!$B$11:$B$14,MATCH(U5,'Event Settings'!$A$11:$A$14,0)),0.5) | AB5: =IFERROR(INDEX('Chain Event Library'!$C$4:$C$19,MATCH(F5&"|"&C5,'Chain Event Library'!$E$4:$E$19,0)),IFERROR(INDEX('Article Event Library'!$C$4:$C$13,MATCH(H5&"|"&C5,'Article Event Library'!$E$4:$E$13,0)),0)) | AC5: =IF(P5<>"",P5,AB5) | AD5: =IF(W5="Approved",1,0)*AC5*T5*AA5*(IFERROR(INDEX('Seasonality Matrix'!$B$4:$M$11,MATCH(H5,'Seasonality Matrix'!$A$4:$A$11,0),MATCH('Control Panel'!$B$12,'Seasonality Matrix'!$B$3:$M$3,0))/IFERROR(INDEX('Seasonality Matrix'!$N$4:$N$11,MATCH(H5,'Seasonality Matrix'!$A$4:$A$11,0)),1),1))*(IF(X5="RAMP",IF('Control Panel'!$B$9-Y5<0,0,INDEX('Event Settings'!$B$18:$B$23,MIN('Control Panel'!$B$9-Y5+1,6))),IF('Control Panel'!$B$9<Y5,0,IF('Control Panel'!$B$9<=Z5,1,IFERROR(INDEX('Event Settings'!$B$27:$B$30,MIN('Control Panel'!$B$9-Z5+1,4)),0))))) | AE5: =IF(W5="Approved",1,0)*AC5*T5*AA5*(IFERROR(INDEX('Seasonality Matrix'!$B$4:$M$11,MATCH(H5,'Seasonality Matrix'!$A$4:$A$11,0),MATCH('Control Panel'!$B$13,'Seasonality Matrix'!$B$3:$M$3,0))/IFERROR(INDEX('Seasonality Matrix'!$N$4:$N$11,MATCH(H5,'Seasonality Matrix'!$A$4:$A$11,0)),1),1))*(IF(X5="RAMP",IF('Control Panel'!$B$10-Y5<0,0,INDEX('Event Settings'!$B$18:$B$23,MIN('Control Panel'!$B$10-Y5+1,6))),IF('Control Panel'!$B$10<Y5,0,IF('Control Panel'!$B$10<=Z5,1,IFERROR(INDEX('Event Settings'!$B$27:$B$30,MIN('Control Panel'!$B$10-Z5+1,4)),0))))) | AF5: =IF(W5="Approved",1,0)*AC5*T5*AA5*(IFERROR(INDEX('Seasonality Matrix'!$B$4:$M$11,MATCH(H5,'Seasonality Matrix'!$A$4:$A$11,0),MATCH('Control Panel'!$B$14,'Seasonality Matrix'!$B$3:$M$3,0))/IFERROR(INDEX('Seasonality Matrix'!$N$4:$N$11,MATCH(H5,'Seasonality Matrix'!$A$4:$A$11,0)),1),1))*(IF(X5="RAMP",IF('Control Panel'!$B$11-Y5<0,0,INDEX('Event Settings'!$B$18:$B$23,MIN('Control Panel'!$B$11-Y5+1,6))),IF('Control Panel'!$B$11<Y5,0,IF('Control Panel'!$B$11<=Z5,1,IFERROR(INDEX('Event Settings'!$B$27:$B$30,MIN('Control Panel'!$B$11-Z5+1,4)),0))))) | AG5: =IF(W5="Approved",1,0)*(Q5*'Event Settings'!$B$4/10000000*(IF('Control Panel'!$B$9=Y5,1,0))+R5*S5*'Event Settings'!$B$4/10000000*(IF(X5="RAMP",IF('Control Panel'!$B$9-Y5<0,0,INDEX('Event Settings'!$B$18:$B$23,MIN('Control Panel'!$B$9-Y5+1,6))),IF('Control Panel'!$B$9<Y5,0,IF('Control Panel'!$B$9<=Z5,1,IFERROR(INDEX('Event Settings'!$B$27:$B$30,MIN('Control Panel'!$B$9-Z5+1,4)),0)))))) | AH5: =IF(W5="Approved",1,0)*(Q5*'Event Settings'!$B$4/10000000*(IF('Control Panel'!$B$10=Y5,1,0))+R5*S5*'Event Settings'!$B$4/10000000*(IF(X5="RAMP",IF('Control Panel'!$B$10-Y5<0,0,INDEX('Event Settings'!$B$18:$B$23,MIN('Control Panel'!$B$10-Y5+1,6))),IF('Control Panel'!$B$10<Y5,0,IF('Control Panel'!$B$10<=Z5,1,IFERROR(INDEX('Event Settings'!$B$27:$B$30,MIN('Control Panel'!$B$10-Z5+1,4)),0)))))) | AI5: =IF(W5="Approved",1,0)*(Q5*'Event Settings'!$B$4/10000000*(IF('Control Panel'!$B$11=Y5,1,0))+R5*S5*'Event Settings'!$B$4/10000000*(IF(X5="RAMP",IF('Control Panel'!$B$11-Y5<0,0,INDEX('Event Settings'!$B$18:$B$23,MIN('Control Panel'!$B$11-Y5+1,6))),IF('Control Panel'!$B$11<Y5,0,IF('Control Panel'!$B$11<=Z5,1,IFERROR(INDEX('Event Settings'!$B$27:$B$30,MIN('Control Panel'!$B$11-Z5+1,4)),0)))))) | AJ5: =IF(AD5>-1,LN(1+AD5),0) | AK5: =IF(AE5>-1,LN(1+AE5),0) | AL5: =IF(AF5>-1,LN(1+AF5),0) | AM5: =SUMIFS('Forecast Engine'!$AK$4:$AK$12,'Forecast Engine'!$A$4:$A$12,G5,'Forecast Engine'!$B$4:$B$12,H5)*AD5+SUMIFS('Forecast Engine'!$AL$4:$AL$12,'Forecast Engine'!$A$4:$A$12,G5,'Forecast Engine'!$B$4:$B$12,H5)*AE5+SUMIFS('Forecast Engine'!$AM$4:$AM$12,'Forecast Engine'!$A$4:$A$12,G5,'Forecast Engine'!$B$4:$B$12,H5)*AF5+AG5+AH5+AI5 | AN5: =IFERROR(AM5*10000000/'Event Settings'!$B$4,0)
A6: EV03 | B6: Price Drop 10% | C6: Price Drop | D6: Jun'26 | E6: Jun'26 | F6: Reliance Retail | G6: Mamaearth | H6: Face | I6: Sunscreen range | J6: West | K6: West | L6: Maharashtra | M6: Reliance DC Mumbai | N6: Mumbai | O6: Percentage | P6: 0.1 | T6: 0.85 | U6: High | V6: KAM | W6: Approved | X6: =IF((ISNUMBER(SEARCH("NPI",C6))+ISNUMBER(SEARCH("Launch",C6))+ISNUMBER(SEARCH("Relaunch",C6))+ISNUMBER(SEARCH("Listing",C6))+ISNUMBER(SEARCH("Distribution",C6))+ISNUMBER(SEARCH("Store",C6))+ISNUMBER(SEARCH("Warehouse",C6))+ISNUMBER(SEARCH("Distributor",C6))+ISNUMBER(SEARCH("Market",C6))+ISNUMBER(SEARCH("Export",C6))+ISNUMBER(SEARCH("Institutional",C6)))>0,"RAMP","DECAY") | Y6: =IFERROR(MATCH(D6,Calendar!$B$3:$B$38,0),0) | Z6: =IFERROR(MATCH(E6,Calendar!$B$3:$B$38,0),Y6) | AA6: =IFERROR(INDEX('Event Settings'!$B$11:$B$14,MATCH(U6,'Event Settings'!$A$11:$A$14,0)),0.5) | AB6: =IFERROR(INDEX('Chain Event Library'!$C$4:$C$19,MATCH(F6&"|"&C6,'Chain Event Library'!$E$4:$E$19,0)),IFERROR(INDEX('Article Event Library'!$C$4:$C$13,MATCH(H6&"|"&C6,'Article Event Library'!$E$4:$E$13,0)),0)) | AC6: =IF(P6<>"",P6,AB6) | AD6: =IF(W6="Approved",1,0)*AC6*T6*AA6*(IFERROR(INDEX('Seasonality Matrix'!$B$4:$M$11,MATCH(H6,'Seasonality Matrix'!$A$4:$A$11,0),MATCH('Control Panel'!$B$12,'Seasonality Matrix'!$B$3:$M$3,0))/IFERROR(INDEX('Seasonality Matrix'!$N$4:$N$11,MATCH(H6,'Seasonality Matrix'!$A$4:$A$11,0)),1),1))*(IF(X6="RAMP",IF('Control Panel'!$B$9-Y6<0,0,INDEX('Event Settings'!$B$18:$B$23,MIN('Control Panel'!$B$9-Y6+1,6))),IF('Control Panel'!$B$9<Y6,0,IF('Control Panel'!$B$9<=Z6,1,IFERROR(INDEX('Event Settings'!$B$27:$B$30,MIN('Control Panel'!$B$9-Z6+1,4)),0))))) | AE6: =IF(W6="Approved",1,0)*AC6*T6*AA6*(IFERROR(INDEX('Seasonality Matrix'!$B$4:$M$11,MATCH(H6,'Seasonality Matrix'!$A$4:$A$11,0),MATCH('Control Panel'!$B$13,'Seasonality Matrix'!$B$3:$M$3,0))/IFERROR(INDEX('Seasonality Matrix'!$N$4:$N$11,MATCH(H6,'Seasonality Matrix'!$A$4:$A$11,0)),1),1))*(IF(X6="RAMP",IF('Control Panel'!$B$10-Y6<0,0,INDEX('Event Settings'!$B$18:$B$23,MIN('Control Panel'!$B$10-Y6+1,6))),IF('Control Panel'!$B$10<Y6,0,IF('Control Panel'!$B$10<=Z6,1,IFERROR(INDEX('Event Settings'!$B$27:$B$30,MIN('Control Panel'!$B$10-Z6+1,4)),0))))) | AF6: =IF(W6="Approved",1,0)*AC6*T6*AA6*(IFERROR(INDEX('Seasonality Matrix'!$B$4:$M$11,MATCH(H6,'Seasonality Matrix'!$A$4:$A$11,0),MATCH('Control Panel'!$B$14,'Seasonality Matrix'!$B$3:$M$3,0))/IFERROR(INDEX('Seasonality Matrix'!$N$4:$N$11,MATCH(H6,'Seasonality Matrix'!$A$4:$A$11,0)),1),1))*(IF(X6="RAMP",IF('Control Panel'!$B$11-Y6<0,0,INDEX('Event Settings'!$B$18:$B$23,MIN('Control Panel'!$B$11-Y6+1,6))),IF('Control Panel'!$B$11<Y6,0,IF('Control Panel'!$B$11<=Z6,1,IFERROR(INDEX('Event Settings'!$B$27:$B$30,MIN('Control Panel'!$B$11-Z6+1,4)),0))))) | AG6: =IF(W6="Approved",1,0)*(Q6*'Event Settings'!$B$4/10000000*(IF('Control Panel'!$B$9=Y6,1,0))+R6*S6*'Event Settings'!$B$4/10000000*(IF(X6="RAMP",IF('Control Panel'!$B$9-Y6<0,0,INDEX('Event Settings'!$B$18:$B$23,MIN('Control Panel'!$B$9-Y6+1,6))),IF('Control Panel'!$B$9<Y6,0,IF('Control Panel'!$B$9<=Z6,1,IFERROR(INDEX('Event Settings'!$B$27:$B$30,MIN('Control Panel'!$B$9-Z6+1,4)),0)))))) | AH6: =IF(W6="Approved",1,0)*(Q6*'Event Settings'!$B$4/10000000*(IF('Control Panel'!$B$10=Y6,1,0))+R6*S6*'Event Settings'!$B$4/10000000*(IF(X6="RAMP",IF('Control Panel'!$B$10-Y6<0,0,INDEX('Event Settings'!$B$18:$B$23,MIN('Control Panel'!$B$10-Y6+1,6))),IF('Control Panel'!$B$10<Y6,0,IF('Control Panel'!$B$10<=Z6,1,IFERROR(INDEX('Event Settings'!$B$27:$B$30,MIN('Control Panel'!$B$10-Z6+1,4)),0)))))) | AI6: =IF(W6="Approved",1,0)*(Q6*'Event Settings'!$B$4/10000000*(IF('Control Panel'!$B$11=Y6,1,0))+R6*S6*'Event Settings'!$B$4/10000000*(IF(X6="RAMP",IF('Control Panel'!$B$11-Y6<0,0,INDEX('Event Settings'!$B$18:$B$23,MIN('Control Panel'!$B$11-Y6+1,6))),IF('Control Panel'!$B$11<Y6,0,IF('Control Panel'!$B$11<=Z6,1,IFERROR(INDEX('Event Settings'!$B$27:$B$30,MIN('Control Panel'!$B$11-Z6+1,4)),0)))))) | AJ6: =IF(AD6>-1,LN(1+AD6),0) | AK6: =IF(AE6>-1,LN(1+AE6),0) | AL6: =IF(AF6>-1,LN(1+AF6),0) | AM6: =SUMIFS('Forecast Engine'!$AK$4:$AK$12,'Forecast Engine'!$A$4:$A$12,G6,'Forecast Engine'!$B$4:$B$12,H6)*AD6+SUMIFS('Forecast Engine'!$AL$4:$AL$12,'Forecast Engine'!$A$4:$A$12,G6,'Forecast Engine'!$B$4:$B$12,H6)*AE6+SUMIFS('Forecast Engine'!$AM$4:$AM$12,'Forecast Engine'!$A$4:$A$12,G6,'Forecast Engine'!$B$4:$B$12,H6)*AF6+AG6+AH6+AI6 | AN6: =IFERROR(AM6*10000000/'Event Settings'!$B$4,0)
A7: EV04 | B7: Endcap Visibility | C7: Endcap | D7: Jun'26 | E7: Jul'26 | F7: Reliance Retail | G7: Mamaearth | H7: Face | I7: Sunscreen range | J7: West | K7: West | L7: Maharashtra | M7: Reliance DC Mumbai | N7: Mumbai | O7: Percentage | T7: 0.9 | U7: High | V7: Trade Mktg | W7: Approved | X7: =IF((ISNUMBER(SEARCH("NPI",C7))+ISNUMBER(SEARCH("Launch",C7))+ISNUMBER(SEARCH("Relaunch",C7))+ISNUMBER(SEARCH("Listing",C7))+ISNUMBER(SEARCH("Distribution",C7))+ISNUMBER(SEARCH("Store",C7))+ISNUMBER(SEARCH("Warehouse",C7))+ISNUMBER(SEARCH("Distributor",C7))+ISNUMBER(SEARCH("Market",C7))+ISNUMBER(SEARCH("Export",C7))+ISNUMBER(SEARCH("Institutional",C7)))>0,"RAMP","DECAY") | Y7: =IFERROR(MATCH(D7,Calendar!$B$3:$B$38,0),0) | Z7: =IFERROR(MATCH(E7,Calendar!$B$3:$B$38,0),Y7) | AA7: =IFERROR(INDEX('Event Settings'!$B$11:$B$14,MATCH(U7,'Event Settings'!$A$11:$A$14,0)),0.5) | AB7: =IFERROR(INDEX('Chain Event Library'!$C$4:$C$19,MATCH(F7&"|"&C7,'Chain Event Library'!$E$4:$E$19,0)),IFERROR(INDEX('Article Event Library'!$C$4:$C$13,MATCH(H7&"|"&C7,'Article Event Library'!$E$4:$E$13,0)),0)) | AC7: =IF(P7<>"",P7,AB7) | AD7: =IF(W7="Approved",1,0)*AC7*T7*AA7*(IFERROR(INDEX('Seasonality Matrix'!$B$4:$M$11,MATCH(H7,'Seasonality Matrix'!$A$4:$A$11,0),MATCH('Control Panel'!$B$12,'Seasonality Matrix'!$B$3:$M$3,0))/IFERROR(INDEX('Seasonality Matrix'!$N$4:$N$11,MATCH(H7,'Seasonality Matrix'!$A$4:$A$11,0)),1),1))*(IF(X7="RAMP",IF('Control Panel'!$B$9-Y7<0,0,INDEX('Event Settings'!$B$18:$B$23,MIN('Control Panel'!$B$9-Y7+1,6))),IF('Control Panel'!$B$9<Y7,0,IF('Control Panel'!$B$9<=Z7,1,IFERROR(INDEX('Event Settings'!$B$27:$B$30,MIN('Control Panel'!$B$9-Z7+1,4)),0))))) | AE7: =IF(W7="Approved",1,0)*AC7*T7*AA7*(IFERROR(INDEX('Seasonality Matrix'!$B$4:$M$11,MATCH(H7,'Seasonality Matrix'!$A$4:$A$11,0),MATCH('Control Panel'!$B$13,'Seasonality Matrix'!$B$3:$M$3,0))/IFERROR(INDEX('Seasonality Matrix'!$N$4:$N$11,MATCH(H7,'Seasonality Matrix'!$A$4:$A$11,0)),1),1))*(IF(X7="RAMP",IF('Control Panel'!$B$10-Y7<0,0,INDEX('Event Settings'!$B$18:$B$23,MIN('Control Panel'!$B$10-Y7+1,6))),IF('Control Panel'!$B$10<Y7,0,IF('Control Panel'!$B$10<=Z7,1,IFERROR(INDEX('Event Settings'!$B$27:$B$30,MIN('Control Panel'!$B$10-Z7+1,4)),0))))) | AF7: =IF(W7="Approved",1,0)*AC7*T7*AA7*(IFERROR(INDEX('Seasonality Matrix'!$B$4:$M$11,MATCH(H7,'Seasonality Matrix'!$A$4:$A$11,0),MATCH('Control Panel'!$B$14,'Seasonality Matrix'!$B$3:$M$3,0))/IFERROR(INDEX('Seasonality Matrix'!$N$4:$N$11,MATCH(H7,'Seasonality Matrix'!$A$4:$A$11,0)),1),1))*(IF(X7="RAMP",IF('Control Panel'!$B$11-Y7<0,0,INDEX('Event Settings'!$B$18:$B$23,MIN('Control Panel'!$B$11-Y7+1,6))),IF('Control Panel'!$B$11<Y7,0,IF('Control Panel'!$B$11<=Z7,1,IFERROR(INDEX('Event Settings'!$B$27:$B$30,MIN('Control Panel'!$B$11-Z7+1,4)),0))))) | AG7: =IF(W7="Approved",1,0)*(Q7*'Event Settings'!$B$4/10000000*(IF('Control Panel'!$B$9=Y7,1,0))+R7*S7*'Event Settings'!$B$4/10000000*(IF(X7="RAMP",IF('Control Panel'!$B$9-Y7<0,0,INDEX('Event Settings'!$B$18:$B$23,MIN('Control Panel'!$B$9-Y7+1,6))),IF('Control Panel'!$B$9<Y7,0,IF('Control Panel'!$B$9<=Z7,1,IFERROR(INDEX('Event Settings'!$B$27:$B$30,MIN('Control Panel'!$B$9-Z7+1,4)),0)))))) | AH7: =IF(W7="Approved",1,0)*(Q7*'Event Settings'!$B$4/10000000*(IF('Control Panel'!$B$10=Y7,1,0))+R7*S7*'Event Settings'!$B$4/10000000*(IF(X7="RAMP",IF('Control Panel'!$B$10-Y7<0,0,INDEX('Event Settings'!$B$18:$B$23,MIN('Control Panel'!$B$10-Y7+1,6))),IF('Control Panel'!$B$10<Y7,0,IF('Control Panel'!$B$10<=Z7,1,IFERROR(INDEX('Event Settings'!$B$27:$B$30,MIN('Control Panel'!$B$10-Z7+1,4)),0)))))) | AI7: =IF(W7="Approved",1,0)*(Q7*'Event Settings'!$B$4/10000000*(IF('Control Panel'!$B$11=Y7,1,0))+R7*S7*'Event Settings'!$B$4/10000000*(IF(X7="RAMP",IF('Control Panel'!$B$11-Y7<0,0,INDEX('Event Settings'!$B$18:$B$23,MIN('Control Panel'!$B$11-Y7+1,6))),IF('Control Panel'!$B$11<Y7,0,IF('Control Panel'!$B$11<=Z7,1,IFERROR(INDEX('Event Settings'!$B$27:$B$30,MIN('Control Panel'!$B$11-Z7+1,4)),0)))))) | AJ7: =IF(AD7>-1,LN(1+AD7),0) | AK7: =IF(AE7>-1,LN(1+AE7),0) | AL7: =IF(AF7>-1,LN(1+AF7),0) | AM7: =SUMIFS('Forecast Engine'!$AK$4:$AK$12,'Forecast Engine'!$A$4:$A$12,G7,'Forecast Engine'!$B$4:$B$12,H7)*AD7+SUMIFS('Forecast Engine'!$AL$4:$AL$12,'Forecast Engine'!$A$4:$A$12,G7,'Forecast Engine'!$B$4:$B$12,H7)*AE7+SUMIFS('Forecast Engine'!$AM$4:$AM$12,'Forecast Engine'!$A$4:$A$12,G7,'Forecast Engine'!$B$4:$B$12,H7)*AF7+AG7+AH7+AI7 | AN7: =IFERROR(AM7*10000000/'Event Settings'!$B$4,0)
